Workbook

Sheet 00_อ่านก่อน
B2: CI/CD Resource & Compliance Planner
B3: ตารางเครื่องมือ CI/CD ทุกประเภท + การคำนวณทรัพยากรกรณีเครื่องแชร์ + ผลลัพธ์ระยะยาว
B4: Schema 1.2.0 — ใช้เป็นแบบฟอร์มกลางสำหรับประเมินโครงการใด ๆ (ไม่มีข้อมูลเฉพาะโครงการอยู่ในไฟล์นี้)
B6: ชีทในไฟล์นี้
B7: 05_Params | C7: พารามิเตอร์ทั้งหมดของโมเดล — เปลี่ยนโหมด strict/realistic, Scale Factor, OS Reserve, ช่วงเวลาประเมิน (ช่องสีเหลืองคือช่องที่แก้ได้)
B8: 01_Tool_Catalog | C8: ตารางเครื่องมือ 72 รายการ ครบ 6 Stage พร้อม minimum vCPU/RAM/Disk, ที่มาของตัวเลข, มาตรฐานไทย/สากลที่แต่ละเครื่องมือช่วยตอบ, ทางเลือก Enterprise/OSS และข้อควรระวัง
B9: 02_Freq_Weight | C9: ชั้นความถี่การรัน 7 ระดับ และการแปลงเป็นน้ำหนัก 50%-95%
B10: 03_Colocation_Calc | C10: ตารางกำหนดว่าเครื่องมือใดติดตั้งบน VM ใด (ใส่ 1/0) — เป็นช่องกรอกหลัก
B11: 04_VM_Sizing | C11: ผลการคำนวณต่อ VM: เงื่อนไข A / B1 / B2 / C, ค่าที่ต้องจัดสรร, และส่วนต่างกับ spec จริง
B12: 06_Storage_LongTerm | C12: ผลลัพธ์ระยะยาวของพื้นที่จัดเก็บที่ 12 / 24 / 36 / 60 เดือน + สิ่งที่ต้องทำเพื่อคุมการโต
B13: 07_Compliance_Matrix | C13: มาตรการที่ต้องทำ 50 รายการ พร้อมสถานะผ่าน/ไม่ผ่าน และเลขข้อของมาตรฐานที่อ้างแต่ละมาตรการ
B14: 08_Tool_Capability | C14: เมทริกซ์เครื่องมือ x capability (ฐานคำนวณของชีท 07)
B15: 09_Profile_Comparison | C15: เปรียบเทียบประเภทโครงการ 5 แบบ
B16: 10_Archetypes | C16: ผังเครื่องอ้างอิง 4 แบบ (2 / 4 / 6 เครื่อง และ AI/ML) พร้อมชุดเครื่องมือตามบทบาท — ใช้เป็นจุดตั้งต้นของโครงการใหม่
B17: 11_Frameworks | C17: ทะเบียนกฎหมายและมาตรฐาน 48 ฉบับ แยกไทย/สากล พร้อมเมทริกซ์ว่าฉบับใดอ้างมาตรการใด (เลขข้ออยู่ใน comment ของช่อง)
B19: วิธีใช้
B20: ขั้นที่ 1 | C20: เปิดชีท 05_Params เลือกโหมดการคำนวณและ Scale Factor ให้ตรงกับขนาดงานจริง
B21: ขั้นที่ 2 | C21: เลือกผังตั้งต้นจากชีท 10_Archetypes แล้วเปิดชีท 03_Colocation_Calc ใส่ 1 ในคอลัมน์ VM ที่จะติดตั้งเครื่องมือนั้น (VM01-06 ใส่ผังอ้างอิงภาครัฐ 6 เครื่องไว้ให้แล้ว, VM07-10 ว่างสำหรับกรณีอื่น)
B22: ขั้นที่ 3 | C22: ดูผลที่ชีท 04_VM_Sizing — คอลัมน์ 'จัดสรร' คือค่า minimum ที่ต้องขอ และคอลัมน์ 'ผลประเมิน' บอกว่า spec ที่ขอไว้พอหรือไม่
B23: ขั้นที่ 4 | C23: ตรวจ compliance ที่ชีท 07_Compliance_Matrix — ข้อที่ 'ไม่ผ่าน' คือ capability ที่ยังไม่มีเครื่องมือรองรับ
B24: ขั้นที่ 5 | C24: วางแผนพื้นที่จัดเก็บระยะยาวจากชีท 06_Storage_LongTerm
B26: รหัสสีที่ใช้
B27: ตัวเลขสีน้ำเงิน + พื้นเหลือง | C27: ช่องที่ผู้ใช้กรอก/แก้ไขได้
B28: ตัวเลขสีเขียว | C28: สูตรที่อ้างอิงข้ามชีท
B29: ตัวเลขสีดำ | C29: สูตรคำนวณภายในชีทเดียวกัน
B30: พื้นเขียวอ่อน | C30: ผลลัพธ์สุดท้ายที่ต้องนำไปใช้ขอทรัพยากร
B31: พื้นสีตาม Stage | C31: ฟ้า=Stage 1, เหลือง=2, ส้ม=3, เขียว=4, ม่วง=5, พีช=6
B33: ข้อจำกัดที่ต้องรู้ก่อนใช้ตัวเลขนี้
B34: 1 | C34: ตัวเลข minimum เป็นค่าตั้งต้นจากเอกสารติดตั้งของผู้พัฒนาแต่ละเครื่องมือ รวมกับค่าที่พบจากการใช้งานจริงระดับ UAT/Production ขนาดเล็ก ไม่ใช่ผลวัดจากระบบของท่าน — ต้องวัด baseline จริง 2-4 สัปดาห์แล้วปรับ
B35: 2 | C35: โหมด strict (ตามโจทย์) จะได้ค่าสูงกว่าความเป็นจริงในเครื่องที่มีเครื่องมือ ephemeral จำนวนมาก เพราะบวกทุกตัวแม้ในความจริงจะรันเรียงต่อกัน — ใช้ยื่นขอทรัพยากรเพื่อความปลอดภัย และใช้โหมด realistic เพื่อดูค่าที่น่าจะเกิดขึ้นจริง
B36: 3 | C36: ปริมาณข้อมูลต่อวันอ่อนไหวต่อระดับ log และจำนวน build มาก — เปลี่ยน Scale Factor ให้ตรงกับปริมาณจริงก่อนอ่านผลชีท 06
B37: 3.1 | C37: คอลัมน์มาตรฐานในชีท 01 บอกว่าเครื่องมือ 'ช่วยตอบ' ข้อกำหนดใดได้ ไม่ได้รับประกันว่าตั้งค่าถูกต้อง — การผ่านมาตรฐานจริงยังต้องมีการตั้งค่า กระบวนการ และหลักฐานการตรวจสอบประกอบ
B38: 4 | C38: ตารางนี้ไม่ครอบคลุม network bandwidth, IOPS และ license cost ซึ่งต้องประเมินแยก
B39: 5 | C39: License ที่เป็น GPL/AGPL (MinIO, Grafana, Zabbix, FOSSology, Wazuh, testssl.sh) ขัดกับข้อห้ามของโครงการภาครัฐบางแห่ง — ต้องตรวจเงื่อนไขการใช้งานก่อน

Sheet 01_Tool_Catalog
A1: 01 — ตารางเครื่องมือ CI/CD ทุกประเภท + Resource Requirements (Minimum) | C1: 72 เครื่องมือ ครบ 6 Stage ตาม CI/CD Service Blueprint V0.2
A2: tool_id | B2: เครื่องมือ | C2: Stage | D2: หมวด (ขั้นตอนย่อย) | E2: Core/Opt | F2: Grade | G2: License | H2: min vCPU | I2: min RAM (GB) | J2: min Disk OS (GB) | K2: rec vCPU | L2: rec RAM (GB) | M2: rec Disk OS (GB) | N2: Resident 24/7 | O2: Idle RAM (GB) | P2: Conc Group | Q2: freq_id | R2: น้ำหนัก w | S2: Data GB/วัน | T2: Retention (วัน) | U2: Index OH | V2: Growth/ปี | W2: Capabilities ที่ตอบได้ | X2: มาตรฐานไทยที่ช่วยตอบ | Y2: มาตรฐานสากลที่ช่วยตอบ | Z2: มาตรการที่ตอบได้ครบด้วยตัวเอง | AA2: มาตรการที่ช่วยตอบบางส่วน | AB2: จำนวน มาตรการ | AC2: ทางเลือก Enterprise-Grade | AD2: ทางเลือก Open Source อื่น | AE2: ที่มาของตัวเลข Minimum (Sizing Reference) | AF2: ข้อสังเกต / ข้อควรระวังในการวางเครื่อง
A3: gitlab-ce | B3: GitLab Community Edition (Self-hosted Git) | C3: 1 | D3: Git Repository | E3: Core | F3: oss | G3: MIT | H3: 4 | I3: 8 | J3: 40 | K3: 8 | L3: 16 | M3: 200 | N3: 1 | O3: 5 | P3: resident | Q3: resident | R3: =INDEX('02_Freq_Weight'!$E$3:$E$9,MATCH(Q3,'02_Freq_Weight'!$A$3:$A$9,0)) | S3: 0.05 | T3: 3650 | U3: 0.2 | V3: 0.25 | W3: git_scm, webhook, branch_protection, pipeline, audit_trail | X3: พ.ร.บ. คอมพิวเตอร์ 2550/2560; พ.ร.บ. ไซเบอร์ 2562; มาตรฐานข้อมูลเปิดภาครัฐ; พ.ร.บ. ปฏิบัติราชการทางอิเล็กทรอนิกส์ 2565; ขมธอ. ลายมือชื่อ/เอกสารอิเล็กทรอนิกส์; ITA (ป.ป.ช.); มาตรฐานขั้นต่ำ 2566; กรอบมาตรฐานไซเบอร์ 2564; มาตรฐานเว็บไซต์ 2568; PDPA 2562 | Y3: ISO 22301:2019; ISO/IEC 27001:2022; ISO/IEC 27018; ISO/IEC 27701; ISO/IEC 42001:2023; NIST SP 800-53r5; NIST CSF 2.0; NIST SSDF (SP 800-218); OWASP SAMM 2; SLSA v1.0; SOC 2 (TSC) | Z3: C-LOG-AUDIT | AA3: C-LOG-90, C-OPS-BCP, C-SDLC-REVIEW, C-SDLC-TRACE, C-WEB-SELF | AB3: 6 | AC3: GitLab Enterprise Edition; GitHub Enterprise Server; Bitbucket Data Center; Azure DevOps Server | AD3: Gitea; Forgejo; Gogs; Onedev | AE3: GitLab docs: 4 vCPU / 4 GB (แนะนำ 8 GB) รองรับได้ถึง ~500 users; Puma+Sidekiq+Gitaly+PostgreSQL+Redis รวมในเครื่องเดียว | AF3: ทางเลือกหลักของภาครัฐที่ต้องการ Git แบบ On-premise เต็มรูปแบบ กินทรัพยากรมากเพราะรวมหลาย service; ถ้าต้องการเบาให้ใช้ Gitea
A4: gitea | B4: Gitea / Forgejo (Lightweight Git) | C4: 1 | D4: Git Repository | E4: Core | F4: oss | G4: MIT | H4: 1 | I4: 1 | J4: 10 | K4: 2 | L4: 4 | M4: 100 | N4: 1 | O4: 0.5 | P4: resident | Q4: resident | R4: =INDEX('02_Freq_Weight'!$E$3:$E$9,MATCH(Q4,'02_Freq_Weight'!$A$3:$A$9,0)) | S4: 0.02 | T4: 3650 | U4: 0.1 | V4: 0.25 | W4: git_scm, webhook, branch_protection, audit_trail | X4: พ.ร.บ. คอมพิวเตอร์ 2550/2560; พ.ร.บ. ไซเบอร์ 2562; มาตรฐานข้อมูลเปิดภาครัฐ; พ.ร.บ. ปฏิบัติราชการทางอิเล็กทรอนิกส์ 2565; ขมธอ. ลายมือชื่อ/เอกสารอิเล็กทรอนิกส์; ITA (ป.ป.ช.); มาตรฐานขั้นต่ำ 2566; กรอบมาตรฐานไซเบอร์ 2564; มาตรฐานเว็บไซต์ 2568; PDPA 2562 | Y4: ISO 22301:2019; ISO/IEC 27001:2022; ISO/IEC 27018; ISO/IEC 27701; ISO/IEC 42001:2023; NIST SP 800-53r5; NIST CSF 2.0; NIST SSDF (SP 800-218); OWASP SAMM 2; SLSA v1.0; SOC 2 (TSC) | Z4: C-LOG-AUDIT | AA4: C-LOG-90, C-OPS-BCP, C-SDLC-REVIEW, C-SDLC-TRACE, C-WEB-SELF | AB4: 6 | AC4: GitLab Enterprise Edition; GitHub Enterprise Server; Bitbucket Data Center | AE4: Gitea docs: 2 CPU cores / 1 GB RAM เพียงพอสำหรับทีมขนาดเล็ก-กลาง; binary เดียว + SQLite/PostgreSQL | AF4: ตัวเลือกเบาสำหรับเครื่องที่ต้องแชร์กับเครื่องมืออื่น กินแค่ ~300-500 MB RAM ตอน idle
A5: github-actions-runner | B5: GitHub Actions Self-hosted Runner | C5: 1 | D5: Pipeline Orchestration | E5: Core | F5: oss | G5: MIT | H5: 2 | I5: 4 | J5: 60 | K5: 4 | L5: 8 | M5: 150 | N5: 0 | O5: 0.2 | P5: ci_seq | Q5: per_commit | R5: =INDEX('02_Freq_Weight'!$E$3:$E$9,MATCH(Q5,'02_Freq_Weight'!$A$3:$A$9,0)) | S5: 0.6 | T5: 30 | U5: 0.05 | V5: 0.2 | W5: pipeline, webhook, build | X5: มาตรฐานข้อมูลเปิดภาครัฐ; พ.ร.บ. ปฏิบัติราชการทางอิเล็กทรอนิกส์ 2565 | Y5: CIS Benchmarks; NIST SSDF (SP 800-218); OWASP Top 10:2025; SLSA v1.0 | Z5: - | AA5: C-SC-IMG, C-SC-PIN, C-SDLC-TRACE | AB5: 3 | AC5: GitHub Actions Enterprise; GitHub Enterprise Server | AE5: GitHub-hosted standard runner = 2 vCPU / 7 GB / 14 GB SSD — ใช้เป็นเกณฑ์เทียบขั้นต่ำของ self-hosted runner | AF5: รูปแบบที่ประหยัดที่สุดคือให้ Runner ของผู้ให้บริการ Git ทำงานเบา (Lint / Unit Test) แล้วส่ง Webhook เข้า Orchestrator ในองค์กร จึงไม่ต้องใช้ VM ของหน่วยงานในขั้นนี้; ถ้าอยู่หลัง Proxy ต้อง whitelist โดเมนของผู้ให้บริการ (เช่น *.github.com, *.ghcr.io, *.githubusercontent.com)
A6: jenkins-master | B6: Jenkins Master / Controller | C6: 1 | D6: Pipeline Orchestration | E6: Core | F6: oss | G6: MIT | H6: 2 | I6: 4 | J6: 20 | K6: 4 | L6: 8 | M6: 100 | N6: 1 | O6: 2 | P6: resident | Q6: resident | R6: =INDEX('02_Freq_Weight'!$E$3:$E$9,MATCH(Q6,'02_Freq_Weight'!$A$3:$A$9,0)) | S6: 0.15 | T6: 180 | U6: 0.1 | V6: 0.15 | W6: pipeline, webhook, quality_gate, audit_trail, notify | X6: พ.ร.บ. คอมพิวเตอร์ 2550/2560; พ.ร.บ. ไซเบอร์ 2562; มาตรฐานข้อมูลเปิดภาครัฐ; พ.ร.บ. ปฏิบัติราชการทางอิเล็กทรอนิกส์ 2565; ขมธอ. ลายมือชื่อ/เอกสารอิเล็กทรอนิกส์; ITA (ป.ป.ช.); มาตรฐานขั้นต่ำ 2566; กรอบมาตรฐานไซเบอร์ 2564; มาตรฐานเว็บไซต์ 2568; PDPA 2562; ประกาศ PDPC แจ้งเหตุละเมิด 2565 | Y6: ISO 22301:2019; ISO/IEC 27001:2022; ISO/IEC 27018; ISO/IEC 27034; ISO/IEC 27701; ISO/IEC 42001:2023; NIST SP 800-53r5; NIST CSF 2.0; NIST SSDF (SP 800-218); OWASP SAMM 2; OWASP Top 10:2025; SLSA v1.0; SOC 2 (TSC) | Z6: C-LOG-AUDIT | AA6: C-AI-GOV, C-LOG-90, C-LOG-NOTIFY, C-OPS-BCP, C-PRV-BREACH, C-SDLC-REVIEW, C-SDLC-THREAT, C-SDLC-TRACE, C-WEB-SELF | AB6: 10 | AC6: CloudBees CI; Jenkins Enterprise; Azure DevOps Server; GitLab Ultimate Self-Managed | AD6: Argo Workflows; Tekton Pipelines; Woodpecker CI; Drone CI; Concourse CI | AE6: Jenkins docs: absolute min 256 MB RAM / 1 GB disk; 'small team' 1 GB+ RAM / 50 GB disk — ภาครัฐที่ลง plugin RBAC/Audit/Pipeline ควรเริ่ม 2 vCPU / 4 GB (JVM heap 2 GB) | AF6: ห้ามรัน Build บน Master (Controller) — ให้สั่ง Agent เท่านั้น เพื่อกัน Master ล่มและกันช่องโหว่ Script Approval
A7: jenkins-agent | B7: Jenkins Agent / Build Executor (ต่อ 1 Executor) | C7: 1 | D7: Pipeline Orchestration | E7: Core | F7: oss | G7: MIT | H7: 2 | I7: 4 | J7: 60 | K7: 4 | L7: 8 | M7: 200 | N7: 0 | O7: 0.3 | P7: resident | Q7: per_commit | R7: =INDEX('02_Freq_Weight'!$E$3:$E$9,MATCH(Q7,'02_Freq_Weight'!$A$3:$A$9,0)) | S7: 0.8 | T7: 7 | U7: 0.05 | V7: 0.2 | W7: pipeline, build, unit_test | X7: มาตรฐานข้อมูลเปิดภาครัฐ; พ.ร.บ. ปฏิบัติราชการทางอิเล็กทรอนิกส์ 2565 | Y7: CIS Benchmarks; ISO/IEC 25010:2023; ISO/IEC 27001:2022; ISO/IEC 27034; NIST SSDF (SP 800-218); OWASP Top 10:2025; SLSA v1.0 | Z7: - | AA7: C-SC-IMG, C-SC-PIN, C-SDLC-QUALITY, C-SDLC-TEST, C-SDLC-TRACE | AB7: 5 | AC7: CloudBees CI Agent; Azure Pipelines Agent | AE7: 1 Executor = 1 build พร้อมกัน; ประสบการณ์ทั่วไป 1 vCPU + 2 GB ต่อ executor เป็นขั้นต่ำ, 2 vCPU + 4 GB เมื่อ build Java/Node ที่มี dependency มาก | AF7: จำนวน Executor = จำนวน build ที่รันขนานได้ ให้คำนวณ vCPU/RAM แบบคูณจำนวน executor; Workspace ควรมี disk 60-200 GB และตั้ง cleanup ทุกรอบ
A8: argo-workflows | B8: Argo Workflows (CNCF Graduated) | C8: 1 | D8: Pipeline Orchestration | E8: Core | F8: oss | G8: Apache-2.0 | H8: 1 | I8: 2 | J8: 10 | K8: 2 | L8: 4 | M8: 40 | N8: 1 | O8: 1 | P8: resident | Q8: resident | R8: =INDEX('02_Freq_Weight'!$E$3:$E$9,MATCH(Q8,'02_Freq_Weight'!$A$3:$A$9,0)) | S8: 0.15 | T8: 90 | U8: 0.1 | V8: 0.2 | W8: pipeline, webhook, audit_trail | X8: พ.ร.บ. คอมพิวเตอร์ 2550/2560; พ.ร.บ. ไซเบอร์ 2562; มาตรฐานข้อมูลเปิดภาครัฐ; พ.ร.บ. ปฏิบัติราชการทางอิเล็กทรอนิกส์ 2565; ขมธอ. ลายมือชื่อ/เอกสารอิเล็กทรอนิกส์; ITA (ป.ป.ช.); มาตรฐานขั้นต่ำ 2566; กรอบมาตรฐานไซเบอร์ 2564; มาตรฐานเว็บไซต์ 2568; PDPA 2562 | Y8: ISO 22301:2019; ISO/IEC 27001:2022; ISO/IEC 27018; ISO/IEC 27701; ISO/IEC 42001:2023; NIST SP 800-53r5; NIST CSF 2.0; NIST SSDF (SP 800-218); SLSA v1.0; SOC 2 (TSC) | Z8: C-LOG-AUDIT | AA8: C-LOG-90, C-OPS-BCP, C-SDLC-TRACE, C-WEB-SELF | AB8: 5 | AC8: Azure DevOps; CloudBees CI; Harness | AE8: Argo Workflows controller ทั่วไปตั้ง request 100m CPU / 128Mi และ limit ~500m / 1Gi; ต้องมี Kubernetes อยู่แล้ว | AF8: เหมาะเมื่อมี Kubernetes แล้ว — เบากว่า Jenkins มาก แต่ต้องนับ resource ของ K8s control plane เพิ่ม
A9: opa-conftest | B9: Open Policy Agent / Conftest (Policy-as-Code Gate) | C9: 1 | D9: Branch Protection | E9: Optional | F9: oss | G9: Apache-2.0 | H9: 1 | I9: 1 | J9: 5 | K9: 1 | L9: 2 | M9: 10 | N9: 0 | O9: 0 | P9: ci_seq | Q9: per_pr | R9: =INDEX('02_Freq_Weight'!$E$3:$E$9,MATCH(Q9,'02_Freq_Weight'!$A$3:$A$9,0)) | S9: 0.01 | T9: 90 | U9: 0.05 | V9: 0.1 | W9: branch_protection, iac_scan, quality_gate | X9: มาตรฐานคลาวด์ 2567 | Y9: CIS Benchmarks; ISO/IEC 27001:2022; ISO/IEC 27034; ISO/IEC 42001:2023; NIST SSDF (SP 800-218); OWASP SAMM 2; OWASP Top 10:2025; SOC 2 (TSC) | Z9: C-OPS-IAC | AA9: C-AI-GOV, C-SDLC-REVIEW, C-SDLC-THREAT | AB9: 4 | AC9: GitHub Enterprise Branch Protection; GitLab Premium Protected Branches; Azure Branch Policies | AE9: OPA binary เดียว ใช้ RAM หลักสิบ MB ตอนประเมิน policy; ค่าขั้นต่ำ 1 vCPU / 1 GB คือการกันที่ให้ container | AF9: ใช้บังคับกฎ 'ต้องมี 2 Approvers' และตรวจ Terraform/K8s YAML ก่อน Merge ตาม CORE-R1
A10: nginx-gateway | B10: Nginx (Reverse Proxy / Webhook Relay) | C10: 1 | D10: Webhook Trigger | E10: Core | F10: oss | G10: BSD-2 | H10: 1 | I10: 1 | J10: 10 | K10: 2 | L10: 4 | M10: 40 | N10: 1 | O10: 0.3 | P10: resident | Q10: resident | R10: =INDEX('02_Freq_Weight'!$E$3:$E$9,MATCH(Q10,'02_Freq_Weight'!$A$3:$A$9,0)) | S10: 0.1 | T10: 90 | U10: 0.1 | V10: 0.2 | W10: webhook, tls_check | X10: มสพร. 11-2566 เว็บไซต์ภาครัฐ 3.0; มาตรฐานข้อมูลเปิดภาครัฐ; พ.ร.บ. ปฏิบัติราชการทางอิเล็กทรอนิกส์ 2565; ขมธอ. ความมั่นคงปลอดภัยสารสนเทศ; มาตรฐานเว็บไซต์ 2568; PDPA 2562; ประกาศ PDPC มาตรการความปลอดภัย 2565; พ.ร.ฎ. วิธีการแบบปลอดภัย 2553 | Y10: CycloneDX / ECMA-424; ISO/IEC 27018; ISO/IEC 27701; ISO/IEC 29100; NIST PQC Migration; NIST SSDF (SP 800-218); OWASP Top 10:2025; PCI DSS v4.0; SLSA v1.0 | Z10: C-CRY-TLS | AA10: C-CRY-PQC, C-PRV-MEASURE, C-SDLC-TRACE | AB10: 4 | AC10: F5 BIG-IP; Azure Application Gateway; AWS ALB | AE10: Nginx worker กิน RAM หลักสิบ MB ต่อ worker; 1 vCPU / 1 GB รองรับหลักพัน req/s ของ webhook ได้ | AF10: โดยทั่วไปวาง Reverse Proxy แยกเครื่อง (2 vCPU / 4 GB เพียงพอสำหรับ traffic ระดับหน่วยงาน); บนเครื่อง CI ใช้เพียง relay webhook ผ่าน Proxy Whitelist จึงกินทรัพยากรน้อยมาก
A11: sonarqube | B11: SonarQube Community Edition | C11: 2 | D11: SAST + Code Quality | E11: Core | F11: oss | G11: LGPL-3.0 | H11: 2 | I11: 4 | J11: 30 | K11: 4 | L11: 8 | M11: 100 | N11: 1 | O11: 3.5 | P11: resident | Q11: resident | R11: =INDEX('02_Freq_Weight'!$E$3:$E$9,MATCH(Q11,'02_Freq_Weight'!$A$3:$A$9,0)) | S11: 0.1 | T11: 365 | U11: 0.3 | V11: 0.2 | W11: sast, code_quality, quality_gate | X11: ขมธอ. ความมั่นคงปลอดภัยสารสนเทศ; มาตรฐานเว็บไซต์ 2568 | Y11: CIS Controls v8.1; ISO/IEC 25010:2023; ISO/IEC 27001:2022; ISO/IEC 27002:2022; ISO/IEC 27034; ISO/IEC 42001:2023; NIST SP 800-53r5; NIST SSDF (SP 800-218); OWASP API Top 10:2023; OWASP ASVS 5.0; OWASP MASVS; OWASP SAMM 2; OWASP Top 10:2025; PCI DSS v4.0; SOC 2 (TSC) | Z11: C-APP-ERROR, C-SDLC-SAST, C-SDLC-THREAT | AA11: C-AI-GOV, C-APP-ACCESS, C-APP-INJECT, C-SDLC-QUALITY, C-SDLC-REVIEW | AB11: 8 | AC11: SonarQube Enterprise; Checkmarx SAST; Fortify SCA; Veracode Static Analysis | AD11: Semgrep; SpotBugs; Bandit; gosec; Brakeman; ESLint Security | AE11: SonarQube docs: ขั้นต่ำ 2 GB RAM ว่างสำหรับ server + 1 GB สำหรับ OS; ตัว server รัน 3 process (Web + Compute Engine + Elasticsearch) จึงควรมี 4 GB ขึ้นไป และตั้ง vm.max_map_count=524288 | AF11: เป็นหัวใจของ Quality Gate; ต้องมี PostgreSQL แยก (ห้ามใช้ embedded H2 ใน production) และมี Embedded Elasticsearch อยู่ในตัว ทำให้ RAM เป็นค่าคงค้างตลอดเวลา ไม่ใช่ค่าชั่วคราว — เป็นเหตุผลหลักที่เครื่อง Orchestrator มักต้องการ RAM มากกว่าที่ประเมินไว้ตอนแรก
A12: postgresql-tools | B12: PostgreSQL (ฐานข้อมูลของเครื่องมือ CI/CD) | C12: 2 | D12: Supporting Database | E12: Core | F12: oss | G12: PostgreSQL License | H12: 2 | I12: 4 | J12: 20 | K12: 4 | L12: 8 | M12: 100 | N12: 1 | O12: 3 | P12: resident | Q12: resident | R12: =INDEX('02_Freq_Weight'!$E$3:$E$9,MATCH(Q12,'02_Freq_Weight'!$A$3:$A$9,0)) | S12: 0.05 | T12: 2555 | U12: 0.35 | V12: 0.2 | W12: audit_trail | X12: พ.ร.บ. คอมพิวเตอร์ 2550/2560; พ.ร.บ. ไซเบอร์ 2562; มาตรฐานข้อมูลเปิดภาครัฐ; พ.ร.บ. ปฏิบัติราชการทางอิเล็กทรอนิกส์ 2565; ขมธอ. ลายมือชื่อ/เอกสารอิเล็กทรอนิกส์; ITA (ป.ป.ช.); มาตรฐานขั้นต่ำ 2566; กรอบมาตรฐานไซเบอร์ 2564; มาตรฐานเว็บไซต์ 2568; PDPA 2562 | Y12: ISO 22301:2019; ISO/IEC 27001:2022; ISO/IEC 27018; ISO/IEC 27701; ISO/IEC 42001:2023; NIST SP 800-53r5; NIST CSF 2.0; NIST SSDF (SP 800-218); SLSA v1.0; SOC 2 (TSC) | Z12: C-LOG-AUDIT | AA12: C-LOG-90, C-OPS-BCP, C-SDLC-TRACE, C-WEB-SELF | AB12: 5 | AC12: Azure Database for PostgreSQL; AWS RDS; Oracle Database | AE12: PostgreSQL ทำงานได้ที่ 1 GB แต่ shared_buffers 25% ของ RAM + work_mem ต่อ connection ทำให้ 4 GB เป็นค่าที่ปลอดภัยเมื่อรองรับ SonarQube + Jenkins | AF12: SonarQube ต้องมี PostgreSQL แยก (ห้ามใช้ embedded H2 ใน production); ถ้าเก็บ Audit Trail 7 ปีตามภาครัฐ ต้องวางแผน partition + archive
A13: semgrep | B13: Semgrep (SAST แบบ Rule-based) | C13: 2 | D13: SAST | E13: Core | F13: oss | G13: LGPL-2.1 | H13: 2 | I13: 4 | J13: 5 | K13: 4 | L13: 8 | M13: 20 | N13: 0 | O13: 0 | P13: ci_seq | Q13: per_commit | R13: =INDEX('02_Freq_Weight'!$E$3:$E$9,MATCH(Q13,'02_Freq_Weight'!$A$3:$A$9,0)) | S13: 0.02 | T13: 180 | U13: 0.05 | V13: 0.15 | W13: sast | X13: ขมธอ. ความมั่นคงปลอดภัยสารสนเทศ; มาตรฐานเว็บไซต์ 2568 | Y13: CIS Controls v8.1; ISO/IEC 27002:2022; ISO/IEC 27034; NIST SP 800-53r5; NIST SSDF (SP 800-218); OWASP API Top 10:2023; OWASP ASVS 5.0; OWASP MASVS; OWASP SAMM 2; OWASP Top 10:2025; PCI DSS v4.0 | Z13: C-SDLC-SAST | AA13: C-APP-ACCESS, C-APP-ERROR, C-APP-INJECT | AB13: 4 | AC13: Semgrep Enterprise; Checkmarx SAST; Fortify SCA; CodeQL (GitHub Advanced Security) | AE13: Semgrep แนะนำ ~4 GB RAM สำหรับ repo ขนาดกลาง; RAM ขึ้นกับขนาดไฟล์ที่ใหญ่สุด ไม่ใช่จำนวนไฟล์ | AF13: เร็วกว่า SonarQube หลายเท่า เหมาะรันทุก commit เป็น Fast Gate แล้วปล่อย SonarQube รันรอบ nightly
A14: gitleaks | B14: GitLeaks / TruffleHog (Secret Scanning) | C14: 2 | D14: Secret Scanning | E14: Core | F14: oss | G14: MIT | H14: 1 | I14: 2 | J14: 3 | K14: 2 | L14: 4 | M14: 10 | N14: 0 | O14: 0 | P14: ci_seq | Q14: per_commit | R14: =INDEX('02_Freq_Weight'!$E$3:$E$9,MATCH(Q14,'02_Freq_Weight'!$A$3:$A$9,0)) | S14: 0.01 | T14: 365 | U14: 0.05 | V14: 0.1 | W14: secret_scan | X14: PDPA 2562 | Y14: ISO/IEC 27002:2022; ISO/IEC 27018; ISO/IEC 27701; ISO/IEC 29100 | Z14: - | AA14: C-PRV-MINIMIZE, C-SDLC-SECRET | AB14: 2 | AC14: GitHub Advanced Security Secret Scanning; GitLab Ultimate Secret Detection; HashiCorp Vault Radar | AE14: GitLeaks เป็น Go binary สแกน git history ด้วย regex/entropy; RAM ~200-500 MB ต่อ repo ขนาดกลาง | AF14: ต้องตั้งเป็น Blocking Gate (พบ = หยุด Pipeline) ตาม PDPA-R3; ควรติดตั้ง pre-commit hook ที่ฝั่ง Developer ด้วย
A15: dependency-check | B15: OWASP Dependency-Check (SCA) | C15: 2 | D15: Software Composition Analysis | E15: Optional | F15: oss | G15: Apache-2.0 | H15: 2 | I15: 4 | J15: 15 | K15: 4 | L15: 8 | M15: 40 | N15: 0 | O15: 0.5 | P15: async | Q15: nightly | R15: =INDEX('02_Freq_Weight'!$E$3:$E$9,MATCH(Q15,'02_Freq_Weight'!$A$3:$A$9,0)) | S15: 0.05 | T15: 365 | U15: 0.1 | V15: 0.15 | W15: sca, sbom | X15: มาตรฐานขั้นต่ำ 2566 | Y15: CIS Controls v8.1; CSA CCM v4 / STAR; CycloneDX / ECMA-424; ISO/IEC 27002:2022; NIST SP 800-161r1; NIST SSDF (SP 800-218); OWASP Top 10:2025; PCI DSS v4.0; SLSA v1.0; SPDX / ISO 5962 | Z15: C-SC-SBOM, C-SC-SCA | AA15: - | AB15: 2 | AC15: Snyk Enterprise; BlackDuck (Synopsys); JFrog Xray; Sonatype Nexus Lifecycle; Mend (WhiteSource) | AD15: Trivy; Grype (Anchore); Dependency-Track; OSV-Scanner | AE15: Dependency-Check ต้องดาวน์โหลดและ cache NVD CVE Database (~2-8 GB) และแนะนำ JVM heap 4 GB; รอบแรกใช้เวลา 20-60 นาที | AF15: ควรย้ายไปรันรอบ nightly เพราะช้า และตั้ง NVD_API_KEY + local mirror เพื่อรองรับ Air-gapped ตามภาครัฐ
A16: trivy | B16: Trivy (SCA + Container + IaC + Secret ในตัวเดียว) | C16: 2 | D16: Multi-purpose Scanner | E16: Core | F16: oss | G16: Apache-2.0 | H16: 2 | I16: 2 | J16: 10 | K16: 2 | L16: 4 | M16: 30 | N16: 0 | O16: 0 | P16: ci_seq | Q16: per_build | R16: =INDEX('02_Freq_Weight'!$E$3:$E$9,MATCH(Q16,'02_Freq_Weight'!$A$3:$A$9,0)) | S16: 0.03 | T16: 365 | U16: 0.05 | V16: 0.15 | W16: sca, container_scan, iac_scan, secret_scan, sbom | X16: มาตรฐานคลาวด์ 2567; มาตรฐานขั้นต่ำ 2566; PDPA 2562 | Y16: CIS Benchmarks; CIS Controls v8.1; CSA CCM v4 / STAR; CycloneDX / ECMA-424; ISO/IEC 27002:2022; ISO/IEC 27018; ISO/IEC 27701; ISO/IEC 29100; NIST SP 800-161r1; NIST SSDF (SP 800-218); OWASP Top 10:2025; PCI DSS v4.0; SLSA v1.0; SPDX / ISO 5962 | Z16: C-OPS-IAC, C-SC-CONTAINER, C-SC-SBOM, C-SC-SCA | AA16: C-PRV-MINIMIZE, C-SDLC-SECRET | AB16: 6 | AC16: Aqua Container Security; Prisma Cloud (Twistlock); Snyk Container; JFrog Xray | AE16: Trivy เป็น Go binary; vulnerability DB cache ~1-3 GB, Java DB เพิ่มอีก ~1-2 GB; RAM ปกติ < 1 GB แต่ image ใหญ่อาจถึง 2 GB | AF16: คุ้มค่าที่สุดต่อ resource เพราะทำได้ 5 หน้าที่ในตัวเดียว ลดจำนวนเครื่องมือที่ต้องแชร์เครื่อง — แนะนำเป็นตัวหลักเมื่อ VM จำกัด
A17: fossology | B17: FOSSology / ScanCode (License Compliance) | C17: 2 | D17: License Compliance | E17: Optional | F17: oss | G17: GPL-2.0 | H17: 4 | I17: 8 | J17: 30 | K17: 4 | L17: 8 | M17: 100 | N17: 1 | O17: 2 | P17: resident | Q17: weekly | R17: =INDEX('02_Freq_Weight'!$E$3:$E$9,MATCH(Q17,'02_Freq_Weight'!$A$3:$A$9,0)) | S17: 0.05 | T17: 730 | U17: 0.2 | V17: 0.1 | W17: license | X17: - | Y17: ISO/IEC 27001:2022; NIST SP 800-161r1; SPDX / ISO 5962 | Z17: C-SC-LICENSE | AA17: - | AB17: 1 | AC17: BlackDuck License Compliance; FOSSA Enterprise; Mend (WhiteSource); Snyk License | AD17: ScanCode Toolkit; License Finder; Licensee; REUSE | AE17: FOSSology เป็น web app + PostgreSQL + scheduler; เอกสารแนะนำ 4 GB RAM ขึ้นไป และ CPU มากขึ้นตามจำนวน agent ที่รันขนาน | AF17: ภาครัฐบังคับ 'ห้ามใช้ GPL/AGPL' — ควรรัน ScanCode Toolkit (เบากว่า, ephemeral) ทุก build และเก็บ FOSSology ไว้ทำ audit รายสัปดาห์แทน
A18: linters | B18: Linters (ESLint / Pylint / golangci-lint / RuboCop) | C18: 2 | D18: Code Quality | E18: Optional | F18: oss | G18: MIT | H18: 1 | I18: 2 | J18: 3 | K18: 2 | L18: 4 | M18: 10 | N18: 0 | O18: 0 | P18: ci_seq | Q18: per_commit | R18: =INDEX('02_Freq_Weight'!$E$3:$E$9,MATCH(Q18,'02_Freq_Weight'!$A$3:$A$9,0)) | S18: 0.01 | T18: 90 | U18: 0.05 | V18: 0.1 | W18: code_quality | X18: - | Y18: ISO/IEC 25010:2023; ISO/IEC 27001:2022; ISO/IEC 27034; OWASP ASVS 5.0; OWASP MASVS; OWASP SAMM 2; OWASP Top 10:2025 | Z18: - | AA18: C-APP-ERROR, C-SDLC-QUALITY, C-SDLC-THREAT | AB18: 3 | AC18: SonarQube Enterprise; CodeClimate Enterprise; Codacy Enterprise | AE18: Linter ทำงานใน process เดียว ใช้ RAM 200 MB - 1 GB ตามขนาด codebase; golangci-lint อาจถึง 2 GB บน monorepo | AF18: ควรรันบน Runner ของผู้ให้บริการ Git ก่อนส่ง Webhook เข้า Orchestrator ในองค์กร เพื่อไม่กินทรัพยากร VM ที่หน่วยงานต้องจัดหาเอง
A19: maven-gradle | B19: Maven / Gradle / npm / pip (Build & Compilation) | C19: 3 | D19: Build & Compilation | E19: Core | F19: oss | G19: Apache-2.0 | H19: 2 | I19: 4 | J19: 40 | K19: 4 | L19: 8 | M19: 120 | N19: 0 | O19: 0 | P19: ci_seq | Q19: per_commit | R19: =INDEX('02_Freq_Weight'!$E$3:$E$9,MATCH(Q19,'02_Freq_Weight'!$A$3:$A$9,0)) | S19: 0.3 | T19: 30 | U19: 0.05 | V19: 0.2 | W19: build | X19: - | Y19: CIS Benchmarks; NIST SSDF (SP 800-218); OWASP Top 10:2025; SLSA v1.0 | Z19: - | AA19: C-SC-IMG, C-SC-PIN | AB19: 2 | AC19: JFrog Artifactory (with Maven/Gradle); Azure DevOps Build; AWS CodeBuild; CloudBees Build | AE19: Gradle daemon ตั้ง heap 1-2 GB โดยปริยาย; Maven fork JVM ต่อ module; local cache ~/.m2 หรือ ~/.gradle โต 5-20 GB และ node_modules 1-3 GB ต่อโปรเจกต์ | AF19: อย่าลืมกัน disk ให้ dependency cache — เป็นสาเหตุ 'disk full' อันดับ 1 บนเครื่อง Agent; ควรตั้ง cache cleanup รายสัปดาห์
A20: docker-buildkit | B20: Docker Engine / BuildKit (Container Image Builder) | C20: 3 | D20: Container Image Builder | E20: Core | F20: oss | G20: Apache-2.0 | H20: 2 | I20: 4 | J20: 100 | K20: 4 | L20: 8 | M20: 300 | N20: 1 | O20: 0.5 | P20: ci_seq | Q20: per_commit | R20: =INDEX('02_Freq_Weight'!$E$3:$E$9,MATCH(Q20,'02_Freq_Weight'!$A$3:$A$9,0)) | S20: 2 | T20: 21 | U20: 0.1 | V20: 0.2 | W20: image_build, build | X20: - | Y20: CIS Benchmarks; NIST SSDF (SP 800-218); OWASP Top 10:2025; SLSA v1.0 | Z20: C-SC-IMG | AA20: C-SC-PIN | AB20: 2 | AC20: Google Cloud Build; Azure Container Registry Build; Red Hat Quay Build; AWS CodeBuild | AD20: Kaniko; Buildah; Podman; Cloud Native Buildpacks; img; ko | AE20: Docker daemon idle ~200-400 MB; multi-stage build ของ Java/Node ใช้ 2-4 GB ตอน compile layer; image layer cache เป็นตัวกิน disk หลัก | AF20: จุดเสี่ยงหลักคือ Disk ไม่ใช่ RAM — layer cache + dangling image โต 2-5 GB/วัน ต้องตั้ง `docker system prune` เป็น cron; ถ้าต้องการ Rootless Build ตามข้อกำหนดภาครัฐให้ใช้ Kaniko/Buildah แทน
A21: checkov | B21: Checkov / tfsec / KubeLinter (IaC Validation) | C21: 3 | D21: IaC Validation | E21: Optional | F21: oss | G21: Apache-2.0 | H21: 1 | I21: 2 | J21: 5 | K21: 2 | L21: 4 | M21: 15 | N21: 0 | O21: 0 | P21: ci_seq | Q21: per_build | R21: =INDEX('02_Freq_Weight'!$E$3:$E$9,MATCH(Q21,'02_Freq_Weight'!$A$3:$A$9,0)) | S21: 0.01 | T21: 365 | U21: 0.05 | V21: 0.1 | W21: iac_scan | X21: มาตรฐานคลาวด์ 2567 | Y21: CIS Benchmarks; OWASP Top 10:2025 | Z21: C-OPS-IAC | AA21: - | AB21: 1 | AC21: Prisma Cloud IaC Scanning; Snyk IaC Enterprise; Bridgecrew | AE21: Checkov เป็น Python CLI ใช้ RAM 300 MB - 1.5 GB ตามจำนวนไฟล์ Terraform/K8s; ephemeral ทั้งหมด | AF21: ภาครัฐกำหนดเป็น Mandatory (ตาม OWASP A02 + CLOUD2567-R1) — ตรวจ Security Group เปิดกว้าง, ไม่มี Resource Limits, ไม่ได้เข้ารหัส Volume
A22: cosign | B22: Sigstore Cosign / Notary v2 (Artifact Signing) | C22: 3 | D22: Artifact Signing | E22: Optional | F22: oss | G22: Apache-2.0 | H22: 1 | I22: 2 | J22: 5 | K22: 1 | L22: 2 | M22: 10 | N22: 0 | O22: 0 | P22: ci_seq | Q22: per_build | R22: =INDEX('02_Freq_Weight'!$E$3:$E$9,MATCH(Q22,'02_Freq_Weight'!$A$3:$A$9,0)) | S22: 0.01 | T22: 2555 | U22: 0.05 | V22: 0.1 | W22: artifact_sign | X22: ขมธอ. ลายมือชื่อ/เอกสารอิเล็กทรอนิกส์ | Y22: ISO/IEC 42001:2023; NIST SP 800-161r1; NIST SSDF (SP 800-218); OWASP Top 10:2025; SLSA v1.0 | Z22: C-SC-SIGN | AA22: C-AI-GOV | AB22: 2 | AC22: Azure Code Signing; AWS Signer; Venafi CodeSign Protect; Google Binary Authorization | AE22: Cosign เป็น Go binary ใช้ RAM < 300 MB; ต้องมีที่เก็บ key อย่างปลอดภัย (KMS/Vault) และ Rekor transparency log ถ้าต้องการ | AF22: ภาครัฐกำหนด Mandatory ตาม OWASP A08 + NIST SSDF — ต้อง Verify signature ก่อน Pull มา Deploy ทุกครั้ง ไม่ใช่แค่ Sign
A23: syft | B23: Syft / CycloneDX CLI (SBOM Generation) | C23: 3 | D23: SBOM | E23: Optional | F23: oss | G23: Apache-2.0 | H23: 1 | I23: 2 | J23: 5 | K23: 2 | L23: 4 | M23: 20 | N23: 0 | O23: 0 | P23: ci_seq | Q23: per_build | R23: =INDEX('02_Freq_Weight'!$E$3:$E$9,MATCH(Q23,'02_Freq_Weight'!$A$3:$A$9,0)) | S23: 0.02 | T23: 2555 | U23: 0.05 | V23: 0.15 | W23: sbom | X23: มาตรฐานขั้นต่ำ 2566 | Y23: CSA CCM v4 / STAR; CycloneDX / ECMA-424; NIST SP 800-161r1; NIST SSDF (SP 800-218); OWASP Top 10:2025; SLSA v1.0; SPDX / ISO 5962 | Z23: C-SC-SBOM | AA23: - | AB23: 1 | AC23: JFrog Xray SBOM; Snyk SBOM; BlackDuck SBOM; Google Cloud SBOM | AE23: Syft สแกน image layer สร้าง SBOM; RAM ~500 MB - 2 GB ตามขนาด image; ไฟล์ SBOM 1-10 MB ต่อ artifact | AF23: ภาครัฐกำหนด Mandatory ตาม OWASP A03 + NIST SP 800-161; SBOM ต้องเก็บคู่กับ artifact และเก็บนานเท่ากับอายุการใช้งานระบบ (7+ ปี)
A24: unit-test-runner | B24: pytest / Jest / JUnit / Go test (Unit Test) | C24: 4 | D24: Unit Test | E24: Core | F24: oss | G24: MIT | H24: 2 | I24: 4 | J24: 20 | K24: 4 | L24: 8 | M24: 60 | N24: 0 | O24: 0 | P24: ci_seq | Q24: per_commit | R24: =INDEX('02_Freq_Weight'!$E$3:$E$9,MATCH(Q24,'02_Freq_Weight'!$A$3:$A$9,0)) | S24: 0.1 | T24: 90 | U24: 0.05 | V24: 0.15 | W24: unit_test, code_quality | X24: - | Y24: ISO/IEC 25010:2023; ISO/IEC 27001:2022; ISO/IEC 27034; NIST SSDF (SP 800-218); OWASP ASVS 5.0; OWASP MASVS; OWASP SAMM 2; OWASP Top 10:2025 | Z24: C-SDLC-QUALITY | AA24: C-APP-ERROR, C-SDLC-TEST, C-SDLC-THREAT | AB24: 4 | AC24: Visual Studio Test Professional; TestNG Enterprise; NCrunch; JUnit (IntelliJ Ultimate) | AE24: Test runner แบบขนาน (pytest-xdist / Jest workers) ใช้ RAM ≈ 500 MB ต่อ worker; 4 worker ≈ 2-4 GB | AF24: ภาครัฐบังคับ Coverage > 80% — coverage instrumentation ทำให้ใช้ RAM และเวลาเพิ่ม ~30-50% ต้องเผื่อไว้
A25: testcontainers | B25: Testcontainers / WireMock / Pact (Integration Test) | C25: 4 | D25: Integration Test | E25: Core | F25: oss | G25: MIT | H25: 4 | I25: 8 | J25: 40 | K25: 4 | L25: 8 | M25: 100 | N25: 0 | O25: 0 | P25: ci_seq | Q25: per_build | R25: =INDEX('02_Freq_Weight'!$E$3:$E$9,MATCH(Q25,'02_Freq_Weight'!$A$3:$A$9,0)) | S25: 0.15 | T25: 90 | U25: 0.05 | V25: 0.15 | W25: integration_test | X25: - | Y25: ISO/IEC 25010:2023; ISO/IEC 27001:2022; ISO/IEC 27034; NIST SSDF (SP 800-218) | Z25: - | AA25: C-SDLC-TEST | AB25: 1 | AC25: Tricentis Tosca; SmartBear ReadyAPI; Parasoft SOAtest; Postman Enterprise | AE25: Integration test ที่ spin ฐานข้อมูล/queue จริงเป็น container ต้องบวก RAM ของ PostgreSQL (~1 GB) + Redis (~0.5 GB) + RabbitMQ (~1 GB) เข้าไปในตอนรัน | AF25: เป็นขั้นที่กิน RAM สูงสุดใน Stage 4 เพราะรัน dependency จริงพร้อมกัน — อย่าให้ทับเวลากับ DAST Full Scan
A26: owasp-zap | B26: OWASP ZAP (DAST + API Security) | C26: 4 | D26: DAST | E26: Optional | F26: oss | G26: Apache-2.0 | H26: 2 | I26: 4 | J26: 20 | K26: 4 | L26: 8 | M26: 60 | N26: 0 | O26: 0 | P26: async | Q26: nightly | R26: =INDEX('02_Freq_Weight'!$E$3:$E$9,MATCH(Q26,'02_Freq_Weight'!$A$3:$A$9,0)) | S26: 0.15 | T26: 730 | U26: 0.1 | V26: 0.15 | W26: dast, api_security, vapt | X26: พ.ร.บ. ไซเบอร์ 2562; ITA (ป.ป.ช.); มาตรฐานขั้นต่ำ 2566; กรอบมาตรฐานไซเบอร์ 2564; มาตรฐานเว็บไซต์ 2568 | Y26: CIS Controls v8.1; ISO/IEC 27001:2022; ISO/IEC 27034; NIST SP 800-53r5; NIST SP 800-63B; OWASP API Top 10:2023; OWASP ASVS 5.0; OWASP MASVS; OWASP SAMM 2; OWASP Top 10:2025; PCI DSS v4.0 | Z26: C-APP-API, C-APP-DAST, C-APP-PENTEST | AA26: C-APP-ACCESS, C-APP-AUTHN, C-APP-INJECT, C-WEB-SELF | AB26: 7 | AC26: Veracode Dynamic Analysis; Burp Suite Professional; Acunetix; Rapid7 InsightAppSec; StackHawk | AD26: Nikto; w3af; Nuclei; Arachni; RESTler; Schemathesis | AE26: ZAP เป็น Java app ค่าปริยาย heap ~25% ของ RAM เครื่อง; Full Scan/AJAX Spider บนเว็บใหญ่ควรตั้ง -Xmx 4 GB ขึ้นไป และ session file โต 1-10 GB ต่อรอบ | AF26: แนวปฏิบัติที่ดีคือติดตั้ง ZAP บนเครื่องหนึ่งแล้วยิงสแกนข้ามเครื่องไปยัง Target ที่รันอยู่ (ห้ามยิงตัวเองเพราะจะแย่ง CPU กันจนผลเพี้ยน); การติดตั้งแบบ Native บน Host แทนการรันใน Docker ช่วยลด RAM ได้ประมาณ 15-20% เมื่อทรัพยากรจำกัด
A27: nuclei | B27: Nuclei (Template-based Vulnerability Scan) | C27: 4 | D27: DAST | E27: Optional | F27: oss | G27: MIT | H27: 2 | I27: 2 | J27: 10 | K27: 2 | L27: 4 | M27: 20 | N27: 0 | O27: 0 | P27: async | Q27: nightly | R27: =INDEX('02_Freq_Weight'!$E$3:$E$9,MATCH(Q27,'02_Freq_Weight'!$A$3:$A$9,0)) | S27: 0.05 | T27: 365 | U27: 0.05 | V27: 0.15 | W27: dast, api_security, vapt, tls_check | X27: พ.ร.บ. ไซเบอร์ 2562; มสพร. 11-2566 เว็บไซต์ภาครัฐ 3.0; พ.ร.บ. ปฏิบัติราชการทางอิเล็กทรอนิกส์ 2565; ขมธอ. ความมั่นคงปลอดภัยสารสนเทศ; ITA (ป.ป.ช.); มาตรฐานขั้นต่ำ 2566; กรอบมาตรฐานไซเบอร์ 2564; มาตรฐานเว็บไซต์ 2568; PDPA 2562; ประกาศ PDPC มาตรการความปลอดภัย 2565; พ.ร.ฎ. วิธีการแบบปลอดภัย 2553 | Y27: CIS Controls v8.1; CycloneDX / ECMA-424; ISO/IEC 27001:2022; ISO/IEC 27018; ISO/IEC 27034; ISO/IEC 27701; ISO/IEC 29100; NIST SP 800-53r5; NIST SP 800-63B; NIST PQC Migration; OWASP API Top 10:2023; OWASP ASVS 5.0; OWASP MASVS; OWASP SAMM 2; OWASP Top 10:2025; PCI DSS v4.0 | Z27: C-APP-API, C-APP-DAST, C-APP-PENTEST, C-CRY-TLS | AA27: C-APP-ACCESS, C-APP-AUTHN, C-APP-INJECT, C-CRY-PQC, C-PRV-MEASURE, C-WEB-SELF | AB27: 10 | AC27: Rapid7 InsightAppSec; Tenable.io; Qualys WAS | AE27: Nuclei เป็น Go binary รัน template ขนานสูง; RAM 500 MB - 2 GB ตามจำนวน concurrency ที่ตั้ง | AF27: เบากว่า ZAP มาก เหมาะรันทุกวันเป็น Fast Security Gate แล้วปล่อย ZAP Full Scan รอบสัปดาห์
A28: locust | B28: Locust (Performance / Load Test) | C28: 4 | D28: Performance Test | E28: Optional | F28: oss | G28: MIT | H28: 4 | I28: 8 | J28: 20 | K28: 8 | L28: 16 | M28: 60 | N28: 0 | O28: 0 | P28: load | Q28: weekly | R28: =INDEX('02_Freq_Weight'!$E$3:$E$9,MATCH(Q28,'02_Freq_Weight'!$A$3:$A$9,0)) | S28: 0.05 | T28: 365 | U28: 0.1 | V28: 0.15 | W28: perf_test | X28: - | Y28: ISO/IEC 25010:2023; ISO/IEC 27001:2022 | Z28: C-OPS-PERF | AA28: - | AB28: 1 | AC28: BlazeMeter; LoadRunner Enterprise; NeoLoad; Gatling Enterprise | AD28: K6; Apache JMeter; Gatling; Artillery; Vegeta; wrk | AE28: Locust ใช้ ~1 CPU core ต่อ ~1,000 concurrent users (แบบ single-process) จึงต้องรัน master + workers; แนะนำ 1 worker ต่อ core และ RAM ~1 GB ต่อ 1,000 users | AF28: ข้อควรระวังสำคัญ: ถ้ารัน Load Generator บนเครื่องเดียวกับระบบที่กำลังทดสอบ ผลการวัดจะเพี้ยน เพราะแย่ง CPU กันเอง ควรแยกเครื่องหรือแยกช่วงเวลาให้ชัดเจน และต้องกันทรัพยากรไว้เต็มจำนวนในช่วงที่รัน
A29: playwright-a11y | B29: Playwright + axe-core / pa11y-ci / Lighthouse CI (Accessibility) | C29: 4 | D29: Accessibility Test | E29: Optional | F29: oss | G29: Apache-2.0 | H29: 2 | I29: 4 | J29: 15 | K29: 4 | L29: 8 | M29: 40 | N29: 0 | O29: 0 | P29: async | Q29: nightly | R29: =INDEX('02_Freq_Weight'!$E$3:$E$9,MATCH(Q29,'02_Freq_Weight'!$A$3:$A$9,0)) | S29: 0.05 | T29: 365 | U29: 0.05 | V29: 0.1 | W29: accessibility, integration_test | X29: มสพร. 11-2566 เว็บไซต์ภาครัฐ 3.0 | Y29: ISO/IEC 25010:2023; ISO/IEC 27001:2022; ISO/IEC 27034; NIST SSDF (SP 800-218); WCAG 2.2 AA | Z29: C-WEB-A11Y | AA29: C-SDLC-TEST | AB29: 2 | AC29: Deque axe DevTools Pro; Siteimprove; Level Access | AE29: Headless Chromium ใช้ RAM ~300-700 MB ต่อ browser context; 4 context ขนาน ≈ 2-3 GB | AF29: จำเป็นสำหรับ .go.th ตาม มสพร. 11-2566 (WCAG 2.1/2.2 AA) — เป็นข้อที่โครงการภาครัฐมักตกเพราะไม่มีใน Pipeline; ต้องเก็บผลเป็นหลักฐาน Self-Assessment ตาม WEB2568-R4
A30: testssl | B30: testssl.sh / sslyze / CBOMkit (TLS + Crypto Inventory) | C30: 4 | D30: TLS & Crypto Validation | E30: Optional | F30: oss | G30: GPL-2.0 | H30: 1 | I30: 2 | J30: 5 | K30: 2 | L30: 2 | M30: 10 | N30: 0 | O30: 0 | P30: async | Q30: weekly | R30: =INDEX('02_Freq_Weight'!$E$3:$E$9,MATCH(Q30,'02_Freq_Weight'!$A$3:$A$9,0)) | S30: 0.01 | T30: 365 | U30: 0.05 | V30: 0.1 | W30: tls_check, crypto_agility | X30: มสพร. 11-2566 เว็บไซต์ภาครัฐ 3.0; พ.ร.บ. ปฏิบัติราชการทางอิเล็กทรอนิกส์ 2565; ขมธอ. ความมั่นคงปลอดภัยสารสนเทศ; มาตรฐานเว็บไซต์ 2568; PDPA 2562; ประกาศ PDPC มาตรการความปลอดภัย 2565; พ.ร.ฎ. วิธีการแบบปลอดภัย 2553 | Y30: CycloneDX / ECMA-424; ISO/IEC 27018; ISO/IEC 27701; ISO/IEC 29100; NIST PQC Migration; OWASP Top 10:2025; PCI DSS v4.0 | Z30: C-CRY-PQC, C-CRY-TLS | AA30: C-PRV-MEASURE | AB30: 3 | AC30: Qualys SSL Labs API; Venafi TLS Protect; Entrust | AE30: testssl.sh เป็น bash + openssl ใช้ RAM < 300 MB; ใช้เวลา 2-10 นาทีต่อ endpoint | AF30: ตรวจว่า TLS 1.2/1.3 เท่านั้น ไม่มี Self-signed ตาม มสพร. 11-2566 และ WEB2568-R1; CBOMkit ใช้ทำ Crypto Bill of Materials เตรียม Post-Quantum ตาม OWASP-PQC
A31: harbor | B31: Harbor (Private Container Registry, CNCF Graduated) | C31: 5 | D31: Container Registry | E31: Core | F31: oss | G31: Apache-2.0 | H31: 2 | I31: 4 | J31: 60 | K31: 4 | L31: 8 | M31: 200 | N31: 1 | O31: 3 | P31: resident | Q31: resident | R31: =INDEX('02_Freq_Weight'!$E$3:$E$9,MATCH(Q31,'02_Freq_Weight'!$A$3:$A$9,0)) | S31: 1 | T31: 180 | U31: 0.2 | V31: 0.25 | W31: registry, container_scan, artifact_sign, audit_trail, version_tag | X31: พ.ร.บ. คอมพิวเตอร์ 2550/2560; พ.ร.บ. ไซเบอร์ 2562; มาตรฐานข้อมูลเปิดภาครัฐ; พ.ร.บ. ปฏิบัติราชการทางอิเล็กทรอนิกส์ 2565; ขมธอ. ลายมือชื่อ/เอกสารอิเล็กทรอนิกส์; ITA (ป.ป.ช.); มาตรฐานขั้นต่ำ 2566; กรอบมาตรฐานไซเบอร์ 2564; มาตรฐานเว็บไซต์ 2568; PDPA 2562 | Y31: CIS Benchmarks; ISO 22301:2019; ISO/IEC 27001:2022; ISO/IEC 27018; ISO/IEC 27701; ISO/IEC 42001:2023; NIST SP 800-161r1; NIST SP 800-53r5; NIST CSF 2.0; NIST SSDF (SP 800-218); OWASP Top 10:2025; PCI DSS v4.0; SLSA v1.0; SOC 2 (TSC) | Z31: C-LOG-AUDIT, C-SC-CONTAINER, C-SC-REGISTRY, C-SC-SIGN | AA31: C-AI-GOV, C-LOG-90, C-OPS-BCP, C-SC-PIN, C-SDLC-TRACE, C-WEB-SELF | AB31: 10 | AC31: JFrog Artifactory Enterprise; Amazon ECR; Azure Container Registry; Google Artifact Registry | AD31: Zot; Quay.io; Distribution (Docker Registry); GitLab Container Registry | AE31: Harbor docs: minimum 2 CPU / 4 GB RAM / 40 GB disk; recommended 4 CPU / 8 GB RAM / 160 GB disk — ประกอบด้วย core, registry, jobservice, PostgreSQL, Redis, Trivy | AF31: รองรับ Air-gapped ตามข้อกำหนดภาครัฐ + มี Vulnerability Scan และ Cosign verification ในตัว; ต้องตั้ง Retention Policy ไม่งั้น disk โตไม่หยุด (2-5 GB/วัน จาก image tag ใหม่)
A32: minio | B32: MinIO (S3-compatible Object Storage) | C32: 5 | D32: Artifact Storage | E32: Core | F32: oss | G32: AGPL-3.0 | H32: 2 | I32: 4 | J32: 20 | K32: 4 | L32: 8 | M32: 500 | N32: 1 | O32: 1.5 | P32: resident | Q32: resident | R32: =INDEX('02_Freq_Weight'!$E$3:$E$9,MATCH(Q32,'02_Freq_Weight'!$A$3:$A$9,0)) | S32: 1 | T32: 180 | U32: 0.15 | V32: 0.25 | W32: registry, backup_dr, audit_trail | X32: พ.ร.บ. คอมพิวเตอร์ 2550/2560; พ.ร.บ. ไซเบอร์ 2562; มสพร. 11-2566 เว็บไซต์ภาครัฐ 3.0; มาตรฐานข้อมูลเปิดภาครัฐ; พ.ร.บ. ปฏิบัติราชการทางอิเล็กทรอนิกส์ 2565; ขมธอ. การใช้บริการคลาวด์; ขมธอ. ลายมือชื่อ/เอกสารอิเล็กทรอนิกส์; ITA (ป.ป.ช.); มาตรฐานขั้นต่ำ 2566; กรอบมาตรฐานไซเบอร์ 2564; มาตรฐานเว็บไซต์ 2568; PDPA 2562; พ.ร.ฎ. วิธีการแบบปลอดภัย 2553 | Y32: CIS Controls v8.1; ISO 22301:2019; ISO/IEC 27001:2022; ISO/IEC 27018; ISO/IEC 27701; ISO/IEC 42001:2023; NIST SP 800-161r1; NIST SP 800-53r5; NIST CSF 2.0; NIST SSDF (SP 800-218); OWASP Top 10:2025; SLSA v1.0; SOC 2 (TSC) | Z32: C-LOG-AUDIT, C-OPS-BACKUP, C-OPS-BCP, C-SC-REGISTRY | AA32: C-AI-GOV, C-LOG-90, C-SDLC-TRACE, C-WEB-SELF | AB32: 8 | AC32: Amazon S3; Azure Blob Storage; NetApp StorageGRID; Dell ECS | AE32: MinIO ขั้นต่ำใช้งานได้ที่ 2 vCPU / 4 GB (เอกสารแนะนำ 32 GB สำหรับ production ที่โหลดสูง เพราะ cache metadata ใน RAM); erasure coding ต้องมี 4 drive ขึ้นไปถ้าต้องการ HA | AF32: ใช้เป็นคลังเก็บ Container Image, Source Archive และ Report ที่เข้าถึงแบบ S3 API ได้ ต้องแยก Data Disk ออกจาก OS Disk เสมอ — ข้อควรระวัง License เป็น AGPL-3.0 ซึ่งขัดกับข้อห้าม ใช้ GPL/AGPL ของโครงการภาครัฐบางแห่ง ต้องตรวจว่าเข้าเงื่อนไข 'ไม่แก้ไข source และไม่ให้บริการต่อสาธารณะ' หรือขอ Commercial License
A33: elasticsearch | B33: Elasticsearch (Log / Audit Trail Index) | C33: 5 | D33: Log & Audit Store | E33: Core | F33: oss | G33: SSPL / Elastic License | H33: 2 | I33: 4 | J33: 40 | K33: 8 | L33: 16 | M33: 500 | N33: 1 | O33: 3.5 | P33: resident | Q33: resident | R33: =INDEX('02_Freq_Weight'!$E$3:$E$9,MATCH(Q33,'02_Freq_Weight'!$A$3:$A$9,0)) | S33: 1.5 | T33: 90 | U33: 0.45 | V33: 0.3 | W33: log_mgmt, audit_trail, siem_alert | X33: พ.ร.บ. คอมพิวเตอร์ 2550/2560; พ.ร.บ. ไซเบอร์ 2562; มสพร. 11-2566 เว็บไซต์ภาครัฐ 3.0; มาตรฐานข้อมูลเปิดภาครัฐ; พ.ร.บ. ปฏิบัติราชการทางอิเล็กทรอนิกส์ 2565; ขมธอ. ลายมือชื่อ/เอกสารอิเล็กทรอนิกส์; ขมธอ. ความมั่นคงปลอดภัยสารสนเทศ; ITA (ป.ป.ช.); มาตรฐานคลาวด์ 2567; มาตรฐานขั้นต่ำ 2566; กรอบมาตรฐานไซเบอร์ 2564; มาตรฐานเว็บไซต์ 2568; PDPA 2562; ประกาศ PDPC แจ้งเหตุละเมิด 2565; ประกาศ PDPC มาตรการความปลอดภัย 2565; พ.ร.ฎ. วิธีการแบบปลอดภัย 2553 | Y33: CIS Controls v8.1; CSA CCM v4 / STAR; ISO 22301:2019; ISO/IEC 27001:2022; ISO/IEC 27002:2022; ISO/IEC 27017; ISO/IEC 27018; ISO/IEC 27701; ISO/IEC 29100; ISO/IEC 42001:2023; NIST SP 800-207; NIST SP 800-53r5; NIST CSF 2.0; NIST SSDF (SP 800-218); OWASP ASVS 5.0; OWASP Top 10:2025; PCI DSS v4.0; SLSA v1.0; SOC 2 (TSC) | Z33: C-LOG-90, C-LOG-AUDIT, C-LOG-CENTRAL | AA33: C-LOG-NOTIFY, C-LOG-SIEM, C-OPS-BCP, C-PRV-BREACH, C-PRV-MEASURE, C-PRV-MINIMIZE, C-SDLC-TRACE, C-WEB-SELF | AB33: 11 | AC33: Splunk Enterprise; Datadog; Sumo Logic; Microsoft Sentinel | AE33: Elasticsearch แนะนำ JVM heap ไม่เกิน 50% ของ RAM และไม่เกิน ~31 GB; ที่ 4 GB RAM ต้องตั้ง ES_JAVA_OPTS=-Xms2g -Xmx2g; index overhead รวม replica + doc_values ประมาณ 30-50% ของ raw log | AF33: เป็นตัวกิน RAM และ Disk มากที่สุดในระบบ CI/CD — ถ้าต้องแชร์เครื่องกับ Orchestrator หรือ SAST ให้จำกัด heap ด้วย ES_JAVA_OPTS (เช่น 2-4 GB) เพื่อรักษาเสถียรภาพของเครื่อง; มาตรฐานขั้นต่ำ พ.ศ. 2566 บังคับเก็บ Log อย่างน้อย 90 วัน ซึ่งเป็นตัวกำหนดขนาด Data Disk โดยตรง
A34: logstash | B34: Logstash (Log Pipeline / Parser) | C34: 5 | D34: Log Ingest | E34: Optional | F34: oss | G34: SSPL / Elastic License | H34: 2 | I34: 4 | J34: 15 | K34: 2 | L34: 4 | M34: 40 | N34: 1 | O34: 1.5 | P34: resident | Q34: resident | R34: =INDEX('02_Freq_Weight'!$E$3:$E$9,MATCH(Q34,'02_Freq_Weight'!$A$3:$A$9,0)) | S34: 0.1 | T34: 30 | U34: 0.05 | V34: 0.2 | W34: log_mgmt | X34: พ.ร.บ. คอมพิวเตอร์ 2550/2560; มสพร. 11-2566 เว็บไซต์ภาครัฐ 3.0; ขมธอ. ความมั่นคงปลอดภัยสารสนเทศ; มาตรฐานคลาวด์ 2567; มาตรฐานขั้นต่ำ 2566; มาตรฐานเว็บไซต์ 2568; PDPA 2562; ประกาศ PDPC แจ้งเหตุละเมิด 2565; ประกาศ PDPC มาตรการความปลอดภัย 2565; พ.ร.ฎ. วิธีการแบบปลอดภัย 2553 | Y34: CIS Controls v8.1; CSA CCM v4 / STAR; ISO/IEC 27001:2022; ISO/IEC 27002:2022; ISO/IEC 27017; ISO/IEC 27018; ISO/IEC 27701; ISO/IEC 29100; OWASP ASVS 5.0; OWASP Top 10:2025; PCI DSS v4.0 | Z34: C-LOG-CENTRAL | AA34: C-LOG-90, C-PRV-BREACH, C-PRV-MEASURE, C-PRV-MINIMIZE | AB34: 5 | AC34: Splunk Forwarder; Datadog Agent; Cribl Stream | AE34: Logstash ค่าปริยาย heap 1 GB (แนะนำ 4-8 GB เมื่อ throughput สูง); ทุก pipeline worker กิน RAM เพิ่ม | AF34: ถ้า RAM จำกัด ให้ตัด Logstash ออกและใช้ Filebeat -> Elasticsearch Ingest Pipeline โดยตรง ประหยัดได้ 1.5-4 GB ต่อเครื่อง
A35: kibana | B35: Kibana (Log Visualization / Audit Review) | C35: 5 | D35: Log UI | E35: Core | F35: oss | G35: SSPL / Elastic License | H35: 1 | I35: 2 | J35: 10 | K35: 2 | L35: 4 | M35: 30 | N35: 1 | O35: 1.2 | P35: resident | Q35: resident | R35: =INDEX('02_Freq_Weight'!$E$3:$E$9,MATCH(Q35,'02_Freq_Weight'!$A$3:$A$9,0)) | S35: 0.05 | T35: 90 | U35: 0.05 | V35: 0.15 | W35: log_mgmt, audit_trail, siem_alert | X35: พ.ร.บ. คอมพิวเตอร์ 2550/2560; พ.ร.บ. ไซเบอร์ 2562; มสพร. 11-2566 เว็บไซต์ภาครัฐ 3.0; มาตรฐานข้อมูลเปิดภาครัฐ; พ.ร.บ. ปฏิบัติราชการทางอิเล็กทรอนิกส์ 2565; ขมธอ. ลายมือชื่อ/เอกสารอิเล็กทรอนิกส์; ขมธอ. ความมั่นคงปลอดภัยสารสนเทศ; ITA (ป.ป.ช.); มาตรฐานคลาวด์ 2567; มาตรฐานขั้นต่ำ 2566; กรอบมาตรฐานไซเบอร์ 2564; มาตรฐานเว็บไซต์ 2568; PDPA 2562; ประกาศ PDPC แจ้งเหตุละเมิด 2565; ประกาศ PDPC มาตรการความปลอดภัย 2565; พ.ร.ฎ. วิธีการแบบปลอดภัย 2553 | Y35: CIS Controls v8.1; CSA CCM v4 / STAR; ISO 22301:2019; ISO/IEC 27001:2022; ISO/IEC 27002:2022; ISO/IEC 27017; ISO/IEC 27018; ISO/IEC 27701; ISO/IEC 29100; ISO/IEC 42001:2023; NIST SP 800-207; NIST SP 800-53r5; NIST CSF 2.0; NIST SSDF (SP 800-218); OWASP ASVS 5.0; OWASP Top 10:2025; PCI DSS v4.0; SLSA v1.0; SOC 2 (TSC) | Z35: C-LOG-90, C-LOG-AUDIT, C-LOG-CENTRAL | AA35: C-LOG-NOTIFY, C-LOG-SIEM, C-OPS-BCP, C-PRV-BREACH, C-PRV-MEASURE, C-PRV-MINIMIZE, C-SDLC-TRACE, C-WEB-SELF | AB35: 11 | AC35: Splunk Dashboards; Datadog; Grafana Enterprise | AE35: Kibana เป็น Node.js app ค่าปริยาย heap ~1 GB (ปรับผ่าน NODE_OPTIONS --max-old-space-size) | AF35: ใช้ตรวจ Access Log และ Audit Log ก่อนกด Approve ขึ้น Production ซึ่งเป็นหลักฐานประกอบการตรวจสอบระบบตาม พ.ร.บ. ไซเบอร์ ม.54-57
A36: filebeat | B36: Filebeat (Log Shipper ต่อเครื่อง) | C36: 5 | D36: Log Agent | E36: Core | F36: oss | G36: SSPL / Elastic License | H36: 1 | I36: 1 | J36: 5 | K36: 1 | L36: 1 | M36: 10 | N36: 1 | O36: 0.15 | P36: resident | Q36: resident | R36: =INDEX('02_Freq_Weight'!$E$3:$E$9,MATCH(Q36,'02_Freq_Weight'!$A$3:$A$9,0)) | S36: 0.02 | T36: 7 | U36: 0.05 | V36: 0.2 | W36: log_mgmt | X36: พ.ร.บ. คอมพิวเตอร์ 2550/2560; มสพร. 11-2566 เว็บไซต์ภาครัฐ 3.0; ขมธอ. ความมั่นคงปลอดภัยสารสนเทศ; มาตรฐานคลาวด์ 2567; มาตรฐานขั้นต่ำ 2566; มาตรฐานเว็บไซต์ 2568; PDPA 2562; ประกาศ PDPC แจ้งเหตุละเมิด 2565; ประกาศ PDPC มาตรการความปลอดภัย 2565; พ.ร.ฎ. วิธีการแบบปลอดภัย 2553 | Y36: CIS Controls v8.1; CSA CCM v4 / STAR; ISO/IEC 27001:2022; ISO/IEC 27002:2022; ISO/IEC 27017; ISO/IEC 27018; ISO/IEC 27701; ISO/IEC 29100; OWASP ASVS 5.0; OWASP Top 10:2025; PCI DSS v4.0 | Z36: C-LOG-CENTRAL | AA36: C-LOG-90, C-PRV-BREACH, C-PRV-MEASURE, C-PRV-MINIMIZE | AB36: 5 | AC36: Splunk Universal Forwarder; Datadog Agent; Fluent Bit | AE36: Filebeat เป็น Go binary กิน RAM 50-150 MB ต่อ instance; ต้องลงทุกเครื่องที่ต้องการเก็บ log | AF36: ทั้ง 2 โครงการใช้ Filebeat ส่ง Log เข้า Elasticsearch แบบ Real-time; ต้องนับ 1 instance ต่อ 1 VM ในการคำนวณ (เล็กแต่คูณจำนวนเครื่อง)
A37: wazuh | B37: Wazuh (SIEM / HIDS + Alerting) | C37: 5 | D37: SIEM | E37: Optional | F37: oss | G37: GPL-2.0 | H37: 4 | I37: 8 | J37: 50 | K37: 8 | L37: 16 | M37: 300 | N37: 1 | O37: 6 | P37: resident | Q37: resident | R37: =INDEX('02_Freq_Weight'!$E$3:$E$9,MATCH(Q37,'02_Freq_Weight'!$A$3:$A$9,0)) | S37: 1 | T37: 90 | U37: 0.4 | V37: 0.3 | W37: siem_alert, log_mgmt, audit_trail, runtime_security, config_mgmt | X37: พ.ร.บ. คอมพิวเตอร์ 2550/2560; พ.ร.บ. ไซเบอร์ 2562; มสพร. 11-2566 เว็บไซต์ภาครัฐ 3.0; มาตรฐานข้อมูลเปิดภาครัฐ; พ.ร.บ. ปฏิบัติราชการทางอิเล็กทรอนิกส์ 2565; ขมธอ. การใช้บริการคลาวด์; ขมธอ. ลายมือชื่อ/เอกสารอิเล็กทรอนิกส์; ขมธอ. ความมั่นคงปลอดภัยสารสนเทศ; ITA (ป.ป.ช.); มาตรฐานคลาวด์ 2567; มาตรฐานขั้นต่ำ 2566; กรอบมาตรฐานไซเบอร์ 2564; มาตรฐานเว็บไซต์ 2568; PDPA 2562; ประกาศ PDPC แจ้งเหตุละเมิด 2565; ประกาศ PDPC มาตรการความปลอดภัย 2565; พ.ร.ฎ. วิธีการแบบปลอดภัย 2553 | Y37: CIS Benchmarks; CIS Controls v8.1; CSA CCM v4 / STAR; ISO 22301:2019; ISO/IEC 27001:2022; ISO/IEC 27002:2022; ISO/IEC 27017; ISO/IEC 27018; ISO/IEC 27701; ISO/IEC 29100; ISO/IEC 42001:2023; NIST SP 800-207; NIST SP 800-53r5; NIST CSF 2.0; NIST SSDF (SP 800-218); OWASP ASVS 5.0; OWASP Top 10:2025; PCI DSS v4.0; SLSA v1.0; SOC 2 (TSC) | Z37: C-LOG-90, C-LOG-AUDIT, C-LOG-CENTRAL, C-OPS-HARDEN, C-OPS-RUNTIME | AA37: C-AI-DRIFT, C-IAM-LEAST, C-IAM-REMOTE, C-LOG-NOTIFY, C-LOG-SIEM, C-OPS-BCP, C-PRV-BREACH, C-PRV-MEASURE, C-PRV-MINIMIZE, C-SDLC-TRACE, C-WEB-SELF | AB37: 16 | AC37: Splunk Enterprise Security; Microsoft Sentinel; IBM QRadar; Elastic Security | AE37: Wazuh docs: server ขั้นต่ำ 2 vCPU / 4 GB สำหรับ < 25 agents แต่แนะนำ 4 vCPU / 8 GB ขึ้นไปเมื่อรวม Indexer; Indexer เป็น OpenSearch จึงกิน RAM แบบเดียวกับ Elasticsearch | AF37: จำเป็นสำหรับ CYBER2562-R2 (เฝ้าระวัง + รายงาน สกมช. ทันที) และ PDPA-R2 (แจ้งเหตุใน 72 ชม.); ถ้ามี ELK อยู่แล้วให้พิจารณา Elastic Security แทนเพื่อไม่ต้องรัน OpenSearch ซ้อน
A38: vault | B38: HashiCorp Vault / OpenBao (Secret Management) | C38: 5 | D38: Secret Management | E38: Optional | F38: oss | G38: BUSL-1.1 / MPL-2.0 | H38: 2 | I38: 4 | J38: 20 | K38: 2 | L38: 4 | M38: 60 | N38: 1 | O38: 1 | P38: resident | Q38: resident | R38: =INDEX('02_Freq_Weight'!$E$3:$E$9,MATCH(Q38,'02_Freq_Weight'!$A$3:$A$9,0)) | S38: 0.05 | T38: 2555 | U38: 0.1 | V38: 0.15 | W38: secret_mgmt, iam_mfa, audit_trail | X38: พ.ร.บ. คอมพิวเตอร์ 2550/2560; พ.ร.บ. ไซเบอร์ 2562; มสพร. 11-2566 เว็บไซต์ภาครัฐ 3.0; มาตรฐานข้อมูลเปิดภาครัฐ; พ.ร.บ. ปฏิบัติราชการทางอิเล็กทรอนิกส์ 2565; ขมธอ. การใช้บริการคลาวด์; ขมธอ. ลายมือชื่อ/เอกสารอิเล็กทรอนิกส์; ขมธอ. ความมั่นคงปลอดภัยสารสนเทศ; ITA (ป.ป.ช.); มาตรฐานคลาวด์ 2567; มาตรฐานขั้นต่ำ 2566; กรอบมาตรฐานไซเบอร์ 2564; มาตรฐานเว็บไซต์ 2568; PDPA 2562; ประกาศ PDPC มาตรการความปลอดภัย 2565; พ.ร.ฎ. วิธีการแบบปลอดภัย 2553 | Y38: CIS Benchmarks; CIS Controls v8.1; CSA CCM v4 / STAR; ISO 22301:2019; ISO/IEC 27001:2022; ISO/IEC 27002:2022; ISO/IEC 27017; ISO/IEC 27018; ISO/IEC 27701; ISO/IEC 29100; ISO/IEC 42001:2023; NIST SP 800-207; NIST SP 800-53r5; NIST SP 800-63B; NIST CSF 2.0; NIST SSDF (SP 800-218); OWASP API Top 10:2023; OWASP ASVS 5.0; OWASP MASVS; OWASP Top 10:2025; SLSA v1.0; SOC 2 (TSC) | Z38: C-CRY-KEY, C-IAM-MFA, C-LOG-AUDIT | AA38: C-APP-AUTHN, C-IAM-LEAST, C-IAM-REMOTE, C-LOG-90, C-OPS-BCP, C-PRV-MEASURE, C-SDLC-SECRET, C-SDLC-TRACE, C-WEB-SELF | AB38: 12 | AC38: HashiCorp Vault Enterprise; Azure Key Vault; AWS Secrets Manager; CyberArk Conjur | AD38: OpenBao; Infisical; SOPS + age; Sealed Secrets | AE38: Vault แนะนำ 2 vCPU / 4-8 GB สำหรับ production ขนาดเล็ก (มี in-memory cache + audit log); ต้องมี storage backend (Raft/Consul) | AF38: ตอบ PDPA-R1 (การเข้ารหัส + Key Rotation) และ OWASP-A04; ห้ามเก็บ Credential ใน Jenkins Credentials อย่างเดียวเพราะไม่มี Rotation/Lease — Vault ต้องเปิด Audit Device ตลอดเวลา
A39: k3s-control | B39: Kubernetes / K3s Control Plane (ต่อ 1 Node) | C39: 6 | D39: Container Orchestration | E39: Core | F39: oss | G39: Apache-2.0 | H39: 2 | I39: 4 | J39: 40 | K39: 4 | L39: 8 | M39: 100 | N39: 1 | O39: 2.5 | P39: resident | Q39: resident | R39: =INDEX('02_Freq_Weight'!$E$3:$E$9,MATCH(Q39,'02_Freq_Weight'!$A$3:$A$9,0)) | S39: 0.3 | T39: 90 | U39: 0.15 | V39: 0.2 | W39: orchestration, deploy_strategy, iam_mfa | X39: พ.ร.บ. ไซเบอร์ 2562; มสพร. 11-2566 เว็บไซต์ภาครัฐ 3.0; ขมธอ. การใช้บริการคลาวด์; ขมธอ. ความมั่นคงปลอดภัยสารสนเทศ; มาตรฐานคลาวด์ 2567; มาตรฐานขั้นต่ำ 2566; มาตรฐานเว็บไซต์ 2568; PDPA 2562; ประกาศ PDPC มาตรการความปลอดภัย 2565; พ.ร.ฎ. วิธีการแบบปลอดภัย 2553 | Y39: CIS Benchmarks; CIS Controls v8.1; CSA CCM v4 / STAR; ISO/IEC 27001:2022; ISO/IEC 27017; ISO/IEC 27018; ISO/IEC 27701; ISO/IEC 29100; NIST SP 800-207; NIST SP 800-53r5; NIST SP 800-63B; OWASP API Top 10:2023; OWASP ASVS 5.0; OWASP MASVS; OWASP Top 10:2025; SOC 2 (TSC) | Z39: C-IAM-MFA, C-OPS-DEPLOY | AA39: C-APP-AUTHN, C-IAM-LEAST, C-IAM-REMOTE, C-PRV-MEASURE | AB39: 6 | AC39: Red Hat OpenShift; Rancher Enterprise; VMware Tanzu; Google GKE Enterprise; Azure AKS | AD39: MicroK8s; K0s; Docker Swarm; Nomad; Docker Compose (UAT เท่านั้น) | AE39: K3s docs: server node ขั้นต่ำ 2 vCPU / 2 GB (แนะนำ 4 GB); kubeadm control plane ขั้นต่ำ 2 vCPU / 2 GB แต่ etcd + apiserver ที่โหลดจริงควรมี 4 GB ขึ้นไป | AF39: ถ้าโครงการยังใช้ Docker Compose อยู่ (เช่น UAT ของทั้ง 2 โครงการ) ยังไม่ต้องนับส่วนนี้ — แต่ต้องเผื่อไว้ในแผน Production เพราะ Blueprint ระบุ Container Orchestration เป็น Core
A40: argocd | B40: Argo CD / Flux (GitOps Continuous Delivery) | C40: 6 | D40: Deployment Strategy | E40: Core | F40: oss | G40: Apache-2.0 | H40: 2 | I40: 4 | J40: 20 | K40: 4 | L40: 8 | M40: 60 | N40: 1 | O40: 2 | P40: resident | Q40: resident | R40: =INDEX('02_Freq_Weight'!$E$3:$E$9,MATCH(Q40,'02_Freq_Weight'!$A$3:$A$9,0)) | S40: 0.1 | T40: 365 | U40: 0.1 | V40: 0.15 | W40: deploy_strategy, audit_trail, quality_gate, version_tag | X40: พ.ร.บ. คอมพิวเตอร์ 2550/2560; พ.ร.บ. ไซเบอร์ 2562; มาตรฐานข้อมูลเปิดภาครัฐ; พ.ร.บ. ปฏิบัติราชการทางอิเล็กทรอนิกส์ 2565; ขมธอ. ลายมือชื่อ/เอกสารอิเล็กทรอนิกส์; ITA (ป.ป.ช.); มาตรฐานขั้นต่ำ 2566; กรอบมาตรฐานไซเบอร์ 2564; มาตรฐานเว็บไซต์ 2568; PDPA 2562 | Y40: CIS Controls v8.1; ISO 22301:2019; ISO/IEC 27001:2022; ISO/IEC 27018; ISO/IEC 27034; ISO/IEC 27701; ISO/IEC 42001:2023; NIST SP 800-53r5; NIST CSF 2.0; NIST SSDF (SP 800-218); OWASP SAMM 2; OWASP Top 10:2025; SLSA v1.0; SOC 2 (TSC) | Z40: C-LOG-AUDIT | AA40: C-AI-GOV, C-LOG-90, C-OPS-BCP, C-OPS-DEPLOY, C-SC-PIN, C-SDLC-REVIEW, C-SDLC-THREAT, C-SDLC-TRACE, C-WEB-SELF | AB40: 10 | AC40: Harness CD; Spinnaker Enterprise; GitLab Premium Auto DevOps; LaunchDarkly | AE40: Argo CD ประกอบด้วย api-server, repo-server, application-controller, Redis; รวมกันขั้นต่ำ ~2 vCPU / 2-4 GB สำหรับ < 50 applications | AF40: ให้ Git เป็น Single Source of Truth = ได้ Audit Trail และ Rollback ฟรีตาม CORE-R2; Argo Rollouts เพิ่ม Canary/Blue-Green ได้ด้วย resource เพิ่มเพียง ~0.5 vCPU / 0.5 GB
A41: falco | B41: Falco (Runtime Security Monitoring, ต่อ Node) | C41: 6 | D41: Runtime Security | E41: Optional | F41: oss | G41: Apache-2.0 | H41: 1 | I41: 2 | J41: 10 | K41: 2 | L41: 4 | M41: 30 | N41: 1 | O41: 0.8 | P41: resident | Q41: resident | R41: =INDEX('02_Freq_Weight'!$E$3:$E$9,MATCH(Q41,'02_Freq_Weight'!$A$3:$A$9,0)) | S41: 0.3 | T41: 90 | U41: 0.2 | V41: 0.25 | W41: runtime_security, siem_alert | X41: พ.ร.บ. ไซเบอร์ 2562; ขมธอ. การใช้บริการคลาวด์; ขมธอ. ความมั่นคงปลอดภัยสารสนเทศ; มาตรฐานคลาวด์ 2567; กรอบมาตรฐานไซเบอร์ 2564; มาตรฐานเว็บไซต์ 2568; PDPA 2562; ประกาศ PDPC แจ้งเหตุละเมิด 2565 | Y41: CIS Benchmarks; CSA CCM v4 / STAR; ISO/IEC 27001:2022; ISO/IEC 27017; ISO/IEC 27701; ISO/IEC 42001:2023; NIST SP 800-207; NIST SP 800-53r5; NIST CSF 2.0; OWASP Top 10:2025; SOC 2 (TSC) | Z41: C-OPS-RUNTIME | AA41: C-AI-DRIFT, C-IAM-LEAST, C-LOG-NOTIFY, C-LOG-SIEM, C-PRV-BREACH | AB41: 6 | AC41: Aqua Runtime Security; Prisma Cloud Runtime Defense; Sysdig Secure; Lacework | AD41: Tetragon; KubeArmor; Tracee; Osquery | AE41: Falco ใช้ eBPF/kernel module ดักจับ syscall; RAM ~200-500 MB ต่อ node แต่ CPU เพิ่มขึ้นตาม syscall rate (ปกติ 5-15% ของ 1 core) | AF41: ภาครัฐกำหนด 'Mandatory Real-time' — ต้องลงทุก node ที่รัน container; ระวัง event flood ทำให้ Elasticsearch โตเร็วกว่าที่ประเมิน ให้ตั้ง rule ให้แคบก่อนเปิดใช้จริง
A42: prometheus | B42: Prometheus (Metrics & Alerting) | C42: 6 | D42: Monitoring | E42: Core | F42: oss | G42: Apache-2.0 | H42: 2 | I42: 4 | J42: 40 | K42: 4 | L42: 8 | M42: 200 | N42: 1 | O42: 2.5 | P42: resident | Q42: resident | R42: =INDEX('02_Freq_Weight'!$E$3:$E$9,MATCH(Q42,'02_Freq_Weight'!$A$3:$A$9,0)) | S42: 0.8 | T42: 90 | U42: 0.1 | V42: 0.3 | W42: monitoring, siem_alert, notify | X42: พ.ร.บ. ไซเบอร์ 2562; มาตรฐานคลาวด์ 2567; กรอบมาตรฐานไซเบอร์ 2564; มาตรฐานเว็บไซต์ 2568; PDPA 2562; ประกาศ PDPC แจ้งเหตุละเมิด 2565 | Y42: ISO/IEC 27701; ISO/IEC 42001:2023; NIST SP 800-207; NIST CSF 2.0; OWASP Top 10:2025; SOC 2 (TSC) | Z42: C-LOG-NOTIFY, C-LOG-SIEM, C-OPS-MONITOR | AA42: C-AI-DRIFT, C-PRV-BREACH | AB42: 5 | AC42: Datadog; Dynatrace; New Relic; Splunk; AppDynamics | AD42: VictoriaMetrics; Mimir; Zabbix; OpenTelemetry Collector | AE42: Prometheus ใช้ RAM ประมาณ 2-4 KB ต่อ active time series; 500,000 series ≈ 2-4 GB; disk ≈ 1.5-2 bytes ต่อ sample (scrape 15s = ~5,760 sample/series/วัน) | AF42: สูตรประมาณ disk: series × 5,760 × 2 bytes × retention_days; 200,000 series เก็บ 180 วัน ≈ 400 GB — ถ้า disk ไม่พอให้ลด retention เป็น 30 วันแล้วส่งต่อไป Thanos/VictoriaMetrics
A43: grafana | B43: Grafana (Dashboard) | C43: 6 | D43: Monitoring UI | E43: Core | F43: oss | G43: AGPL-3.0 | H43: 1 | I43: 2 | J43: 10 | K43: 2 | L43: 4 | M43: 30 | N43: 1 | O43: 0.6 | P43: resident | Q43: resident | R43: =INDEX('02_Freq_Weight'!$E$3:$E$9,MATCH(Q43,'02_Freq_Weight'!$A$3:$A$9,0)) | S43: 0.02 | T43: 365 | U43: 0.05 | V43: 0.15 | W43: monitoring | X43: พ.ร.บ. ไซเบอร์ 2562; มาตรฐานคลาวด์ 2567; กรอบมาตรฐานไซเบอร์ 2564; มาตรฐานเว็บไซต์ 2568; ประกาศ PDPC แจ้งเหตุละเมิด 2565 | Y43: ISO/IEC 42001:2023; NIST SP 800-207; NIST CSF 2.0; OWASP Top 10:2025; SOC 2 (TSC) | Z43: C-OPS-MONITOR | AA43: C-AI-DRIFT, C-LOG-SIEM | AB43: 3 | AC43: Datadog Dashboards; Grafana Enterprise; New Relic One | AE43: Grafana เป็น Go binary กิน RAM 150-500 MB; ใช้ SQLite ในตัวหรือ PostgreSQL ภายนอก | AF43: License เป็น AGPL-3.0 — เช่นเดียวกับ MinIO ต้องตรวจข้อห้าม GPL/AGPL ของภาครัฐก่อนใช้เชิงพาณิชย์/ให้บริการต่อ
A44: zabbix | B44: Zabbix Server (Infrastructure Monitoring) | C44: 6 | D44: Monitoring | E44: Optional | F44: oss | G44: AGPL-3.0 | H44: 2 | I44: 4 | J44: 30 | K44: 4 | L44: 8 | M44: 150 | N44: 1 | O44: 2 | P44: resident | Q44: resident | R44: =INDEX('02_Freq_Weight'!$E$3:$E$9,MATCH(Q44,'02_Freq_Weight'!$A$3:$A$9,0)) | S44: 0.4 | T44: 365 | U44: 0.25 | V44: 0.2 | W44: monitoring, notify, siem_alert | X44: พ.ร.บ. ไซเบอร์ 2562; มาตรฐานคลาวด์ 2567; กรอบมาตรฐานไซเบอร์ 2564; มาตรฐานเว็บไซต์ 2568; PDPA 2562; ประกาศ PDPC แจ้งเหตุละเมิด 2565 | Y44: ISO/IEC 27701; ISO/IEC 42001:2023; NIST SP 800-207; NIST CSF 2.0; OWASP Top 10:2025; SOC 2 (TSC) | Z44: C-LOG-NOTIFY, C-LOG-SIEM, C-OPS-MONITOR | AA44: C-AI-DRIFT, C-PRV-BREACH | AB44: 5 | AC44: Datadog; SolarWinds; Nagios XI; PRTG | AE44: Zabbix server ขั้นต่ำ 2 vCPU / 2 GB สำหรับ < 100 hosts แต่ต้องรวม MySQL/PostgreSQL อีก 2-4 GB; disk โตตาม history + trends | AF44: ถ้าหน่วยงานมีระบบ Monitoring ส่วนกลางอยู่แล้ว (สังเกตได้จากพอร์ต 10051 ที่เปิดรออยู่บนเครื่อง) ให้ประสานส่ง metric เข้าระบบเดิม ไม่ติดตั้ง Prometheus ซ้อนอีกชุด เพื่อไม่ให้เสีย RAM ซ้ำซ้อน
A45: ansible-chef | B45: Ansible / Chef Client (Config Management & Hardening) | C45: 6 | D45: Configuration Management | E45: Optional | F45: oss | G45: GPL-3.0 / Apache-2.0 | H45: 1 | I45: 2 | J45: 15 | K45: 2 | L45: 4 | M45: 40 | N45: 0 | O45: 0.1 | P45: async | Q45: nightly | R45: =INDEX('02_Freq_Weight'!$E$3:$E$9,MATCH(Q45,'02_Freq_Weight'!$A$3:$A$9,0)) | S45: 0.05 | T45: 365 | U45: 0.1 | V45: 0.15 | W45: config_mgmt, iac_scan, backup_dr | X45: พ.ร.บ. ไซเบอร์ 2562; มสพร. 11-2566 เว็บไซต์ภาครัฐ 3.0; ขมธอ. การใช้บริการคลาวด์; ขมธอ. ความมั่นคงปลอดภัยสารสนเทศ; มาตรฐานคลาวด์ 2567; มาตรฐานขั้นต่ำ 2566; กรอบมาตรฐานไซเบอร์ 2564; มาตรฐานเว็บไซต์ 2568; พ.ร.ฎ. วิธีการแบบปลอดภัย 2553 | Y45: CIS Benchmarks; CIS Controls v8.1; ISO 22301:2019; ISO/IEC 27001:2022; ISO/IEC 27002:2022; NIST SP 800-53r5; NIST CSF 2.0; OWASP Top 10:2025; SOC 2 (TSC) | Z45: C-OPS-BACKUP, C-OPS-HARDEN, C-OPS-IAC | AA45: C-IAM-REMOTE, C-OPS-BCP | AB45: 5 | AC45: Red Hat Ansible Automation Platform; Chef Enterprise Automate; Puppet Enterprise | AE45: Ansible controller ใช้ RAM ~100 MB ต่อ fork; 10 forks ≈ 1-2 GB; Chef Client บน node กิน ~300-500 MB ต่อรอบ converge | AF45: ใช้ตรวจและบังคับ Configuration Baseline อัตโนมัติ เช่น Dual-Stack IPv4/IPv6, Kernel Parameter, Firewall Rule, การปิด service ที่ไม่ใช้ — ตอบข้อ Hardening Baseline ของ OWASP A02 และ MIN2566-R2
A46: modsecurity | B46: ModSecurity / Coraza (Web Application Firewall) | C46: 6 | D46: WAF | E46: Optional | F46: oss | G46: Apache-2.0 | H46: 2 | I46: 4 | J46: 15 | K46: 4 | L46: 8 | M46: 60 | N46: 1 | O46: 1 | P46: resident | Q46: resident | R46: =INDEX('02_Freq_Weight'!$E$3:$E$9,MATCH(Q46,'02_Freq_Weight'!$A$3:$A$9,0)) | S46: 0.4 | T46: 90 | U46: 0.15 | V46: 0.25 | W46: waf, tls_check | X46: มสพร. 11-2566 เว็บไซต์ภาครัฐ 3.0; พ.ร.บ. ปฏิบัติราชการทางอิเล็กทรอนิกส์ 2565; ขมธอ. ความมั่นคงปลอดภัยสารสนเทศ; มาตรฐานเว็บไซต์ 2568; PDPA 2562; ประกาศ PDPC มาตรการความปลอดภัย 2565; พ.ร.ฎ. วิธีการแบบปลอดภัย 2553 | Y46: CycloneDX / ECMA-424; ISO/IEC 27018; ISO/IEC 27701; ISO/IEC 29100; NIST PQC Migration; OWASP Top 10:2025; PCI DSS v4.0 | Z46: C-APP-WAF, C-CRY-TLS | AA46: C-CRY-PQC, C-PRV-MEASURE | AB46: 4 | AC46: F5 Advanced WAF; Cloudflare WAF; Imperva; Azure Application Gateway WAF; AWS WAF | AE46: ModSecurity + OWASP CRS ทำงานเป็น module ของ Nginx/Apache; เพิ่ม RAM ~500 MB - 1 GB และ CPU ~10-30% ต่อ request เมื่อเปิด rule set เต็ม | AF46: มสพร. 11-2566 'แนะนำ' แต่มาตรฐานเว็บไซต์ พ.ศ. 2568 'บังคับ' ให้ติดตั้ง WAF — ควรวางไว้ที่ Reverse Proxy หรือ API Gateway ไม่ใช่บนเครื่อง CI/CD เพราะจะกิน CPU ของ Pipeline
A47: keycloak | B47: Keycloak (SSO / MFA / Identity) | C47: 6 | D47: Identity & Access | E47: Optional | F47: oss | G47: Apache-2.0 | H47: 2 | I47: 4 | J47: 20 | K47: 4 | L47: 8 | M47: 60 | N47: 1 | O47: 1.5 | P47: resident | Q47: resident | R47: =INDEX('02_Freq_Weight'!$E$3:$E$9,MATCH(Q47,'02_Freq_Weight'!$A$3:$A$9,0)) | S47: 0.1 | T47: 2555 | U47: 0.15 | V47: 0.2 | W47: iam_mfa, audit_trail | X47: พ.ร.บ. คอมพิวเตอร์ 2550/2560; พ.ร.บ. ไซเบอร์ 2562; มสพร. 11-2566 เว็บไซต์ภาครัฐ 3.0; มาตรฐานข้อมูลเปิดภาครัฐ; พ.ร.บ. ปฏิบัติราชการทางอิเล็กทรอนิกส์ 2565; ขมธอ. การใช้บริการคลาวด์; ขมธอ. ลายมือชื่อ/เอกสารอิเล็กทรอนิกส์; ขมธอ. ความมั่นคงปลอดภัยสารสนเทศ; ITA (ป.ป.ช.); มาตรฐานคลาวด์ 2567; มาตรฐานขั้นต่ำ 2566; กรอบมาตรฐานไซเบอร์ 2564; มาตรฐานเว็บไซต์ 2568; PDPA 2562; ประกาศ PDPC มาตรการความปลอดภัย 2565; พ.ร.ฎ. วิธีการแบบปลอดภัย 2553 | Y47: CIS Benchmarks; CIS Controls v8.1; CSA CCM v4 / STAR; ISO 22301:2019; ISO/IEC 27001:2022; ISO/IEC 27017; ISO/IEC 27018; ISO/IEC 27701; ISO/IEC 29100; ISO/IEC 42001:2023; NIST SP 800-207; NIST SP 800-53r5; NIST SP 800-63B; NIST CSF 2.0; NIST SSDF (SP 800-218); OWASP API Top 10:2023; OWASP ASVS 5.0; OWASP MASVS; OWASP Top 10:2025; SLSA v1.0; SOC 2 (TSC) | Z47: C-IAM-MFA, C-LOG-AUDIT | AA47: C-APP-AUTHN, C-IAM-LEAST, C-IAM-REMOTE, C-LOG-90, C-OPS-BCP, C-PRV-MEASURE, C-SDLC-TRACE, C-WEB-SELF | AB47: 10 | AC47: Microsoft Entra ID; Okta; PingFederate; ForgeRock | AE47: Keycloak เป็น Quarkus app แนะนำ heap 1-2 GB สำหรับ < 10,000 users; ต้องมี PostgreSQL ภายนอกใน production | AF47: ตอบ WEB2568-R1 (MFA บังคับสำหรับบัญชีสำคัญ) และ OWASP-A07 — ถ้าองค์กรมี SSO ส่วนกลางอยู่แล้ว ให้เชื่อมต่อผ่าน OIDC/SAML แทนการติดตั้งใหม่ ซึ่งประหยัดทั้ง RAM และภาระการดูแล
A48: velero-restic | B48: Velero / restic / pgBackRest (Backup & DR) | C48: 6 | D48: Backup & DR | E48: Optional | F48: oss | G48: Apache-2.0 | H48: 1 | I48: 2 | J48: 20 | K48: 2 | L48: 4 | M48: 60 | N48: 0 | O48: 0.2 | P48: async | Q48: nightly | R48: =INDEX('02_Freq_Weight'!$E$3:$E$9,MATCH(Q48,'02_Freq_Weight'!$A$3:$A$9,0)) | S48: 2 | T48: 90 | U48: 0.05 | V48: 0.25 | W48: backup_dr | X48: พ.ร.บ. ไซเบอร์ 2562; มสพร. 11-2566 เว็บไซต์ภาครัฐ 3.0; ขมธอ. การใช้บริการคลาวด์; มาตรฐานขั้นต่ำ 2566; กรอบมาตรฐานไซเบอร์ 2564; มาตรฐานเว็บไซต์ 2568; พ.ร.ฎ. วิธีการแบบปลอดภัย 2553 | Y48: CIS Controls v8.1; ISO 22301:2019; ISO/IEC 27001:2022; NIST SP 800-53r5; NIST CSF 2.0; SOC 2 (TSC) | Z48: C-OPS-BACKUP | AA48: C-OPS-BCP | AB48: 2 | AC48: Veeam; Commvault; Rubrik; Azure Backup | AE48: restic/Velero ใช้ RAM ~500 MB - 2 GB ตอน backup (dedup index อยู่ใน RAM); ปริมาณ backup = ขนาดข้อมูล × จำนวน full copy + incremental | AF48: MIN2566-R4 บังคับซ้อมแผน BCP ทุกปี และ CYBER2562-R3 บังคับแผนกู้คืนสำหรับ CII — Backup ต้องเก็บแยกเครื่อง/แยก site และต้องทดสอบ Restore จริง ไม่ใช่แค่ Backup ผ่าน
A49: prowler | B49: Prowler / ScoutSuite (Cloud & Infra Posture Scan) | C49: 6 | D49: CSPM | E49: Optional | F49: oss | G49: Apache-2.0 | H49: 2 | I49: 4 | J49: 15 | K49: 2 | L49: 4 | M49: 40 | N49: 0 | O49: 0 | P49: async | Q49: weekly | R49: =INDEX('02_Freq_Weight'!$E$3:$E$9,MATCH(Q49,'02_Freq_Weight'!$A$3:$A$9,0)) | S49: 0.05 | T49: 730 | U49: 0.1 | V49: 0.15 | W49: cspm, iac_scan, config_mgmt | X49: ขมธอ. การใช้บริการคลาวด์; ขมธอ. ความมั่นคงปลอดภัยสารสนเทศ; มาตรฐานคลาวด์ 2567; มาตรฐานขั้นต่ำ 2566; กรอบมาตรฐานไซเบอร์ 2564 | Y49: CIS Benchmarks; CIS Controls v8.1; CSA CCM v4 / STAR; ISO/IEC 27001:2022; ISO/IEC 27002:2022; ISO/IEC 27017; NIST SP 800-53r5; NIST CSF 2.0; OWASP Top 10:2025 | Z49: C-OPS-CSPM, C-OPS-HARDEN, C-OPS-IAC | AA49: C-IAM-REMOTE | AB49: 4 | AC49: Prisma Cloud; Wiz; Orca Security; Microsoft Defender for Cloud | AE49: Prowler เป็น Python CLI เรียก API ของ cloud provider; RAM 1-2 GB, เวลารัน 10-60 นาทีตามขนาด account | AF49: ตอบ CLOUD2567-R1 — Prowler ออกแบบมาสำหรับ Cloud API ถ้าระบบเป็น On-premise ล้วน ให้ใช้ CIS Benchmark scanner เช่น OpenSCAP หรือ Lynis แทน
A50: mlflow | B50: MLflow (Experiment Tracking + Model Registry) | C50: 5 | D50: Model Registry | E50: Core | F50: oss | G50: Apache-2.0 | H50: 2 | I50: 4 | J50: 20 | K50: 4 | L50: 8 | M50: 200 | N50: 1 | O50: 1.5 | P50: resident | Q50: resident | R50: =INDEX('02_Freq_Weight'!$E$3:$E$9,MATCH(Q50,'02_Freq_Weight'!$A$3:$A$9,0)) | S50: 0.5 | T50: 730 | U50: 0.15 | V50: 0.4 | W50: version_tag, registry, audit_trail, artifact_sign | X50: พ.ร.บ. คอมพิวเตอร์ 2550/2560; พ.ร.บ. ไซเบอร์ 2562; มาตรฐานข้อมูลเปิดภาครัฐ; พ.ร.บ. ปฏิบัติราชการทางอิเล็กทรอนิกส์ 2565; ขมธอ. ลายมือชื่อ/เอกสารอิเล็กทรอนิกส์; ITA (ป.ป.ช.); มาตรฐานขั้นต่ำ 2566; กรอบมาตรฐานไซเบอร์ 2564; มาตรฐานเว็บไซต์ 2568; PDPA 2562 | Y50: ISO 22301:2019; ISO/IEC 27001:2022; ISO/IEC 27018; ISO/IEC 27701; ISO/IEC 42001:2023; NIST SP 800-161r1; NIST SP 800-53r5; NIST CSF 2.0; NIST SSDF (SP 800-218); OWASP Top 10:2025; SLSA v1.0; SOC 2 (TSC) | Z50: C-LOG-AUDIT, C-SC-REGISTRY, C-SC-SIGN | AA50: C-AI-GOV, C-LOG-90, C-OPS-BCP, C-SC-PIN, C-SDLC-TRACE, C-WEB-SELF | AB50: 9 | AC50: Azure ML; AWS SageMaker Model Registry; Databricks Model Registry; Weights & Biases; Neptune.ai | AE50: MLflow tracking server เป็น Flask/Gunicorn ใช้ RAM ~500 MB - 2 GB; artifact store ควรชี้ไป MinIO/S3 ไม่ใช่ local disk | AF50: จำเป็นเมื่อต้อง Track Experiment และ Model Version; ถ้าโครงการมีขั้นตอนประเมินผลโมเดล (Model / LLM Evaluation) ควรผูกผลการประเมินเข้ากับ Model Registry เพื่อตรวจย้อนหลังได้ว่า เวอร์ชันไหนผ่านเกณฑ์อะไร
A51: llm-eval | B51: LLM Evaluation Runner (AI/LLM Eval Harness) | C51: 4 | D51: AI Model Evaluation | E51: Optional | F51: oss | G51: MIT | H51: 4 | I51: 8 | J51: 40 | K51: 8 | L51: 16 | M51: 120 | N51: 0 | O51: 0 | P51: load | Q51: per_build | R51: =INDEX('02_Freq_Weight'!$E$3:$E$9,MATCH(Q51,'02_Freq_Weight'!$A$3:$A$9,0)) | S51: 0.2 | T51: 365 | U51: 0.1 | V51: 0.3 | W51: unit_test, integration_test, quality_gate | X51: - | Y51: ISO/IEC 25010:2023; ISO/IEC 27001:2022; ISO/IEC 27034; ISO/IEC 42001:2023; NIST SSDF (SP 800-218); OWASP SAMM 2; OWASP Top 10:2025; SOC 2 (TSC) | Z51: C-SDLC-TEST | AA51: C-AI-GOV, C-SDLC-QUALITY, C-SDLC-REVIEW, C-SDLC-THREAT | AB51: 5 | AC51: Azure ML Quality Gates; SageMaker Model Monitor; Databricks Model Serving | AE51: การประเมิน LLM ผ่าน API ภายนอกใช้ CPU/RAM ไม่มาก (I/O bound) แต่ถ้ารัน model ในเครื่องต้องมี GPU; batch eval ขนาดกลางใช้ 4 vCPU / 8 GB | AF51: ถ้าใช้ AI Model-as-a-Service ภายนอก งานนี้จะเป็น I/O bound ใช้ CPU/RAM ไม่มาก แต่ต้อง whitelist ปลายทางที่ Proxy; ข้อควรระวังคือมักถูกวางรวมกับ Load Test, Search Engine และ Object Storage บนเครื่องเดียว จึงต้องคุมด้วยตารางเวลาไม่ให้รันทับกัน
A52: gpu-training | B52: GPU Training Node (Model Training / Fine-tune) | C52: 3 | D52: AI Model Training | E52: Optional | F52: oss | G52: N/A | H52: 8 | I52: 16 | J52: 200 | K52: 16 | L52: 64 | M52: 1000 | N52: 0 | O52: 0 | P52: load | Q52: weekly | R52: =INDEX('02_Freq_Weight'!$E$3:$E$9,MATCH(Q52,'02_Freq_Weight'!$A$3:$A$9,0)) | S52: 5 | T52: 180 | U52: 0.1 | V52: 0.4 | W52: build | X52: - | Y52: CIS Benchmarks; NIST SSDF (SP 800-218); OWASP Top 10:2025; SLSA v1.0 | Z52: - | AA52: C-SC-IMG, C-SC-PIN | AB52: 2 | AC52: Azure ML Compute; AWS SageMaker Training; Google Vertex AI; Databricks | AE52: Training node ต้องมี GPU (เช่น H100/A100) + RAM >= 2 เท่าของ VRAM + NVMe สำหรับ dataset; CPU 8 core ขึ้นไปเพื่อป้อนข้อมูลไม่ให้ GPU รอ | AF52: สภาพแวดล้อมของหน่วยงานหลายแห่งไม่รองรับ GPU ทำให้ต้องแยก Training Node ออกไปภายนอก — ข้อจำกัดนี้ต้องระบุใน TOR ให้ชัดว่าใครรับผิดชอบจัดหา GPU และเชื่อมต่อกันอย่างไร ไม่งั้นจะกลายเป็นข้อพิพาทตอนส่งมอบ
A53: redis | B53: Redis (Cache สำหรับเครื่องมือ CI/CD) | C53: 5 | D53: Supporting Cache | E53: Optional | F53: oss | G53: RSALv2 / SSPL | H53: 1 | I53: 2 | J53: 10 | K53: 2 | L53: 4 | M53: 30 | N53: 1 | O53: 1 | P53: resident | Q53: resident | R53: =INDEX('02_Freq_Weight'!$E$3:$E$9,MATCH(Q53,'02_Freq_Weight'!$A$3:$A$9,0)) | S53: 0.05 | T53: 30 | U53: 0.1 | V53: 0.2 | W53: monitoring | X53: พ.ร.บ. ไซเบอร์ 2562; มาตรฐานคลาวด์ 2567; กรอบมาตรฐานไซเบอร์ 2564; มาตรฐานเว็บไซต์ 2568; ประกาศ PDPC แจ้งเหตุละเมิด 2565 | Y53: ISO/IEC 42001:2023; NIST SP 800-207; NIST CSF 2.0; OWASP Top 10:2025; SOC 2 (TSC) | Z53: C-OPS-MONITOR | AA53: C-AI-DRIFT, C-LOG-SIEM | AB53: 3 | AC53: Azure Cache for Redis; AWS ElastiCache; Redis Enterprise | AE53: Redis เก็บข้อมูลใน RAM ทั้งหมด — ขนาด RAM = ขนาด dataset × 1.5 (เผื่อ fragmentation + COW ตอน BGSAVE); ต้องตั้ง maxmemory-policy | AF53: Harbor, Argo CD และ GitLab ต่างต้องใช้ Redis — ควรใช้ instance เดียวแล้วแยก database index แทนการรัน 3 instance ซึ่งประหยัด RAM ได้ 2-3 GB
A54: rabbitmq | B54: RabbitMQ (Message Queue) | C54: 5 | D54: Supporting Queue | E54: Optional | F54: oss | G54: MPL-2.0 | H54: 2 | I54: 4 | J54: 15 | K54: 2 | L54: 4 | M54: 60 | N54: 1 | O54: 1.5 | P54: resident | Q54: resident | R54: =INDEX('02_Freq_Weight'!$E$3:$E$9,MATCH(Q54,'02_Freq_Weight'!$A$3:$A$9,0)) | S54: 0.1 | T54: 30 | U54: 0.1 | V54: 0.2 | W54: monitoring | X54: พ.ร.บ. ไซเบอร์ 2562; มาตรฐานคลาวด์ 2567; กรอบมาตรฐานไซเบอร์ 2564; มาตรฐานเว็บไซต์ 2568; ประกาศ PDPC แจ้งเหตุละเมิด 2565 | Y54: ISO/IEC 42001:2023; NIST SP 800-207; NIST CSF 2.0; OWASP Top 10:2025; SOC 2 (TSC) | Z54: C-OPS-MONITOR | AA54: C-AI-DRIFT, C-LOG-SIEM | AB54: 3 | AC54: Azure Service Bus; AWS SQS; IBM MQ | AE54: RabbitMQ ต้องมี disk free >= 1-2 GB (disk_free_limit) ไม่งั้นจะ block publisher; RAM watermark ค่าปริยาย 40% ของ RAM เครื่อง | AF54: โดยปกติเป็นของฝั่ง Application ไม่ใช่ CI/CD แต่ต้องนับรวมถ้าถูกวางบนเครื่องเดียวกับ Pipeline เพราะ RAM watermark ค่าปริยาย 40% ของเครื่องจะกินโควตาของงาน Build ไปด้วย
A55: sftp-nfs | B55: SFTP / NFS File Server | C55: 5 | D55: File Transfer | E55: Optional | F55: oss | G55: BSD | H55: 1 | I55: 2 | J55: 20 | K55: 2 | L55: 4 | M55: 500 | N55: 1 | O55: 0.3 | P55: resident | Q55: resident | R55: =INDEX('02_Freq_Weight'!$E$3:$E$9,MATCH(Q55,'02_Freq_Weight'!$A$3:$A$9,0)) | S55: 0.5 | T55: 180 | U55: 0.05 | V55: 0.25 | W55: backup_dr, registry | X55: พ.ร.บ. ไซเบอร์ 2562; มสพร. 11-2566 เว็บไซต์ภาครัฐ 3.0; ขมธอ. การใช้บริการคลาวด์; มาตรฐานขั้นต่ำ 2566; กรอบมาตรฐานไซเบอร์ 2564; มาตรฐานเว็บไซต์ 2568; พ.ร.ฎ. วิธีการแบบปลอดภัย 2553 | Y55: CIS Controls v8.1; ISO 22301:2019; ISO/IEC 27001:2022; ISO/IEC 42001:2023; NIST SP 800-161r1; NIST SP 800-53r5; NIST CSF 2.0; OWASP Top 10:2025; SOC 2 (TSC) | Z55: C-OPS-BACKUP, C-SC-REGISTRY | AA55: C-AI-GOV, C-OPS-BCP | AB55: 4 | AC55: Azure Files; AWS EFS; NetApp | AE55: sshd/nfsd กิน RAM น้อย (< 300 MB) แต่ throughput ขึ้นกับ disk I/O และ network; ต้องเผื่อ page cache | AF55: มักถูกวางรวมกับ Object Storage และ Container Runtime บนเครื่องเดียว ต้องตรวจว่า RAM เหลือพอ สำหรับ metadata cache ของ Object Storage หรือไม่ เพราะ page cache ของ NFS แย่งพื้นที่เดียวกัน
A56: scancode | B56: ScanCode Toolkit / License Finder (License Compliance แบบ Permissive) | C56: 2 | D56: License Compliance | E56: Optional | F56: oss | G56: Apache-2.0 | H56: 2 | I56: 4 | J56: 15 | K56: 2 | L56: 4 | M56: 40 | N56: 0 | O56: 0 | P56: ci_seq | Q56: per_build | R56: =INDEX('02_Freq_Weight'!$E$3:$E$9,MATCH(Q56,'02_Freq_Weight'!$A$3:$A$9,0)) | S56: 0.02 | T56: 730 | U56: 0.05 | V56: 0.1 | W56: license, sbom | X56: มาตรฐานขั้นต่ำ 2566 | Y56: CSA CCM v4 / STAR; CycloneDX / ECMA-424; ISO/IEC 27001:2022; NIST SP 800-161r1; NIST SSDF (SP 800-218); OWASP Top 10:2025; SLSA v1.0; SPDX / ISO 5962 | Z56: C-SC-LICENSE, C-SC-SBOM | AA56: - | AB56: 2 | AC56: BlackDuck License Compliance; FOSSA Enterprise; Mend (WhiteSource); Snyk License | AD56: License Finder; Licensee; REUSE; Trivy license scan | AE56: ScanCode เป็น Python CLI สแกนไฟล์หา license expression; RAM 1-2 GB ต่อ repo ขนาดกลาง ทำงานแบบ ephemeral | AF56: ทางเลือกแทน FOSSology เมื่อโครงการห้ามใช้ GPL/AGPL — ScanCode เองเป็น Apache-2.0 จึงใช้ได้ และเบากว่ามากเพราะไม่ต้องมี web app กับฐานข้อมูลแยก
A57: cbomkit | B57: CBOMkit / Crypto Inventory Scanner (Crypto Bill of Materials) | C57: 4 | D57: Crypto Inventory | E57: Optional | F57: oss | G57: Apache-2.0 | H57: 2 | I57: 4 | J57: 10 | K57: 2 | L57: 4 | M57: 20 | N57: 0 | O57: 0 | P57: async | Q57: weekly | R57: =INDEX('02_Freq_Weight'!$E$3:$E$9,MATCH(Q57,'02_Freq_Weight'!$A$3:$A$9,0)) | S57: 0.02 | T57: 730 | U57: 0.05 | V57: 0.1 | W57: crypto_agility, sbom | X57: มาตรฐานขั้นต่ำ 2566 | Y57: CSA CCM v4 / STAR; CycloneDX / ECMA-424; NIST SP 800-161r1; NIST PQC Migration; NIST SSDF (SP 800-218); OWASP Top 10:2025; SLSA v1.0; SPDX / ISO 5962 | Z57: C-SC-SBOM | AA57: C-CRY-PQC | AB57: 2 | AC57: Venafi TLS Protect; Entrust Crypto Discovery; Keyfactor Command | AD57: Trivy CBOM; cryptography-inventory; sonar-cryptography | AE57: สแกนซอร์สโค้ดและ artifact หาอัลกอริทึมเข้ารหัสที่ใช้อยู่ แล้วออกเป็น CBOM รูปแบบ CycloneDX; RAM 1-2 GB ต่อรอบ ทำงานแบบ ephemeral | AF57: ตอบข้อ Post-Quantum / Crypto-Agility โดยตรง และเป็น Apache-2.0 จึงใช้ได้ในโครงการที่ห้าม GPL (ต่างจาก testssl.sh ที่เป็น GPL-2.0) — ควรรันคู่กับการตรวจ TLS ที่ปลายทาง
A58: opensearch | B58: OpenSearch + OpenSearch Dashboards (Log & SIEM แบบ Apache-2.0) | C58: 5 | D58: Log & Audit Store | E58: Core | F58: oss | G58: Apache-2.0 | H58: 4 | I58: 8 | J58: 50 | K58: 8 | L58: 16 | M58: 500 | N58: 1 | O58: 6 | P58: resident | Q58: resident | R58: =INDEX('02_Freq_Weight'!$E$3:$E$9,MATCH(Q58,'02_Freq_Weight'!$A$3:$A$9,0)) | S58: 1.5 | T58: 90 | U58: 0.45 | V58: 0.3 | W58: log_mgmt, audit_trail, siem_alert | X58: พ.ร.บ. คอมพิวเตอร์ 2550/2560; พ.ร.บ. ไซเบอร์ 2562; มสพร. 11-2566 เว็บไซต์ภาครัฐ 3.0; มาตรฐานข้อมูลเปิดภาครัฐ; พ.ร.บ. ปฏิบัติราชการทางอิเล็กทรอนิกส์ 2565; ขมธอ. ลายมือชื่อ/เอกสารอิเล็กทรอนิกส์; ขมธอ. ความมั่นคงปลอดภัยสารสนเทศ; ITA (ป.ป.ช.); มาตรฐานคลาวด์ 2567; มาตรฐานขั้นต่ำ 2566; กรอบมาตรฐานไซเบอร์ 2564; มาตรฐานเว็บไซต์ 2568; PDPA 2562; ประกาศ PDPC แจ้งเหตุละเมิด 2565; ประกาศ PDPC มาตรการความปลอดภัย 2565; พ.ร.ฎ. วิธีการแบบปลอดภัย 2553 | Y58: CIS Controls v8.1; CSA CCM v4 / STAR; ISO 22301:2019; ISO/IEC 27001:2022; ISO/IEC 27002:2022; ISO/IEC 27017; ISO/IEC 27018; ISO/IEC 27701; ISO/IEC 29100; ISO/IEC 42001:2023; NIST SP 800-207; NIST SP 800-53r5; NIST CSF 2.0; NIST SSDF (SP 800-218); OWASP ASVS 5.0; OWASP Top 10:2025; PCI DSS v4.0; SLSA v1.0; SOC 2 (TSC) | Z58: C-LOG-90, C-LOG-AUDIT, C-LOG-CENTRAL | AA58: C-LOG-NOTIFY, C-LOG-SIEM, C-OPS-BCP, C-PRV-BREACH, C-PRV-MEASURE, C-PRV-MINIMIZE, C-SDLC-TRACE, C-WEB-SELF | AB58: 11 | AC58: Splunk Enterprise; Datadog; Microsoft Sentinel; Sumo Logic | AD58: VictoriaLogs; Graylog Open; Loki (AGPL); Quickwit | AE58: OpenSearch เป็น fork ของ Elasticsearch 7.10 ภายใต้ Apache-2.0; heap ไม่ควรเกิน 50% ของ RAM และไม่เกิน 31 GB ตัวเลขนี้รวม Dashboards (Node.js ~1 GB) ไว้ในเครื่องเดียวกันแล้ว | AF58: ทางเลือกแทน Elasticsearch/Kibana เมื่อโครงการห้ามใช้ License แบบ source-available (SSPL / Elastic License) ซึ่งเป็นเงื่อนไขที่พบในโครงการภาครัฐบางแห่ง — มี Security Analytics plugin ทำหน้าที่ SIEM ได้ในตัว
A59: openbao | B59: OpenBao (Secret Management แบบ MPL-2.0) | C59: 5 | D59: Secret Management | E59: Optional | F59: oss | G59: MPL-2.0 | H59: 2 | I59: 4 | J59: 20 | K59: 2 | L59: 4 | M59: 60 | N59: 1 | O59: 1 | P59: resident | Q59: resident | R59: =INDEX('02_Freq_Weight'!$E$3:$E$9,MATCH(Q59,'02_Freq_Weight'!$A$3:$A$9,0)) | S59: 0.05 | T59: 2555 | U59: 0.1 | V59: 0.15 | W59: secret_mgmt, iam_mfa, audit_trail | X59: พ.ร.บ. คอมพิวเตอร์ 2550/2560; พ.ร.บ. ไซเบอร์ 2562; มสพร. 11-2566 เว็บไซต์ภาครัฐ 3.0; มาตรฐานข้อมูลเปิดภาครัฐ; พ.ร.บ. ปฏิบัติราชการทางอิเล็กทรอนิกส์ 2565; ขมธอ. การใช้บริการคลาวด์; ขมธอ. ลายมือชื่อ/เอกสารอิเล็กทรอนิกส์; ขมธอ. ความมั่นคงปลอดภัยสารสนเทศ; ITA (ป.ป.ช.); มาตรฐานคลาวด์ 2567; มาตรฐานขั้นต่ำ 2566; กรอบมาตรฐานไซเบอร์ 2564; มาตรฐานเว็บไซต์ 2568; PDPA 2562; ประกาศ PDPC มาตรการความปลอดภัย 2565; พ.ร.ฎ. วิธีการแบบปลอดภัย 2553 | Y59: CIS Benchmarks; CIS Controls v8.1; CSA CCM v4 / STAR; ISO 22301:2019; ISO/IEC 27001:2022; ISO/IEC 27002:2022; ISO/IEC 27017; ISO/IEC 27018; ISO/IEC 27701; ISO/IEC 29100; ISO/IEC 42001:2023; NIST SP 800-207; NIST SP 800-53r5; NIST SP 800-63B; NIST CSF 2.0; NIST SSDF (SP 800-218); OWASP API Top 10:2023; OWASP ASVS 5.0; OWASP MASVS; OWASP Top 10:2025; SLSA v1.0; SOC 2 (TSC) | Z59: C-CRY-KEY, C-IAM-MFA, C-LOG-AUDIT | AA59: C-APP-AUTHN, C-IAM-LEAST, C-IAM-REMOTE, C-LOG-90, C-OPS-BCP, C-PRV-MEASURE, C-SDLC-SECRET, C-SDLC-TRACE, C-WEB-SELF | AB59: 12 | AC59: HashiCorp Vault Enterprise; Azure Key Vault; AWS Secrets Manager; CyberArk Conjur | AD59: Infisical; SOPS + age; Sealed Secrets | AE59: OpenBao เป็น fork ของ Vault 1.14 ภายใต้ MPL-2.0 ใช้ resource เท่ากัน; ต้องมี storage backend (Raft) และเปิด Audit Device | AF59: ทางเลือกแทน HashiCorp Vault เมื่อโครงการห้ามใช้ License แบบ source-available (BUSL) — MPL-2.0 เป็น copyleft อ่อน ใช้เป็นบริการแยกได้โดยไม่ลามไปยังโค้ดของโครงการ
A60: azure-devops | B60: Azure DevOps (Cloud CI/CD Platform) | C60: 1 | D60: Cloud CI/CD Platform | E60: Core | F60: commercial | G60: Proprietary (SaaS) | H60: 0 | I60: 0 | J60: 0 | K60: 0 | L60: 0 | M60: 0 | N60: 0 | O60: 0 | P60: ci_seq | Q60: per_commit | R60: =INDEX('02_Freq_Weight'!$E$3:$E$9,MATCH(Q60,'02_Freq_Weight'!$A$3:$A$9,0)) | S60: 0.02 | T60: 365 | U60: 0.1 | V60: 0.2 | W60: git_scm, webhook, branch_protection, pipeline, audit_trail, quality_gate, deploy_strategy | X60: พ.ร.บ. คอมพิวเตอร์ 2550/2560; พ.ร.บ. ไซเบอร์ 2562; มาตรฐานข้อมูลเปิดภาครัฐ; พ.ร.บ. ปฏิบัติราชการทางอิเล็กทรอนิกส์ 2565; ขมธอ. ลายมือชื่อ/เอกสารอิเล็กทรอนิกส์; ITA (ป.ป.ช.); มาตรฐานขั้นต่ำ 2566; กรอบมาตรฐานไซเบอร์ 2564; มาตรฐานเว็บไซต์ 2568; PDPA 2562 | Y60: CIS Controls v8.1; ISO 22301:2019; ISO/IEC 27001:2022; ISO/IEC 27018; ISO/IEC 27034; ISO/IEC 27701; ISO/IEC 42001:2023; NIST SP 800-53r5; NIST CSF 2.0; NIST SSDF (SP 800-218); OWASP SAMM 2; OWASP Top 10:2025; SLSA v1.0; SOC 2 (TSC) | Z60: C-LOG-AUDIT, C-SDLC-REVIEW | AA60: C-AI-GOV, C-LOG-90, C-OPS-BCP, C-OPS-DEPLOY, C-SDLC-THREAT, C-SDLC-TRACE, C-WEB-SELF | AB60: 9 | AC60: GitHub Enterprise Cloud; GitLab SaaS Ultimate | AD60: GitLab CE; Gitea + Jenkins | AE60: Managed service — no self-hosted resource needed; pricing per user/pipeline minute | AF60: CI/CD แบบ managed ของ Microsoft รวม Git, Boards, Pipelines, Artifacts, Test Plans ในที่เดียว รองรับ hybrid agent สำหรับ on-premise build
A61: github-actions | B61: GitHub Actions (Cloud CI/CD) | C61: 1 | D61: Cloud CI/CD Platform | E61: Core | F61: commercial | G61: Proprietary (SaaS / Free tier) | H61: 0 | I61: 0 | J61: 0 | K61: 0 | L61: 0 | M61: 0 | N61: 0 | O61: 0 | P61: ci_seq | Q61: per_commit | R61: =INDEX('02_Freq_Weight'!$E$3:$E$9,MATCH(Q61,'02_Freq_Weight'!$A$3:$A$9,0)) | S61: 0.02 | T61: 90 | U61: 0.1 | V61: 0.2 | W61: pipeline, webhook, build, deploy_strategy, audit_trail | X61: พ.ร.บ. คอมพิวเตอร์ 2550/2560; พ.ร.บ. ไซเบอร์ 2562; มาตรฐานข้อมูลเปิดภาครัฐ; พ.ร.บ. ปฏิบัติราชการทางอิเล็กทรอนิกส์ 2565; ขมธอ. ลายมือชื่อ/เอกสารอิเล็กทรอนิกส์; ITA (ป.ป.ช.); มาตรฐานขั้นต่ำ 2566; กรอบมาตรฐานไซเบอร์ 2564; มาตรฐานเว็บไซต์ 2568; PDPA 2562 | Y61: CIS Benchmarks; CIS Controls v8.1; ISO 22301:2019; ISO/IEC 27001:2022; ISO/IEC 27018; ISO/IEC 27701; ISO/IEC 42001:2023; NIST SP 800-53r5; NIST CSF 2.0; NIST SSDF (SP 800-218); OWASP Top 10:2025; SLSA v1.0; SOC 2 (TSC) | Z61: C-LOG-AUDIT | AA61: C-LOG-90, C-OPS-BCP, C-OPS-DEPLOY, C-SC-IMG, C-SC-PIN, C-SDLC-TRACE, C-WEB-SELF | AB61: 8 | AC61: Azure DevOps; AWS CodePipeline; GitLab SaaS | AD61: Woodpecker CI; Forgejo Actions; Jenkins | AE61: Managed — 2,000 free minutes/month (public repos unlimited); supports self-hosted runners for on-prem builds | AF61: CI/CD ของ GitHub; ecosystem ใหญ่ที่สุด (Marketplace 20K+ actions), รองรับ matrix builds, reusable workflows, OIDC federation
A62: aws-codecommit-pipeline | B62: AWS CodePipeline + CodeBuild + CodeCommit | C62: 1 | D62: Cloud CI/CD Platform | E62: Core | F62: commercial | G62: Proprietary (SaaS) | H62: 0 | I62: 0 | J62: 0 | K62: 0 | L62: 0 | M62: 0 | N62: 0 | O62: 0 | P62: ci_seq | Q62: per_commit | R62: =INDEX('02_Freq_Weight'!$E$3:$E$9,MATCH(Q62,'02_Freq_Weight'!$A$3:$A$9,0)) | S62: 0.02 | T62: 365 | U62: 0.1 | V62: 0.2 | W62: git_scm, webhook, pipeline, build, deploy_strategy, audit_trail | X62: พ.ร.บ. คอมพิวเตอร์ 2550/2560; พ.ร.บ. ไซเบอร์ 2562; มาตรฐานข้อมูลเปิดภาครัฐ; พ.ร.บ. ปฏิบัติราชการทางอิเล็กทรอนิกส์ 2565; ขมธอ. ลายมือชื่อ/เอกสารอิเล็กทรอนิกส์; ITA (ป.ป.ช.); มาตรฐานขั้นต่ำ 2566; กรอบมาตรฐานไซเบอร์ 2564; มาตรฐานเว็บไซต์ 2568; PDPA 2562 | Y62: CIS Benchmarks; CIS Controls v8.1; ISO 22301:2019; ISO/IEC 27001:2022; ISO/IEC 27018; ISO/IEC 27701; ISO/IEC 42001:2023; NIST SP 800-53r5; NIST CSF 2.0; NIST SSDF (SP 800-218); OWASP SAMM 2; OWASP Top 10:2025; SLSA v1.0; SOC 2 (TSC) | Z62: C-LOG-AUDIT | AA62: C-LOG-90, C-OPS-BCP, C-OPS-DEPLOY, C-SC-IMG, C-SC-PIN, C-SDLC-REVIEW, C-SDLC-TRACE, C-WEB-SELF | AB62: 9 | AC62: Azure DevOps; GitLab SaaS Ultimate; GitHub Enterprise Cloud | AD62: GitLab CE + Jenkins; Gitea + Woodpecker | AE62: Managed — pay per pipeline execution minute and build compute; integrates with all AWS services | AF62: CI/CD suite ของ AWS รวม source repo, build, deploy pipeline; รองรับ cross-account deployment, CloudFormation/CDK integration
A63: gcp-cloud-build | B63: Google Cloud Build + Source Repositories | C63: 1 | D63: Cloud CI/CD Platform | E63: Core | F63: commercial | G63: Proprietary (SaaS) | H63: 0 | I63: 0 | J63: 0 | K63: 0 | L63: 0 | M63: 0 | N63: 0 | O63: 0 | P63: ci_seq | Q63: per_commit | R63: =INDEX('02_Freq_Weight'!$E$3:$E$9,MATCH(Q63,'02_Freq_Weight'!$A$3:$A$9,0)) | S63: 0.02 | T63: 365 | U63: 0.1 | V63: 0.2 | W63: pipeline, build, webhook, image_build, deploy_strategy | X63: พ.ร.บ. ไซเบอร์ 2562; มาตรฐานข้อมูลเปิดภาครัฐ; พ.ร.บ. ปฏิบัติราชการทางอิเล็กทรอนิกส์ 2565 | Y63: CIS Benchmarks; CIS Controls v8.1; NIST SSDF (SP 800-218); OWASP Top 10:2025; SLSA v1.0; SOC 2 (TSC) | Z63: C-SC-IMG | AA63: C-OPS-DEPLOY, C-SC-PIN, C-SDLC-TRACE | AB63: 4 | AC63: Azure DevOps; AWS CodePipeline; GitLab SaaS | AD63: Jenkins + Gitea; Tekton + Gitea | AE63: Managed — 120 free build-minutes/day; supports custom workers, multi-step builds, and Cloud Deploy for CD | AF63: CI/CD ของ GCP รองรับ Buildpacks, kaniko builds, Binary Authorization integration, Cloud Deploy สำหรับ progressive delivery
A64: azure-container-registry | B64: Azure Container Registry (ACR) | C64: 4 | D64: Cloud Container Registry | E64: Core | F64: commercial | G64: Proprietary (SaaS) | H64: 0 | I64: 0 | J64: 0 | K64: 0 | L64: 0 | M64: 0 | N64: 0 | O64: 0 | P64: ci_seq | Q64: per_build | R64: =INDEX('02_Freq_Weight'!$E$3:$E$9,MATCH(Q64,'02_Freq_Weight'!$A$3:$A$9,0)) | S64: 0.5 | T64: 365 | U64: 0.1 | V64: 0.3 | W64: registry, container_scan, artifact_sign | X64: ขมธอ. ลายมือชื่อ/เอกสารอิเล็กทรอนิกส์ | Y64: CIS Benchmarks; ISO/IEC 42001:2023; NIST SP 800-161r1; NIST SSDF (SP 800-218); OWASP Top 10:2025; PCI DSS v4.0; SLSA v1.0 | Z64: C-SC-CONTAINER, C-SC-REGISTRY, C-SC-SIGN | AA64: C-AI-GOV | AB64: 4 | AC64: AWS ECR; Google Artifact Registry; JFrog Artifactory Cloud | AD64: Harbor; GitLab Container Registry | AE64: Managed registry — pricing per storage GB + network egress; Premium SKU supports geo-replication and private link | AF64: Container registry ของ Azure รองรับ Helm charts, OCI artifacts, content trust (Notary), integrated vulnerability scanning
A65: aws-ecr | B65: Amazon Elastic Container Registry (ECR) | C65: 4 | D65: Cloud Container Registry | E65: Core | F65: commercial | G65: Proprietary (SaaS) | H65: 0 | I65: 0 | J65: 0 | K65: 0 | L65: 0 | M65: 0 | N65: 0 | O65: 0 | P65: ci_seq | Q65: per_build | R65: =INDEX('02_Freq_Weight'!$E$3:$E$9,MATCH(Q65,'02_Freq_Weight'!$A$3:$A$9,0)) | S65: 0.5 | T65: 365 | U65: 0.1 | V65: 0.3 | W65: registry, container_scan | X65: - | Y65: CIS Benchmarks; ISO/IEC 42001:2023; NIST SP 800-161r1; OWASP Top 10:2025; PCI DSS v4.0 | Z65: C-SC-CONTAINER, C-SC-REGISTRY | AA65: C-AI-GOV | AB65: 3 | AC65: Azure Container Registry; Google Artifact Registry; JFrog Artifactory Cloud | AD65: Harbor; Zot | AE65: Managed registry — pricing per storage GB; supports image scanning, lifecycle policies, cross-region replication | AF65: Container registry ของ AWS รองรับ ECR Enhanced Scanning (Inspector), lifecycle policies, cross-account access
A66: gcp-artifact-registry | B66: Google Artifact Registry (GAR) | C66: 4 | D66: Cloud Container Registry | E66: Core | F66: commercial | G66: Proprietary (SaaS) | H66: 0 | I66: 0 | J66: 0 | K66: 0 | L66: 0 | M66: 0 | N66: 0 | O66: 0 | P66: ci_seq | Q66: per_build | R66: =INDEX('02_Freq_Weight'!$E$3:$E$9,MATCH(Q66,'02_Freq_Weight'!$A$3:$A$9,0)) | S66: 0.5 | T66: 365 | U66: 0.1 | V66: 0.3 | W66: registry, container_scan, artifact_sign | X66: ขมธอ. ลายมือชื่อ/เอกสารอิเล็กทรอนิกส์ | Y66: CIS Benchmarks; ISO/IEC 42001:2023; NIST SP 800-161r1; NIST SSDF (SP 800-218); OWASP Top 10:2025; PCI DSS v4.0; SLSA v1.0 | Z66: C-SC-CONTAINER, C-SC-REGISTRY, C-SC-SIGN | AA66: C-AI-GOV | AB66: 4 | AC66: Azure Container Registry; AWS ECR; JFrog Artifactory Cloud | AD66: Harbor; Zot | AE66: Managed registry — supports Docker, Maven, npm, Python, Apt, Yum packages; integrates with Binary Authorization | AF66: Artifact registry ของ GCP รองรับ multi-format (ไม่ใช่แค่ container), Vulnerability scanning (On-Demand/Automatic), SLSA provenance
A67: azure-kubernetes-service | B67: Azure Kubernetes Service (AKS) | C67: 5 | D67: Cloud Container Orchestration | E67: Core | F67: commercial | G67: Proprietary (SaaS) | H67: 0 | I67: 0 | J67: 0 | K67: 0 | L67: 0 | M67: 0 | N67: 0 | O67: 0 | P67: resident | Q67: resident | R67: =INDEX('02_Freq_Weight'!$E$3:$E$9,MATCH(Q67,'02_Freq_Weight'!$A$3:$A$9,0)) | S67: 0.1 | T67: 90 | U67: 0.1 | V67: 0.25 | W67: orchestration, deploy_strategy, runtime_security, monitoring | X67: พ.ร.บ. ไซเบอร์ 2562; ขมธอ. การใช้บริการคลาวด์; ขมธอ. ความมั่นคงปลอดภัยสารสนเทศ; มาตรฐานคลาวด์ 2567; กรอบมาตรฐานไซเบอร์ 2564; มาตรฐานเว็บไซต์ 2568; PDPA 2562; ประกาศ PDPC แจ้งเหตุละเมิด 2565 | Y67: CIS Benchmarks; CIS Controls v8.1; CSA CCM v4 / STAR; ISO/IEC 27001:2022; ISO/IEC 27017; ISO/IEC 42001:2023; NIST SP 800-207; NIST SP 800-53r5; NIST CSF 2.0; OWASP Top 10:2025; SOC 2 (TSC) | Z67: C-AI-DRIFT, C-OPS-DEPLOY, C-OPS-MONITOR, C-OPS-RUNTIME | AA67: C-IAM-LEAST, C-LOG-SIEM | AB67: 6 | AC67: AWS EKS; Google GKE; Red Hat OpenShift Dedicated | AD67: K3s; MicroK8s; Kubernetes (self-managed) | AE67: Managed K8s — control plane free, pay for worker nodes; supports spot/burstable VMs | AF67: Kubernetes managed ของ Azure รองรับ Azure Policy, Azure AD integration, KEDA auto-scaling, Defender for Containers
... A74: gcp-cloud-operations | B74: Google Cloud Operations (Logging + Monitoring + Trace) | C74: 6 | D74: Cloud Monitoring | E74: Core | F74: commercial | G74: Proprietary (SaaS) | H74: 0 | I74: 0 | J74: 0 | K74: 0 | L74: 0 | M74: 0 | N74: 0 | O74: 0 | P74: resident | Q74: resident | R74: =INDEX('02_Freq_Weight'!$E$3:$E$9,MATCH(Q74,'02_Freq_Weight'!$A$3:$A$9,0)) | S74: 1 | T74: 90 | U74: 0.1 | V74: 0.3 | W74: monitoring, log_mgmt, audit_trail, siem_alert | X74: พ.ร.บ. คอมพิวเตอร์ 2550/2560; พ.ร.บ. ไซเบอร์ 2562; มสพร. 11-2566 เว็บไซต์ภาครัฐ 3.0; มาตรฐานข้อมูลเปิดภาครัฐ; พ.ร.บ. ปฏิบัติราชการทางอิเล็กทรอนิกส์ 2565; ขมธอ. ลายมือชื่อ/เอกสารอิเล็กทรอนิกส์; ขมธอ. ความมั่นคงปลอดภัยสารสนเทศ; ITA (ป.ป.ช.); มาตรฐานคลาวด์ 2567; มาตรฐานขั้นต่ำ 2566; กรอบมาตรฐานไซเบอร์ 2564; มาตรฐานเว็บไซต์ 2568; PDPA 2562; ประกาศ PDPC แจ้งเหตุละเมิด 2565; ประกาศ PDPC มาตรการความปลอดภัย 2565; พ.ร.ฎ. วิธีการแบบปลอดภัย 2553 | Y74: CIS Controls v8.1; CSA CCM v4 / STAR; ISO 22301:2019; ISO/IEC 27001:2022; ISO/IEC 27002:2022; ISO/IEC 27017; ISO/IEC 27018; ISO/IEC 27701; ISO/IEC 29100; ISO/IEC 42001:2023; NIST SP 800-207; NIST SP 800-53r5; NIST CSF 2.0; NIST SSDF (SP 800-218); OWASP ASVS 5.0; OWASP Top 10:2025; PCI DSS v4.0; SLSA v1.0; SOC 2 (TSC) | Z74: C-LOG-90, C-LOG-AUDIT, C-LOG-CENTRAL, C-LOG-SIEM, C-OPS-MONITOR | AA74: C-AI-DRIFT, C-LOG-NOTIFY, C-OPS-BCP, C-PRV-BREACH, C-PRV-MEASURE, C-PRV-MINIMIZE, C-SDLC-TRACE, C-WEB-SELF | AB74: 13 | AC74: Azure Monitor; AWS CloudWatch; Datadog; Splunk Cloud | AD74: Prometheus + Grafana + Loki; OpenSearch | AE74: Managed — first 50 GB/month free for logs; integrates with Chronicle SIEM for security operations | AF74: Observability ของ GCP; Cloud Logging + Cloud Monitoring + Cloud Trace; รองรับ Chronicle (SIEM) และ Security Command Center
A76: สรุป | H76: =SUM(H3:H74) | I76: =SUM(I3:I74) | J76: =SUM(J3:J74)
A77: ผลรวมข้างบนคือ 'ถ้าแยกทุกเครื่องมือคนละเครื่อง' ซึ่งไม่ใช่วิธีที่ใช้จริง — ดูการคำนวณกรณีแชร์เครื่องที่ชีท 03 และ 04
A79: หมายเหตุที่มาของข้อมูล
A80: • โครงสร้าง 6 Stage และรายชื่อเครื่องมือ: CI/CD Service Blueprint V0.2
A81: • ข้อกำหนด compliance: แนวปฏิบัติการพัฒนาซอฟต์แวร์ กฎระเบียบเกี่ยวข้องทางไซเบอร์และสถาปัตยกรรมระบบที่มั่นคงปลอดภัย V0.2
A82: • ค่า min/rec: เอกสารติดตั้งของผู้พัฒนาแต่ละเครื่องมือ (ดูคอลัมน์ Sizing Reference) และค่าที่พบจากการใช้งานจริงระดับ UAT/Production ขนาดเล็ก
A83: • ค่าฐานปริมาณข้อมูล: ค่าฐานอ้างอิงสภาพแวดล้อม UAT/Production ขนาดเล็ก: ประมาณ 10 builds/วัน, 1-3 แอปพลิเคชัน, ทีม 5-15 คน, log ระดับ INFO — ใช้ Scale Factor ในโปรแกรมเพื่อขยายตามขนาดจริง
A84: • คอลัมน์ 'มาตรฐานไทย/สากลที่ช่วยตอบ' คำนวณจาก capability ของเครื่องมือเทียบกับข้อกำหนดในชีท 07 จึงเปลี่ยนตามอัตโนมัติเมื่อเพิ่มข้อกำหนดใหม่
A85: • 'ตอบได้ครบด้วยตัวเอง' = capability ทุกตัวที่ข้อกำหนดนั้นต้องการ มีอยู่ในเครื่องมือนี้ตัวเดียว | 'ช่วยตอบบางส่วน' = ต้องมีเครื่องมืออื่นประกอบด้วย
A86: • การมีเครื่องมือครบ ไม่ได้แปลว่าผ่านมาตรฐาน — ยังต้องตั้งค่าให้ถูกต้องและมีหลักฐานการตรวจสอบตามที่กฎหมายกำหนด
A87: • ตัวเลขทั้งหมดเป็น 'ค่าตั้งต้นสำหรับประเมิน' ต้องปรับตามผลวัดจริง (baseline measurement) หลังติดตั้ง 2-4 สัปดาห์

Sheet 02_Freq_Weight
A1: 02 — ชั้นความถี่การรัน และการแปลงเป็นน้ำหนัก (Duty Weight) | C1: w_solo = w_base + w_span x activity_index -> ช่วงเดี่ยว 20% - 60%; บน VM ใช้ w_max(n) ladder
A2: freq_id | B2: ความถี่การรัน | C2: ครั้ง/วัน | D2: activity_index | E2: น้ำหนัก w | F2: เหตุผล / ข้อควรระวัง
A3: resident | B3: รันค้างตลอดเวลา 24/7 (Resident Daemon) | C3: ตลอดเวลา | D3: 1 | E3: ='05_Params'!$B$9+'05_Params'!$B$10*D3 | F3: น้ำหนักสูงสุด 60% เมื่ออยู่เครื่องเดียว ลดตามจำนวนเครื่องมือร่วมเครื่องลงถึงพื้น 20%
A4: per_commit | B4: ทุก Commit / Push (10-30 ครั้ง/วัน) | C4: 10-30 | D4: 0.8 | E4: ='05_Params'!$B$9+'05_Params'!$B$10*D4 | F4: Trigger บ่อย ยังซ้อนทับได้ แต่ถูกจำกัดด้วยเพดาน w_max(n) ของเครื่องนั้น
A5: per_build | B5: ทุก Build / Merge (5-15 ครั้ง/วัน) | C5: 5-15 | D5: 0.65 | E5: ='05_Params'!$B$9+'05_Params'!$B$10*D5 | F5: รันเป็นช่วง ๆ ระหว่างวันทำงาน มีโอกาสซ้อนทับปานกลาง
A6: per_pr | B6: ทุก Pull Request / Quality Gate (3-10 ครั้ง/วัน) | C6: 3-10 | D6: 0.55 | E6: ='05_Params'!$B$9+'05_Params'!$B$10*D6 | F6: ผูกกับรอบ Review ของทีม
A7: nightly | B7: รอบกลางคืน / วันละครั้ง (Nightly) | C7: 1 | D7: 0.35 | E7: ='05_Params'!$B$9+'05_Params'!$B$10*D7 | F7: เช่น DAST Full Scan, Dependency-Check ที่ใช้เวลานาน ย้ายไปรันหลังบ้าน
A8: weekly | B8: รายสัปดาห์ (1-2 ครั้ง/สัปดาห์) | C8: 0.15-0.3 | D8: 0.15 | E8: ='05_Params'!$B$9+'05_Params'!$B$10*D8 | F8: เช่น Performance/Load Test รอบใหญ่, License Audit
A9: on_demand | B9: ตามคำสั่ง / รอบ Release (ไม่กี่ครั้ง/เดือน) | C9: <0.1 | D9: 0 | E9: ='05_Params'!$B$9+'05_Params'!$B$10*D9 | F9: บวกที่ 20% ซึ่งเป็นค่าต่ำสุดของช่วงที่กำหนด เพราะยังต้องกันที่ไว้ให้รันได้
A11: ช่วง 20-60%: เครื่องมือตามคำสั่งบวกที่ 20% (กันที่ไว้ให้รันได้) เครื่องมือ resident บนเครื่องเดียวบวกที่ 60% แล้วลดตามจำนวนเครื่องมือร่วมเครื่อง ลงถึงพื้น 20% เมื่อมี 8 ตัวขึ้นไป

Sheet 03_Colocation_Calc
A1: 03 — เครื่องคำนวณกรณีเครื่องเดียวแชร์หลายเครื่องมือ (Co-location Input) | C1: ใส่ 1 ในคอลัมน์ VM ที่ต้องการติดตั้งเครื่องมือนั้น (0 หรือว่าง = ไม่ติดตั้ง) แล้วดูผลที่ชีท 04 · ค่าเริ่มต้นคือผังอ้างอิง 6 เครื่องสำหรับภาครัฐ — ผังแบบอื่นดูที่ชีท 10 | T1: EDGE-01 | U1: CI-CONTROL-01 | V1: BUILD-AGENT-01 | W1: SEC-TEST-01 | X1: STORE-LOG-01 | Y1: DEPLOY-MON-01 | Z1: (ว่าง) VM07 | AA1: (ว่าง) VM08 | AB1: (ว่าง) VM09 | AC1: (ว่าง) VM10
A2: tool_id | B2: เครื่องมือ | C2: Stage | D2: conc_group | E2: freq_id | F2: min vCPU | G2: min RAM | H2: Idle RAM | I2: Resident | J2: Install GB | K2: GB/วัน | L2: Retention | M2: Index OH | N2: Growth/ปี | O2: น้ำหนัก w | P2: Data GB @H1 | Q2: Data GB @H2 | R2: Data GB @H3 | S2: Data GB @H4 | T2: VM01 | U2: VM02 | V2: VM03 | W2: VM04 | X2: VM05 | Y2: VM06 | Z2: VM07 | AA2: VM08 | AB2: VM09 | AC2: VM10
A3: gitlab-ce | B3: GitLab Community Edition (Self-hosted Git) | C3: 1 | D3: resident | E3: resident | F3: 4 | G3: 8 | H3: 5 | I3: 1 | J3: 40 | K3: 0.05 | L3: 3650 | M3: 0.2 | N3: 0.25 | O3: =INDEX('02_Freq_Weight'!$E$3:$E$9,MATCH(E3,'02_Freq_Weight'!$A$3:$A$9,0)) | P3: =$K3*'05_Params'!$B$4*POWER(1+$N3,'05_Params'!$B$13/12)*MIN($L3,'05_Params'!$B$13*30.44)*(1+$M3) | Q3: =$K3*'05_Params'!$B$4*POWER(1+$N3,'05_Params'!$B$14/12)*MIN($L3,'05_Params'!$B$14*30.44)*(1+$M3) | R3: =$K3*'05_Params'!$B$4*POWER(1+$N3,'05_Params'!$B$15/12)*MIN($L3,'05_Params'!$B$15*30.44)*(1+$M3) | S3: =$K3*'05_Params'!$B$4*POWER(1+$N3,'05_Params'!$B$16/12)*MIN($L3,'05_Params'!$B$16*30.44)*(1+$M3) | T3: 0 | U3: 0 | V3: 0 | W3: 0 | X3: 0 | Y3: 0 | Z3: 0 | AA3: 0 | AB3: 0 | AC3: 0
A4: gitea | B4: Gitea / Forgejo (Lightweight Git) | C4: 1 | D4: resident | E4: resident | F4: 1 | G4: 1 | H4: 0.5 | I4: 1 | J4: 10 | K4: 0.02 | L4: 3650 | M4: 0.1 | N4: 0.25 | O4: =INDEX('02_Freq_Weight'!$E$3:$E$9,MATCH(E4,'02_Freq_Weight'!$A$3:$A$9,0)) | P4: =$K4*'05_Params'!$B$4*POWER(1+$N4,'05_Params'!$B$13/12)*MIN($L4,'05_Params'!$B$13*30.44)*(1+$M4) | Q4: =$K4*'05_Params'!$B$4*POWER(1+$N4,'05_Params'!$B$14/12)*MIN($L4,'05_Params'!$B$14*30.44)*(1+$M4) | R4: =$K4*'05_Params'!$B$4*POWER(1+$N4,'05_Params'!$B$15/12)*MIN($L4,'05_Params'!$B$15*30.44)*(1+$M4) | S4: =$K4*'05_Params'!$B$4*POWER(1+$N4,'05_Params'!$B$16/12)*MIN($L4,'05_Params'!$B$16*30.44)*(1+$M4) | T4: 0 | U4: 1 | V4: 0 | W4: 0 | X4: 0 | Y4: 0 | Z4: 0 | AA4: 0 | AB4: 0 | AC4: 0
A5: github-actions-runner | B5: GitHub Actions Self-hosted Runner | C5: 1 | D5: ci_seq | E5: per_commit | F5: 2 | G5: 4 | H5: 0.2 | I5: 0 | J5: 60 | K5: 0.6 | L5: 30 | M5: 0.05 | N5: 0.2 | O5: =INDEX('02_Freq_Weight'!$E$3:$E$9,MATCH(E5,'02_Freq_Weight'!$A$3:$A$9,0)) | P5: =$K5*'05_Params'!$B$4*POWER(1+$N5,'05_Params'!$B$13/12)*MIN($L5,'05_Params'!$B$13*30.44)*(1+$M5) | Q5: =$K5*'05_Params'!$B$4*POWER(1+$N5,'05_Params'!$B$14/12)*MIN($L5,'05_Params'!$B$14*30.44)*(1+$M5) | R5: =$K5*'05_Params'!$B$4*POWER(1+$N5,'05_Params'!$B$15/12)*MIN($L5,'05_Params'!$B$15*30.44)*(1+$M5) | S5: =$K5*'05_Params'!$B$4*POWER(1+$N5,'05_Params'!$B$16/12)*MIN($L5,'05_Params'!$B$16*30.44)*(1+$M5) | T5: 0 | U5: 0 | V5: 0 | W5: 0 | X5: 0 | Y5: 0 | Z5: 0 | AA5: 0 | AB5: 0 | AC5: 0
A6: jenkins-master | B6: Jenkins Master / Controller | C6: 1 | D6: resident | E6: resident | F6: 2 | G6: 4 | H6: 2 | I6: 1 | J6: 20 | K6: 0.15 | L6: 180 | M6: 0.1 | N6: 0.15 | O6: =INDEX('02_Freq_Weight'!$E$3:$E$9,MATCH(E6,'02_Freq_Weight'!$A$3:$A$9,0)) | P6: =$K6*'05_Params'!$B$4*POWER(1+$N6,'05_Params'!$B$13/12)*MIN($L6,'05_Params'!$B$13*30.44)*(1+$M6) | Q6: =$K6*'05_Params'!$B$4*POWER(1+$N6,'05_Params'!$B$14/12)*MIN($L6,'05_Params'!$B$14*30.44)*(1+$M6) | R6: =$K6*'05_Params'!$B$4*POWER(1+$N6,'05_Params'!$B$15/12)*MIN($L6,'05_Params'!$B$15*30.44)*(1+$M6) | S6: =$K6*'05_Params'!$B$4*POWER(1+$N6,'05_Params'!$B$16/12)*MIN($L6,'05_Params'!$B$16*30.44)*(1+$M6) | T6: 0 | U6: 1 | V6: 0 | W6: 0 | X6: 0 | Y6: 0 | Z6: 0 | AA6: 0 | AB6: 0 | AC6: 0
A7: jenkins-agent | B7: Jenkins Agent / Build Executor (ต่อ 1 Executor) | C7: 1 | D7: resident | E7: per_commit | F7: 2 | G7: 4 | H7: 0.3 | I7: 0 | J7: 60 | K7: 0.8 | L7: 7 | M7: 0.05 | N7: 0.2 | O7: =INDEX('02_Freq_Weight'!$E$3:$E$9,MATCH(E7,'02_Freq_Weight'!$A$3:$A$9,0)) | P7: =$K7*'05_Params'!$B$4*POWER(1+$N7,'05_Params'!$B$13/12)*MIN($L7,'05_Params'!$B$13*30.44)*(1+$M7) | Q7: =$K7*'05_Params'!$B$4*POWER(1+$N7,'05_Params'!$B$14/12)*MIN($L7,'05_Params'!$B$14*30.44)*(1+$M7) | R7: =$K7*'05_Params'!$B$4*POWER(1+$N7,'05_Params'!$B$15/12)*MIN($L7,'05_Params'!$B$15*30.44)*(1+$M7) | S7: =$K7*'05_Params'!$B$4*POWER(1+$N7,'05_Params'!$B$16/12)*MIN($L7,'05_Params'!$B$16*30.44)*(1+$M7) | T7: 0 | U7: 0 | V7: 1 | W7: 0 | X7: 0 | Y7: 0 | Z7: 0 | AA7: 0 | AB7: 0 | AC7: 0
A8: argo-workflows | B8: Argo Workflows (CNCF Graduated) | C8: 1 | D8: resident | E8: resident | F8: 1 | G8: 2 | H8: 1 | I8: 1 | J8: 10 | K8: 0.15 | L8: 90 | M8: 0.1 | N8: 0.2 | O8: =INDEX('02_Freq_Weight'!$E$3:$E$9,MATCH(E8,'02_Freq_Weight'!$A$3:$A$9,0)) | P8: =$K8*'05_Params'!$B$4*POWER(1+$N8,'05_Params'!$B$13/12)*MIN($L8,'05_Params'!$B$13*30.44)*(1+$M8) | Q8: =$K8*'05_Params'!$B$4*POWER(1+$N8,'05_Params'!$B$14/12)*MIN($L8,'05_Params'!$B$14*30.44)*(1+$M8) | R8: =$K8*'05_Params'!$B$4*POWER(1+$N8,'05_Params'!$B$15/12)*MIN($L8,'05_Params'!$B$15*30.44)*(1+$M8) | S8: =$K8*'05_Params'!$B$4*POWER(1+$N8,'05_Params'!$B$16/12)*MIN($L8,'05_Params'!$B$16*30.44)*(1+$M8) | T8: 0 | U8: 0 | V8: 0 | W8: 0 | X8: 0 | Y8: 0 | Z8: 0 | AA8: 0 | AB8: 0 | AC8: 0
A9: opa-conftest | B9: Open Policy Agent / Conftest (Policy-as-Code Gate) | C9: 1 | D9: ci_seq | E9: per_pr | F9: 1 | G9: 1 | H9: 0 | I9: 0 | J9: 5 | K9: 0.01 | L9: 90 | M9: 0.05 | N9: 0.1 | O9: =INDEX('02_Freq_Weight'!$E$3:$E$9,MATCH(E9,'02_Freq_Weight'!$A$3:$A$9,0)) | P9: =$K9*'05_Params'!$B$4*POWER(1+$N9,'05_Params'!$B$13/12)*MIN($L9,'05_Params'!$B$13*30.44)*(1+$M9) | Q9: =$K9*'05_Params'!$B$4*POWER(1+$N9,'05_Params'!$B$14/12)*MIN($L9,'05_Params'!$B$14*30.44)*(1+$M9) | R9: =$K9*'05_Params'!$B$4*POWER(1+$N9,'05_Params'!$B$15/12)*MIN($L9,'05_Params'!$B$15*30.44)*(1+$M9) | S9: =$K9*'05_Params'!$B$4*POWER(1+$N9,'05_Params'!$B$16/12)*MIN($L9,'05_Params'!$B$16*30.44)*(1+$M9) | T9: 0 | U9: 1 | V9: 0 | W9: 0 | X9: 0 | Y9: 0 | Z9: 0 | AA9: 0 | AB9: 0 | AC9: 0
A10: nginx-gateway | B10: Nginx (Reverse Proxy / Webhook Relay) | C10: 1 | D10: resident | E10: resident | F10: 1 | G10: 1 | H10: 0.3 | I10: 1 | J10: 10 | K10: 0.1 | L10: 90 | M10: 0.1 | N10: 0.2 | O10: =INDEX('02_Freq_Weight'!$E$3:$E$9,MATCH(E10,'02_Freq_Weight'!$A$3:$A$9,0)) | P10: =$K10*'05_Params'!$B$4*POWER(1+$N10,'05_Params'!$B$13/12)*MIN($L10,'05_Params'!$B$13*30.44)*(1+$M10) | Q10: =$K10*'05_Params'!$B$4*POWER(1+$N10,'05_Params'!$B$14/12)*MIN($L10,'05_Params'!$B$14*30.44)*(1+$M10) | R10: =$K10*'05_Params'!$B$4*POWER(1+$N10,'05_Params'!$B$15/12)*MIN($L10,'05_Params'!$B$15*30.44)*(1+$M10) | S10: =$K10*'05_Params'!$B$4*POWER(1+$N10,'05_Params'!$B$16/12)*MIN($L10,'05_Params'!$B$16*30.44)*(1+$M10) | T10: 1 | U10: 0 | V10: 0 | W10: 0 | X10: 0 | Y10: 0 | Z10: 0 | AA10: 0 | AB10: 0 | AC10: 0
A11: sonarqube | B11: SonarQube Community Edition | C11: 2 | D11: resident | E11: resident | F11: 2 | G11: 4 | H11: 3.5 | I11: 1 | J11: 30 | K11: 0.1 | L11: 365 | M11: 0.3 | N11: 0.2 | O11: =INDEX('02_Freq_Weight'!$E$3:$E$9,MATCH(E11,'02_Freq_Weight'!$A$3:$A$9,0)) | P11: =$K11*'05_Params'!$B$4*POWER(1+$N11,'05_Params'!$B$13/12)*MIN($L11,'05_Params'!$B$13*30.44)*(1+$M11) | Q11: =$K11*'05_Params'!$B$4*POWER(1+$N11,'05_Params'!$B$14/12)*MIN($L11,'05_Params'!$B$14*30.44)*(1+$M11) | R11: =$K11*'05_Params'!$B$4*POWER(1+$N11,'05_Params'!$B$15/12)*MIN($L11,'05_Params'!$B$15*30.44)*(1+$M11) | S11: =$K11*'05_Params'!$B$4*POWER(1+$N11,'05_Params'!$B$16/12)*MIN($L11,'05_Params'!$B$16*30.44)*(1+$M11) | T11: 0 | U11: 1 | V11: 0 | W11: 0 | X11: 0 | Y11: 0 | Z11: 0 | AA11: 0 | AB11: 0 | AC11: 0
A12: postgresql-tools | B12: PostgreSQL (ฐานข้อมูลของเครื่องมือ CI/CD) | C12: 2 | D12: resident | E12: resident | F12: 2 | G12: 4 | H12: 3 | I12: 1 | J12: 20 | K12: 0.05 | L12: 2555 | M12: 0.35 | N12: 0.2 | O12: =INDEX('02_Freq_Weight'!$E$3:$E$9,MATCH(E12,'02_Freq_Weight'!$A$3:$A$9,0)) | P12: =$K12*'05_Params'!$B$4*POWER(1+$N12,'05_Params'!$B$13/12)*MIN($L12,'05_Params'!$B$13*30.44)*(1+$M12) | Q12: =$K12*'05_Params'!$B$4*POWER(1+$N12,'05_Params'!$B$14/12)*MIN($L12,'05_Params'!$B$14*30.44)*(1+$M12) | R12: =$K12*'05_Params'!$B$4*POWER(1+$N12,'05_Params'!$B$15/12)*MIN($L12,'05_Params'!$B$15*30.44)*(1+$M12) | S12: =$K12*'05_Params'!$B$4*POWER(1+$N12,'05_Params'!$B$16/12)*MIN($L12,'05_Params'!$B$16*30.44)*(1+$M12) | T12: 0 | U12: 1 | V12: 0 | W12: 0 | X12: 0 | Y12: 0 | Z12: 0 | AA12: 0 | AB12: 0 | AC12: 0
A13: semgrep | B13: Semgrep (SAST แบบ Rule-based) | C13: 2 | D13: ci_seq | E13: per_commit | F13: 2 | G13: 4 | H13: 0 | I13: 0 | J13: 5 | K13: 0.02 | L13: 180 | M13: 0.05 | N13: 0.15 | O13: =INDEX('02_Freq_Weight'!$E$3:$E$9,MATCH(E13,'02_Freq_Weight'!$A$3:$A$9,0)) | P13: =$K13*'05_Params'!$B$4*POWER(1+$N13,'05_Params'!$B$13/12)*MIN($L13,'05_Params'!$B$13*30.44)*(1+$M13) | Q13: =$K13*'05_Params'!$B$4*POWER(1+$N13,'05_Params'!$B$14/12)*MIN($L13,'05_Params'!$B$14*30.44)*(1+$M13) | R13: =$K13*'05_Params'!$B$4*POWER(1+$N13,'05_Params'!$B$15/12)*MIN($L13,'05_Params'!$B$15*30.44)*(1+$M13) | S13: =$K13*'05_Params'!$B$4*POWER(1+$N13,'05_Params'!$B$16/12)*MIN($L13,'05_Params'!$B$16*30.44)*(1+$M13) | T13: 0 | U13: 0 | V13: 1 | W13: 0 | X13: 0 | Y13: 0 | Z13: 0 | AA13: 0 | AB13: 0 | AC13: 0
A14: gitleaks | B14: GitLeaks / TruffleHog (Secret Scanning) | C14: 2 | D14: ci_seq | E14: per_commit | F14: 1 | G14: 2 | H14: 0 | I14: 0 | J14: 3 | K14: 0.01 | L14: 365 | M14: 0.05 | N14: 0.1 | O14: =INDEX('02_Freq_Weight'!$E$3:$E$9,MATCH(E14,'02_Freq_Weight'!$A$3:$A$9,0)) | P14: =$K14*'05_Params'!$B$4*POWER(1+$N14,'05_Params'!$B$13/12)*MIN($L14,'05_Params'!$B$13*30.44)*(1+$M14) | Q14: =$K14*'05_Params'!$B$4*POWER(1+$N14,'05_Params'!$B$14/12)*MIN($L14,'05_Params'!$B$14*30.44)*(1+$M14) | R14: =$K14*'05_Params'!$B$4*POWER(1+$N14,'05_Params'!$B$15/12)*MIN($L14,'05_Params'!$B$15*30.44)*(1+$M14) | S14: =$K14*'05_Params'!$B$4*POWER(1+$N14,'05_Params'!$B$16/12)*MIN($L14,'05_Params'!$B$16*30.44)*(1+$M14) | T14: 0 | U14: 0 | V14: 1 | W14: 0 | X14: 0 | Y14: 0 | Z14: 0 | AA14: 0 | AB14: 0 | AC14: 0
... A74: gcp-cloud-operations | B74: Google Cloud Operations (Logging + Monitoring + Trace) | C74: 6 | D74: resident | E74: resident | F74: 0 | G74: 0 | H74: 0 | I74: 0 | J74: 0 | K74: 1 | L74: 90 | M74: 0.1 | N74: 0.3 | O74: =INDEX('02_Freq_Weight'!$E$3:$E$9,MATCH(E74,'02_Freq_Weight'!$A$3:$A$9,0)) | P74: =$K74*'05_Params'!$B$4*POWER(1+$N74,'05_Params'!$B$13/12)*MIN($L74,'05_Params'!$B$13*30.44)*(1+$M74) | Q74: =$K74*'05_Params'!$B$4*POWER(1+$N74,'05_Params'!$B$14/12)*MIN($L74,'05_Params'!$B$14*30.44)*(1+$M74) | R74: =$K74*'05_Params'!$B$4*POWER(1+$N74,'05_Params'!$B$15/12)*MIN($L74,'05_Params'!$B$15*30.44)*(1+$M74) | S74: =$K74*'05_Params'!$B$4*POWER(1+$N74,'05_Params'!$B$16/12)*MIN($L74,'05_Params'!$B$16*30.44)*(1+$M74) | T74: 0 | U74: 0 | V74: 0 | W74: 0 | X74: 0 | Y74: 0 | Z74: 0 | AA74: 0 | AB74: 0 | AC74: 0
A75: จำนวนเครื่องมือบน VM นี้ | T75: =SUM(T3:T74) | U75: =SUM(U3:U74) | V75: =SUM(V3:V74) | W75: =SUM(W3:W74) | X75: =SUM(X3:X74) | Y75: =SUM(Y3:Y74) | Z75: =SUM(Z3:Z74) | AA75: =SUM(AA3:AA74) | ... AC75: =SUM(AC3:AC74)

Sheet 04_VM_Sizing
A1: 04 — ผลการคำนวณทรัพยากรต่อ VM (Minimum ที่ต้องจัดสรร) | C1: สูตรทั้งหมดอ้างอิงชีท 03 และ 05 — เปลี่ยนการติดตั้งที่ชีท 03 แล้วตัวเลขที่นี่จะเปลี่ยนตาม
A2: VM | B2: บทบาทหน้าที่ | C2: จำนวน เครื่องมือ | D2: A: Peak-Max vCPU | E2: A: Peak-Max RAM | F2: B1 Strict vCPU | G2: B1 Strict RAM | H2: B2 Realistic vCPU | I2: B2 Realistic RAM | J2: C: Resident vCPU | K2: C: Resident RAM | L2: MAX(A,B,C) vCPU | M2: MAX(A,B,C) RAM | N2: +OS vCPU | O2: +OS RAM | P2: จัดสรร vCPU | Q2: จัดสรร RAM (GB) | R2: Install รวม (GB) | S2: Data @H3 (GB) | T2: ต้องมี Disk OS (GB) | U2: ต้องมี Disk Data (GB) | V2: จัดสรร Disk OS | W2: จัดสรร Disk Data | X2: spec จริง vCPU | Y2: spec จริง RAM | Z2: spec จริง Disk OS | AA2: spec จริง Disk Data | AB2: ส่วนต่าง vCPU | AC2: ส่วนต่าง RAM | AD2: ส่วนต่าง Disk OS | AE2: ส่วนต่าง Disk Data | AF2: ผลประเมิน | AG2: ตัวกำหนด vCPU | AH2: ตัวกำหนด RAM
A3: EDGE-01 | B3: Edge / Reverse Proxy: รับ traffic ขาเข้า, WAF, TLS Termination, SSO | C3: =SUM('03_Colocation_Calc'!T$3:T$74) | D3: =SUMPRODUCT(MAX('03_Colocation_Calc'!T$3:T$74*'03_Colocation_Calc'!$F$3:$F$74)) | E3: =SUMPRODUCT(MAX('03_Colocation_Calc'!T$3:T$74*'03_Colocation_Calc'!$G$3:$G$74)) | F3: =SUMPRODUCT('03_Colocation_Calc'!T$3:T$74,'03_Colocation_Calc'!$O$3:$O$74,'03_Colocation_Calc'!$F$3:$F$74) | G3: =SUMPRODUCT('03_Colocation_Calc'!T$3:T$74,'03_Colocation_Calc'!$O$3:$O$74,'03_Colocation_Calc'!$G$3:$G$74) | H3: =SUMPRODUCT('03_Colocation_Calc'!T$3:T$74,--('03_Colocation_Calc'!$D$3:$D$74="resident"),'03_Colocation_Calc'!$O$3:$O$74,'03_Colocation_Calc'!$F$3:$F$74)+SUMPRODUCT(MAX('03_Colocation_Calc'!T$3:T$74*--('03_Colocation_Calc'!$D$3:$D$74="ci_seq")*'03_Colocation_Calc'!$O$3:$O$74*'03_Colocation_Calc'!$F$3:$F$74))+SUMPRODUCT(MAX('03_Colocation_Calc'!T$3:T$74*--('03_Colocation_Calc'!$D$3:$D$74="async")*'03_Colocation_Calc'!$O$3:$O$74*'03_Colocation_Calc'!$F$3:$F$74))+SUMPRODUCT(MAX('03_Colocation_Calc'!T$3:T$74*--('03_Colocation_Calc'!$D$3:$D$74="load")*'03_Colocation_Calc'!$O$3:$O$74*'03_Colocation_Calc'!$F$3:$F$74)) | I3: =SUMPRODUCT('03_Colocation_Calc'!T$3:T$74,--('03_Colocation_Calc'!$D$3:$D$74="resident"),'03_Colocation_Calc'!$O$3:$O$74,'03_Colocation_Calc'!$G$3:$G$74)+SUMPRODUCT(MAX('03_Colocation_Calc'!T$3:T$74*--('03_Colocation_Calc'!$D$3:$D$74="ci_seq")*'03_Colocation_Calc'!$O$3:$O$74*'03_Colocation_Calc'!$G$3:$G$74))+SUMPRODUCT(MAX('03_Colocation_Calc'!T$3:T$74*--('03_Colocation_Calc'!$D$3:$D$74="async")*'03_Colocation_Calc'!$O$3:$O$74*'03_Colocation_Calc'!$G$3:$G$74))+SUMPRODUCT(MAX('03_Colocation_Calc'!T$3:T$74*--('03_Colocation_Calc'!$D$3:$D$74="load")*'03_Colocation_Calc'!$O$3:$O$74*'03_Colocation_Calc'!$G$3:$G$74)) | J3: =SUMPRODUCT('03_Colocation_Calc'!T$3:T$74,'03_Colocation_Calc'!$I$3:$I$74)*0.25 | K3: =SUMPRODUCT('03_Colocation_Calc'!T$3:T$74,'03_Colocation_Calc'!$I$3:$I$74,'03_Colocation_Calc'!$H$3:$H$74) | L3: =MAX(D3,IF('05_Params'!$B$3="strict",F3,H3),J3) | M3: =MAX(E3,IF('05_Params'!$B$3="strict",G3,I3),K3) | N3: =L3+'05_Params'!$B$5 | O3: =M3+'05_Params'!$B$6 | P3: =IFERROR(INDEX('05_Params'!$E$4:$E$23,COUNTIF('05_Params'!$E$4:$E$23,"<"&N3)+1),CEILING(N3,64)) | Q3: =IFERROR(INDEX('05_Params'!$F$4:$F$23,COUNTIF('05_Params'!$F$4:$F$23,"<"&O3)+1),CEILING(O3,64)) | R3: =SUMPRODUCT('03_Colocation_Calc'!T$3:T$74,'03_Colocation_Calc'!$J$3:$J$74) | S3: =SUMPRODUCT('03_Colocation_Calc'!T$3:T$74,'03_Colocation_Calc'!$R$3:$R$74) | T3: =('05_Params'!$B$7+R3)/(1-'05_Params'!$B$8) | U3: =S3/(1-'05_Params'!$B$8) | V3: =IFERROR(INDEX('05_Params'!$G$4:$G$23,COUNTIF('05_Params'!$G$4:$G$23,"<"&T3)+1),CEILING(T3,64)) | W3: =IF(U3<=0,0,IFERROR(INDEX('05_Params'!$G$4:$G$23,COUNTIF('05_Params'!$G$4:$G$23,"<"&U3)+1),CEILING(U3,64))) | AB3: =IF(X3="","",X3-P3) | AC3: =IF(Y3="","",Y3-Q3) | AD3: =IF(Z3="","",Z3-V3) | AE3: =IF(AA3="","",AA3-W3) | AF3: =IF(X3="","(ยังไม่กรอก spec)",IF(OR(AB3<0,AC3<0),"ไม่พอ: CPU/RAM",IF(OR(AD3<0,AE3<0),"เสี่ยง: Disk ไม่พอ","พอเพียง"))) | AG3: =IF(L3=D3,"A Peak-Max",IF(L3=J3,"C Resident","B Weighted")) | AH3: =IF(M3=E3,"A Peak-Max",IF(M3=K3,"C Resident","B Weighted"))
A4: CI-CONTROL-01 | B4: CI Control: Git Repository, Pipeline Orchestration, SAST และ Quality Gate | C4: =SUM('03_Colocation_Calc'!U$3:U$74) | D4: =SUMPRODUCT(MAX('03_Colocation_Calc'!U$3:U$74*'03_Colocation_Calc'!$F$3:$F$74)) | E4: =SUMPRODUCT(MAX('03_Colocation_Calc'!U$3:U$74*'03_Colocation_Calc'!$G$3:$G$74)) | F4: =SUMPRODUCT('03_Colocation_Calc'!U$3:U$74,'03_Colocation_Calc'!$O$3:$O$74,'03_Colocation_Calc'!$F$3:$F$74) | G4: =SUMPRODUCT('03_Colocation_Calc'!U$3:U$74,'03_Colocation_Calc'!$O$3:$O$74,'03_Colocation_Calc'!$G$3:$G$74) | H4: =SUMPRODUCT('03_Colocation_Calc'!U$3:U$74,--('03_Colocation_Calc'!$D$3:$D$74="resident"),'03_Colocation_Calc'!$O$3:$O$74,'03_Colocation_Calc'!$F$3:$F$74)+SUMPRODUCT(MAX('03_Colocation_Calc'!U$3:U$74*--('03_Colocation_Calc'!$D$3:$D$74="ci_seq")*'03_Colocation_Calc'!$O$3:$O$74*'03_Colocation_Calc'!$F$3:$F$74))+SUMPRODUCT(MAX('03_Colocation_Calc'!U$3:U$74*--('03_Colocation_Calc'!$D$3:$D$74="async")*'03_Colocation_Calc'!$O$3:$O$74*'03_Colocation_Calc'!$F$3:$F$74))+SUMPRODUCT(MAX('03_Colocation_Calc'!U$3:U$74*--('03_Colocation_Calc'!$D$3:$D$74="load")*'03_Colocation_Calc'!$O$3:$O$74*'03_Colocation_Calc'!$F$3:$F$74)) | I4: =SUMPRODUCT('03_Colocation_Calc'!U$3:U$74,--('03_Colocation_Calc'!$D$3:$D$74="resident"),'03_Colocation_Calc'!$O$3:$O$74,'03_Colocation_Calc'!$G$3:$G$74)+SUMPRODUCT(MAX('03_Colocation_Calc'!U$3:U$74*--('03_Colocation_Calc'!$D$3:$D$74="ci_seq")*'03_Colocation_Calc'!$O$3:$O$74*'03_Colocation_Calc'!$G$3:$G$74))+SUMPRODUCT(MAX('03_Colocation_Calc'!U$3:U$74*--('03_Colocation_Calc'!$D$3:$D$74="async")*'03_Colocation_Calc'!$O$3:$O$74*'03_Colocation_Calc'!$G$3:$G$74))+SUMPRODUCT(MAX('03_Colocation_Calc'!U$3:U$74*--('03_Colocation_Calc'!$D$3:$D$74="load")*'03_Colocation_Calc'!$O$3:$O$74*'03_Colocation_Calc'!$G$3:$G$74)) | J4: =SUMPRODUCT('03_Colocation_Calc'!U$3:U$74,'03_Colocation_Calc'!$I$3:$I$74)*0.25 | K4: =SUMPRODUCT('03_Colocation_Calc'!U$3:U$74,'03_Colocation_Calc'!$I$3:$I$74,'03_Colocation_Calc'!$H$3:$H$74) | L4: =MAX(D4,IF('05_Params'!$B$3="strict",F4,H4),J4) | M4: =MAX(E4,IF('05_Params'!$B$3="strict",G4,I4),K4) | N4: =L4+'05_Params'!$B$5 | O4: =M4+'05_Params'!$B$6 | P4: =IFERROR(INDEX('05_Params'!$E$4:$E$23,COUNTIF('05_Params'!$E$4:$E$23,"<"&N4)+1),CEILING(N4,64)) | Q4: =IFERROR(INDEX('05_Params'!$F$4:$F$23,COUNTIF('05_Params'!$F$4:$F$23,"<"&O4)+1),CEILING(O4,64)) | R4: =SUMPRODUCT('03_Colocation_Calc'!U$3:U$74,'03_Colocation_Calc'!$J$3:$J$74) | S4: =SUMPRODUCT('03_Colocation_Calc'!U$3:U$74,'03_Colocation_Calc'!$R$3:$R$74) | T4: =('05_Params'!$B$7+R4)/(1-'05_Params'!$B$8) | U4: =S4/(1-'05_Params'!$B$8) | V4: =IFERROR(INDEX('05_Params'!$G$4:$G$23,COUNTIF('05_Params'!$G$4:$G$23,"<"&T4)+1),CEILING(T4,64)) | W4: =IF(U4<=0,0,IFERROR(INDEX('05_Params'!$G$4:$G$23,COUNTIF('05_Params'!$G$4:$G$23,"<"&U4)+1),CEILING(U4,64))) | AB4: =IF(X4="","",X4-P4) | AC4: =IF(Y4="","",Y4-Q4) | AD4: =IF(Z4="","",Z4-V4) | AE4: =IF(AA4="","",AA4-W4) | AF4: =IF(X4="","(ยังไม่กรอก spec)",IF(OR(AB4<0,AC4<0),"ไม่พอ: CPU/RAM",IF(OR(AD4<0,AE4<0),"เสี่ยง: Disk ไม่พอ","พอเพียง"))) | AG4: =IF(L4=D4,"A Peak-Max",IF(L4=J4,"C Resident","B Weighted")) | AH4: =IF(M4=E4,"A Peak-Max",IF(M4=K4,"C Resident","B Weighted"))
A5: BUILD-AGENT-01 | B5: Build Agent: Compile, Container Build, Unit/Integration Test และสแกนใน Pipeline | C5: =SUM('03_Colocation_Calc'!V$3:V$74) | D5: =SUMPRODUCT(MAX('03_Colocation_Calc'!V$3:V$74*'03_Colocation_Calc'!$F$3:$F$74)) | E5: =SUMPRODUCT(MAX('03_Colocation_Calc'!V$3:V$74*'03_Colocation_Calc'!$G$3:$G$74)) | F5: =SUMPRODUCT('03_Colocation_Calc'!V$3:V$74,'03_Colocation_Calc'!$O$3:$O$74,'03_Colocation_Calc'!$F$3:$F$74) | G5: =SUMPRODUCT('03_Colocation_Calc'!V$3:V$74,'03_Colocation_Calc'!$O$3:$O$74,'03_Colocation_Calc'!$G$3:$G$74) | H5: =SUMPRODUCT('03_Colocation_Calc'!V$3:V$74,--('03_Colocation_Calc'!$D$3:$D$74="resident"),'03_Colocation_Calc'!$O$3:$O$74,'03_Colocation_Calc'!$F$3:$F$74)+SUMPRODUCT(MAX('03_Colocation_Calc'!V$3:V$74*--('03_Colocation_Calc'!$D$3:$D$74="ci_seq")*'03_Colocation_Calc'!$O$3:$O$74*'03_Colocation_Calc'!$F$3:$F$74))+SUMPRODUCT(MAX('03_Colocation_Calc'!V$3:V$74*--('03_Colocation_Calc'!$D$3:$D$74="async")*'03_Colocation_Calc'!$O$3:$O$74*'03_Colocation_Calc'!$F$3:$F$74))+SUMPRODUCT(MAX('03_Colocation_Calc'!V$3:V$74*--('03_Colocation_Calc'!$D$3:$D$74="load")*'03_Colocation_Calc'!$O$3:$O$74*'03_Colocation_Calc'!$F$3:$F$74)) | I5: =SUMPRODUCT('03_Colocation_Calc'!V$3:V$74,--('03_Colocation_Calc'!$D$3:$D$74="resident"),'03_Colocation_Calc'!$O$3:$O$74,'03_Colocation_Calc'!$G$3:$G$74)+SUMPRODUCT(MAX('03_Colocation_Calc'!V$3:V$74*--('03_Colocation_Calc'!$D$3:$D$74="ci_seq")*'03_Colocation_Calc'!$O$3:$O$74*'03_Colocation_Calc'!$G$3:$G$74))+SUMPRODUCT(MAX('03_Colocation_Calc'!V$3:V$74*--('03_Colocation_Calc'!$D$3:$D$74="async")*'03_Colocation_Calc'!$O$3:$O$74*'03_Colocation_Calc'!$G$3:$G$74))+SUMPRODUCT(MAX('03_Colocation_Calc'!V$3:V$74*--('03_Colocation_Calc'!$D$3:$D$74="load")*'03_Colocation_Calc'!$O$3:$O$74*'03_Colocation_Calc'!$G$3:$G$74)) | J5: =SUMPRODUCT('03_Colocation_Calc'!V$3:V$74,'03_Colocation_Calc'!$I$3:$I$74)*0.25 | K5: =SUMPRODUCT('03_Colocation_Calc'!V$3:V$74,'03_Colocation_Calc'!$I$3:$I$74,'03_Colocation_Calc'!$H$3:$H$74) | L5: =MAX(D5,IF('05_Params'!$B$3="strict",F5,H5),J5) | M5: =MAX(E5,IF('05_Params'!$B$3="strict",G5,I5),K5) | N5: =L5+'05_Params'!$B$5 | O5: =M5+'05_Params'!$B$6 | P5: =IFERROR(INDEX('05_Params'!$E$4:$E$23,COUNTIF('05_Params'!$E$4:$E$23,"<"&N5)+1),CEILING(N5,64)) | Q5: =IFERROR(INDEX('05_Params'!$F$4:$F$23,COUNTIF('05_Params'!$F$4:$F$23,"<"&O5)+1),CEILING(O5,64)) | R5: =SUMPRODUCT('03_Colocation_Calc'!V$3:V$74,'03_Colocation_Calc'!$J$3:$J$74) | S5: =SUMPRODUCT('03_Colocation_Calc'!V$3:V$74,'03_Colocation_Calc'!$R$3:$R$74) | T5: =('05_Params'!$B$7+R5)/(1-'05_Params'!$B$8) | U5: =S5/(1-'05_Params'!$B$8) | V5: =IFERROR(INDEX('05_Params'!$G$4:$G$23,COUNTIF('05_Params'!$G$4:$G$23,"<"&T5)+1),CEILING(T5,64)) | W5: =IF(U5<=0,0,IFERROR(INDEX('05_Params'!$G$4:$G$23,COUNTIF('05_Params'!$G$4:$G$23,"<"&U5)+1),CEILING(U5,64))) | AB5: =IF(X5="","",X5-P5) | AC5: =IF(Y5="","",Y5-Q5) | AD5: =IF(Z5="","",Z5-V5) | AE5: =IF(AA5="","",AA5-W5) | AF5: =IF(X5="","(ยังไม่กรอก spec)",IF(OR(AB5<0,AC5<0),"ไม่พอ: CPU/RAM",IF(OR(AD5<0,AE5<0),"เสี่ยง: Disk ไม่พอ","พอเพียง"))) | AG5: =IF(L5=D5,"A Peak-Max",IF(L5=J5,"C Resident","B Weighted")) | AH5: =IF(M5=E5,"A Peak-Max",IF(M5=K5,"C Resident","B Weighted"))
A6: SEC-TEST-01 | B6: Security & Performance Test: DAST, API Security, Accessibility, TLS, Load Test | C6: =SUM('03_Colocation_Calc'!W$3:W$74) | D6: =SUMPRODUCT(MAX('03_Colocation_Calc'!W$3:W$74*'03_Colocation_Calc'!$F$3:$F$74)) | E6: =SUMPRODUCT(MAX('03_Colocation_Calc'!W$3:W$74*'03_Colocation_Calc'!$G$3:$G$74)) | F6: =SUMPRODUCT('03_Colocation_Calc'!W$3:W$74,'03_Colocation_Calc'!$O$3:$O$74,'03_Colocation_Calc'!$F$3:$F$74) | G6: =SUMPRODUCT('03_Colocation_Calc'!W$3:W$74,'03_Colocation_Calc'!$O$3:$O$74,'03_Colocation_Calc'!$G$3:$G$74) | H6: =SUMPRODUCT('03_Colocation_Calc'!W$3:W$74,--('03_Colocation_Calc'!$D$3:$D$74="resident"),'03_Colocation_Calc'!$O$3:$O$74,'03_Colocation_Calc'!$F$3:$F$74)+SUMPRODUCT(MAX('03_Colocation_Calc'!W$3:W$74*--('03_Colocation_Calc'!$D$3:$D$74="ci_seq")*'03_Colocation_Calc'!$O$3:$O$74*'03_Colocation_Calc'!$F$3:$F$74))+SUMPRODUCT(MAX('03_Colocation_Calc'!W$3:W$74*--('03_Colocation_Calc'!$D$3:$D$74="async")*'03_Colocation_Calc'!$O$3:$O$74*'03_Colocation_Calc'!$F$3:$F$74))+SUMPRODUCT(MAX('03_Colocation_Calc'!W$3:W$74*--('03_Colocation_Calc'!$D$3:$D$74="load")*'03_Colocation_Calc'!$O$3:$O$74*'03_Colocation_Calc'!$F$3:$F$74)) | I6: =SUMPRODUCT('03_Colocation_Calc'!W$3:W$74,--('03_Colocation_Calc'!$D$3:$D$74="resident"),'03_Colocation_Calc'!$O$3:$O$74,'03_Colocation_Calc'!$G$3:$G$74)+SUMPRODUCT(MAX('03_Colocation_Calc'!W$3:W$74*--('03_Colocation_Calc'!$D$3:$D$74="ci_seq")*'03_Colocation_Calc'!$O$3:$O$74*'03_Colocation_Calc'!$G$3:$G$74))+SUMPRODUCT(MAX('03_Colocation_Calc'!W$3:W$74*--('03_Colocation_Calc'!$D$3:$D$74="async")*'03_Colocation_Calc'!$O$3:$O$74*'03_Colocation_Calc'!$G$3:$G$74))+SUMPRODUCT(MAX('03_Colocation_Calc'!W$3:W$74*--('03_Colocation_Calc'!$D$3:$D$74="load")*'03_Colocation_Calc'!$O$3:$O$74*'03_Colocation_Calc'!$G$3:$G$74)) | J6: =SUMPRODUCT('03_Colocation_Calc'!W$3:W$74,'03_Colocation_Calc'!$I$3:$I$74)*0.25 | K6: =SUMPRODUCT('03_Colocation_Calc'!W$3:W$74,'03_Colocation_Calc'!$I$3:$I$74,'03_Colocation_Calc'!$H$3:$H$74) | L6: =MAX(D6,IF('05_Params'!$B$3="strict",F6,H6),J6) | M6: =MAX(E6,IF('05_Params'!$B$3="strict",G6,I6),K6) | N6: =L6+'05_Params'!$B$5 | O6: =M6+'05_Params'!$B$6 | P6: =IFERROR(INDEX('05_Params'!$E$4:$E$23,COUNTIF('05_Params'!$E$4:$E$23,"<"&N6)+1),CEILING(N6,64)) | Q6: =IFERROR(INDEX('05_Params'!$F$4:$F$23,COUNTIF('05_Params'!$F$4:$F$23,"<"&O6)+1),CEILING(O6,64)) | R6: =SUMPRODUCT('03_Colocation_Calc'!W$3:W$74,'03_Colocation_Calc'!$J$3:$J$74) | S6: =SUMPRODUCT('03_Colocation_Calc'!W$3:W$74,'03_Colocation_Calc'!$R$3:$R$74) | T6: =('05_Params'!$B$7+R6)/(1-'05_Params'!$B$8) | U6: =S6/(1-'05_Params'!$B$8) | V6: =IFERROR(INDEX('05_Params'!$G$4:$G$23,COUNTIF('05_Params'!$G$4:$G$23,"<"&T6)+1),CEILING(T6,64)) | W6: =IF(U6<=0,0,IFERROR(INDEX('05_Params'!$G$4:$G$23,COUNTIF('05_Params'!$G$4:$G$23,"<"&U6)+1),CEILING(U6,64))) | AB6: =IF(X6="","",X6-P6) | AC6: =IF(Y6="","",Y6-Q6) | AD6: =IF(Z6="","",Z6-V6) | AE6: =IF(AA6="","",AA6-W6) | AF6: =IF(X6="","(ยังไม่กรอก spec)",IF(OR(AB6<0,AC6<0),"ไม่พอ: CPU/RAM",IF(OR(AD6<0,AE6<0),"เสี่ยง: Disk ไม่พอ","พอเพียง"))) | AG6: =IF(L6=D6,"A Peak-Max",IF(L6=J6,"C Resident","B Weighted")) | AH6: =IF(M6=E6,"A Peak-Max",IF(M6=K6,"C Resident","B Weighted"))
A7: STORE-LOG-01 | B7: Store & Log: Container Registry, Object Storage, Secret Management, Log และ Audit Trail | C7: =SUM('03_Colocation_Calc'!X$3:X$74) | D7: =SUMPRODUCT(MAX('03_Colocation_Calc'!X$3:X$74*'03_Colocation_Calc'!$F$3:$F$74)) | E7: =SUMPRODUCT(MAX('03_Colocation_Calc'!X$3:X$74*'03_Colocation_Calc'!$G$3:$G$74)) | F7: =SUMPRODUCT('03_Colocation_Calc'!X$3:X$74,'03_Colocation_Calc'!$O$3:$O$74,'03_Colocation_Calc'!$F$3:$F$74) | G7: =SUMPRODUCT('03_Colocation_Calc'!X$3:X$74,'03_Colocation_Calc'!$O$3:$O$74,'03_Colocation_Calc'!$G$3:$G$74) | H7: =SUMPRODUCT('03_Colocation_Calc'!X$3:X$74,--('03_Colocation_Calc'!$D$3:$D$74="resident"),'03_Colocation_Calc'!$O$3:$O$74,'03_Colocation_Calc'!$F$3:$F$74)+SUMPRODUCT(MAX('03_Colocation_Calc'!X$3:X$74*--('03_Colocation_Calc'!$D$3:$D$74="ci_seq")*'03_Colocation_Calc'!$O$3:$O$74*'03_Colocation_Calc'!$F$3:$F$74))+SUMPRODUCT(MAX('03_Colocation_Calc'!X$3:X$74*--('03_Colocation_Calc'!$D$3:$D$74="async")*'03_Colocation_Calc'!$O$3:$O$74*'03_Colocation_Calc'!$F$3:$F$74))+SUMPRODUCT(MAX('03_Colocation_Calc'!X$3:X$74*--('03_Colocation_Calc'!$D$3:$D$74="load")*'03_Colocation_Calc'!$O$3:$O$74*'03_Colocation_Calc'!$F$3:$F$74)) | I7: =SUMPRODUCT('03_Colocation_Calc'!X$3:X$74,--('03_Colocation_Calc'!$D$3:$D$74="resident"),'03_Colocation_Calc'!$O$3:$O$74,'03_Colocation_Calc'!$G$3:$G$74)+SUMPRODUCT(MAX('03_Colocation_Calc'!X$3:X$74*--('03_Colocation_Calc'!$D$3:$D$74="ci_seq")*'03_Colocation_Calc'!$O$3:$O$74*'03_Colocation_Calc'!$G$3:$G$74))+SUMPRODUCT(MAX('03_Colocation_Calc'!X$3:X$74*--('03_Colocation_Calc'!$D$3:$D$74="async")*'03_Colocation_Calc'!$O$3:$O$74*'03_Colocation_Calc'!$G$3:$G$74))+SUMPRODUCT(MAX('03_Colocation_Calc'!X$3:X$74*--('03_Colocation_Calc'!$D$3:$D$74="load")*'03_Colocation_Calc'!$O$3:$O$74*'03_Colocation_Calc'!$G$3:$G$74)) | J7: =SUMPRODUCT('03_Colocation_Calc'!X$3:X$74,'03_Colocation_Calc'!$I$3:$I$74)*0.25 | K7: =SUMPRODUCT('03_Colocation_Calc'!X$3:X$74,'03_Colocation_Calc'!$I$3:$I$74,'03_Colocation_Calc'!$H$3:$H$74) | L7: =MAX(D7,IF('05_Params'!$B$3="strict",F7,H7),J7) | M7: =MAX(E7,IF('05_Params'!$B$3="strict",G7,I7),K7) | N7: =L7+'05_Params'!$B$5 | O7: =M7+'05_Params'!$B$6 | P7: =IFERROR(INDEX('05_Params'!$E$4:$E$23,COUNTIF('05_Params'!$E$4:$E$23,"<"&N7)+1),CEILING(N7,64)) | Q7: =IFERROR(INDEX('05_Params'!$F$4:$F$23,COUNTIF('05_Params'!$F$4:$F$23,"<"&O7)+1),CEILING(O7,64)) | R7: =SUMPRODUCT('03_Colocation_Calc'!X$3:X$74,'03_Colocation_Calc'!$J$3:$J$74) | S7: =SUMPRODUCT('03_Colocation_Calc'!X$3:X$74,'03_Colocation_Calc'!$R$3:$R$74) | T7: =('05_Params'!$B$7+R7)/(1-'05_Params'!$B$8) | U7: =S7/(1-'05_Params'!$B$8) | V7: =IFERROR(INDEX('05_Params'!$G$4:$G$23,COUNTIF('05_Params'!$G$4:$G$23,"<"&T7)+1),CEILING(T7,64)) | W7: =IF(U7<=0,0,IFERROR(INDEX('05_Params'!$G$4:$G$23,COUNTIF('05_Params'!$G$4:$G$23,"<"&U7)+1),CEILING(U7,64))) | AB7: =IF(X7="","",X7-P7) | AC7: =IF(Y7="","",Y7-Q7) | AD7: =IF(Z7="","",Z7-V7) | AE7: =IF(AA7="","",AA7-W7) | AF7: =IF(X7="","(ยังไม่กรอก spec)",IF(OR(AB7<0,AC7<0),"ไม่พอ: CPU/RAM",IF(OR(AD7<0,AE7<0),"เสี่ยง: Disk ไม่พอ","พอเพียง"))) | AG7: =IF(L7=D7,"A Peak-Max",IF(L7=J7,"C Resident","B Weighted")) | AH7: =IF(M7=E7,"A Peak-Max",IF(M7=K7,"C Resident","B Weighted"))
A8: DEPLOY-MON-01 | B8: Deploy & Monitor: Orchestration, GitOps, Runtime Security, Observability, Backup | C8: =SUM('03_Colocation_Calc'!Y$3:Y$74) | D8: =SUMPRODUCT(MAX('03_Colocation_Calc'!Y$3:Y$74*'03_Colocation_Calc'!$F$3:$F$74)) | E8: =SUMPRODUCT(MAX('03_Colocation_Calc'!Y$3:Y$74*'03_Colocation_Calc'!$G$3:$G$74)) | F8: =SUMPRODUCT('03_Colocation_Calc'!Y$3:Y$74,'03_Colocation_Calc'!$O$3:$O$74,'03_Colocation_Calc'!$F$3:$F$74) | G8: =SUMPRODUCT('03_Colocation_Calc'!Y$3:Y$74,'03_Colocation_Calc'!$O$3:$O$74,'03_Colocation_Calc'!$G$3:$G$74) | H8: =SUMPRODUCT('03_Colocation_Calc'!Y$3:Y$74,--('03_Colocation_Calc'!$D$3:$D$74="resident"),'03_Colocation_Calc'!$O$3:$O$74,'03_Colocation_Calc'!$F$3:$F$74)+SUMPRODUCT(MAX('03_Colocation_Calc'!Y$3:Y$74*--('03_Colocation_Calc'!$D$3:$D$74="ci_seq")*'03_Colocation_Calc'!$O$3:$O$74*'03_Colocation_Calc'!$F$3:$F$74))+SUMPRODUCT(MAX('03_Colocation_Calc'!Y$3:Y$74*--('03_Colocation_Calc'!$D$3:$D$74="async")*'03_Colocation_Calc'!$O$3:$O$74*'03_Colocation_Calc'!$F$3:$F$74))+SUMPRODUCT(MAX('03_Colocation_Calc'!Y$3:Y$74*--('03_Colocation_Calc'!$D$3:$D$74="load")*'03_Colocation_Calc'!$O$3:$O$74*'03_Colocation_Calc'!$F$3:$F$74)) | I8: =SUMPRODUCT('03_Colocation_Calc'!Y$3:Y$74,--('03_Colocation_Calc'!$D$3:$D$74="resident"),'03_Colocation_Calc'!$O$3:$O$74,'03_Colocation_Calc'!$G$3:$G$74)+SUMPRODUCT(MAX('03_Colocation_Calc'!Y$3:Y$74*--('03_Colocation_Calc'!$D$3:$D$74="ci_seq")*'03_Colocation_Calc'!$O$3:$O$74*'03_Colocation_Calc'!$G$3:$G$74))+SUMPRODUCT(MAX('03_Colocation_Calc'!Y$3:Y$74*--('03_Colocation_Calc'!$D$3:$D$74="async")*'03_Colocation_Calc'!$O$3:$O$74*'03_Colocation_Calc'!$G$3:$G$74))+SUMPRODUCT(MAX('03_Colocation_Calc'!Y$3:Y$74*--('03_Colocation_Calc'!$D$3:$D$74="load")*'03_Colocation_Calc'!$O$3:$O$74*'03_Colocation_Calc'!$G$3:$G$74)) | J8: =SUMPRODUCT('03_Colocation_Calc'!Y$3:Y$74,'03_Colocation_Calc'!$I$3:$I$74)*0.25 | K8: =SUMPRODUCT('03_Colocation_Calc'!Y$3:Y$74,'03_Colocation_Calc'!$I$3:$I$74,'03_Colocation_Calc'!$H$3:$H$74) | L8: =MAX(D8,IF('05_Params'!$B$3="strict",F8,H8),J8) | M8: =MAX(E8,IF('05_Params'!$B$3="strict",G8,I8),K8) | N8: =L8+'05_Params'!$B$5 | O8: =M8+'05_Params'!$B$6 | P8: =IFERROR(INDEX('05_Params'!$E$4:$E$23,COUNTIF('05_Params'!$E$4:$E$23,"<"&N8)+1),CEILING(N8,64)) | Q8: =IFERROR(INDEX('05_Params'!$F$4:$F$23,COUNTIF('05_Params'!$F$4:$F$23,"<"&O8)+1),CEILING(O8,64)) | R8: =SUMPRODUCT('03_Colocation_Calc'!Y$3:Y$74,'03_Colocation_Calc'!$J$3:$J$74) | S8: =SUMPRODUCT('03_Colocation_Calc'!Y$3:Y$74,'03_Colocation_Calc'!$R$3:$R$74) | T8: =('05_Params'!$B$7+R8)/(1-'05_Params'!$B$8) | U8: =S8/(1-'05_Params'!$B$8) | V8: =IFERROR(INDEX('05_Params'!$G$4:$G$23,COUNTIF('05_Params'!$G$4:$G$23,"<"&T8)+1),CEILING(T8,64)) | W8: =IF(U8<=0,0,IFERROR(INDEX('05_Params'!$G$4:$G$23,COUNTIF('05_Params'!$G$4:$G$23,"<"&U8)+1),CEILING(U8,64))) | AB8: =IF(X8="","",X8-P8) | AC8: =IF(Y8="","",Y8-Q8) | AD8: =IF(Z8="","",Z8-V8) | AE8: =IF(AA8="","",AA8-W8) | AF8: =IF(X8="","(ยังไม่กรอก spec)",IF(OR(AB8<0,AC8<0),"ไม่พอ: CPU/RAM",IF(OR(AD8<0,AE8<0),"เสี่ยง: Disk ไม่พอ","พอเพียง"))) | AG8: =IF(L8=D8,"A Peak-Max",IF(L8=J8,"C Resident","B Weighted")) | AH8: =IF(M8=E8,"A Peak-Max",IF(M8=K8,"C Resident","B Weighted"))
A9: VM07 | B9: (กรอกบทบาทหน้าที่) | C9: =SUM('03_Colocation_Calc'!Z$3:Z$74) | D9: =SUMPRODUCT(MAX('03_Colocation_Calc'!Z$3:Z$74*'03_Colocation_Calc'!$F$3:$F$74)) | E9: =SUMPRODUCT(MAX('03_Colocation_Calc'!Z$3:Z$74*'03_Colocation_Calc'!$G$3:$G$74)) | F9: =SUMPRODUCT('03_Colocation_Calc'!Z$3:Z$74,'03_Colocation_Calc'!$O$3:$O$74,'03_Colocation_Calc'!$F$3:$F$74) | G9: =SUMPRODUCT('03_Colocation_Calc'!Z$3:Z$74,'03_Colocation_Calc'!$O$3:$O$74,'03_Colocation_Calc'!$G$3:$G$74) | H9: =SUMPRODUCT('03_Colocation_Calc'!Z$3:Z$74,--('03_Colocation_Calc'!$D$3:$D$74="resident"),'03_Colocation_Calc'!$O$3:$O$74,'03_Colocation_Calc'!$F$3:$F$74)+SUMPRODUCT(MAX('03_Colocation_Calc'!Z$3:Z$74*--('03_Colocation_Calc'!$D$3:$D$74="ci_seq")*'03_Colocation_Calc'!$O$3:$O$74*'03_Colocation_Calc'!$F$3:$F$74))+SUMPRODUCT(MAX('03_Colocation_Calc'!Z$3:Z$74*--('03_Colocation_Calc'!$D$3:$D$74="async")*'03_Colocation_Calc'!$O$3:$O$74*'03_Colocation_Calc'!$F$3:$F$74))+SUMPRODUCT(MAX('03_Colocation_Calc'!Z$3:Z$74*--('03_Colocation_Calc'!$D$3:$D$74="load")*'03_Colocation_Calc'!$O$3:$O$74*'03_Colocation_Calc'!$F$3:$F$74)) | I9: =SUMPRODUCT('03_Colocation_Calc'!Z$3:Z$74,--('03_Colocation_Calc'!$D$3:$D$74="resident"),'03_Colocation_Calc'!$O$3:$O$74,'03_Colocation_Calc'!$G$3:$G$74)+SUMPRODUCT(MAX('03_Colocation_Calc'!Z$3:Z$74*--('03_Colocation_Calc'!$D$3:$D$74="ci_seq")*'03_Colocation_Calc'!$O$3:$O$74*'03_Colocation_Calc'!$G$3:$G$74))+SUMPRODUCT(MAX('03_Colocation_Calc'!Z$3:Z$74*--('03_Colocation_Calc'!$D$3:$D$74="async")*'03_Colocation_Calc'!$O$3:$O$74*'03_Colocation_Calc'!$G$3:$G$74))+SUMPRODUCT(MAX('03_Colocation_Calc'!Z$3:Z$74*--('03_Colocation_Calc'!$D$3:$D$74="load")*'03_Colocation_Calc'!$O$3:$O$74*'03_Colocation_Calc'!$G$3:$G$74)) | J9: =SUMPRODUCT('03_Colocation_Calc'!Z$3:Z$74,'03_Colocation_Calc'!$I$3:$I$74)*0.25 | K9: =SUMPRODUCT('03_Colocation_Calc'!Z$3:Z$74,'03_Colocation_Calc'!$I$3:$I$74,'03_Colocation_Calc'!$H$3:$H$74) | L9: =MAX(D9,IF('05_Params'!$B$3="strict",F9,H9),J9) | M9: =MAX(E9,IF('05_Params'!$B$3="strict",G9,I9),K9) | N9: =L9+'05_Params'!$B$5 | O9: =M9+'05_Params'!$B$6 | P9: =IFERROR(INDEX('05_Params'!$E$4:$E$23,COUNTIF('05_Params'!$E$4:$E$23,"<"&N9)+1),CEILING(N9,64)) | Q9: =IFERROR(INDEX('05_Params'!$F$4:$F$23,COUNTIF('05_Params'!$F$4:$F$23,"<"&O9)+1),CEILING(O9,64)) | R9: =SUMPRODUCT('03_Colocation_Calc'!Z$3:Z$74,'03_Colocation_Calc'!$J$3:$J$74) | S9: =SUMPRODUCT('03_Colocation_Calc'!Z$3:Z$74,'03_Colocation_Calc'!$R$3:$R$74) | T9: =('05_Params'!$B$7+R9)/(1-'05_Params'!$B$8) | U9: =S9/(1-'05_Params'!$B$8) | V9: =IFERROR(INDEX('05_Params'!$G$4:$G$23,COUNTIF('05_Params'!$G$4:$G$23,"<"&T9)+1),CEILING(T9,64)) | W9: =IF(U9<=0,0,IFERROR(INDEX('05_Params'!$G$4:$G$23,COUNTIF('05_Params'!$G$4:$G$23,"<"&U9)+1),CEILING(U9,64))) | AB9: =IF(X9="","",X9-P9) | AC9: =IF(Y9="","",Y9-Q9) | AD9: =IF(Z9="","",Z9-V9) | AE9: =IF(AA9="","",AA9-W9) | AF9: =IF(X9="","(ยังไม่กรอก spec)",IF(OR(AB9<0,AC9<0),"ไม่พอ: CPU/RAM",IF(OR(AD9<0,AE9<0),"เสี่ยง: Disk ไม่พอ","พอเพียง"))) | AG9: =IF(L9=D9,"A Peak-Max",IF(L9=J9,"C Resident","B Weighted")) | AH9: =IF(M9=E9,"A Peak-Max",IF(M9=K9,"C Resident","B Weighted"))
A10: VM08 | B10: (กรอกบทบาทหน้าที่) | C10: =SUM('03_Colocation_Calc'!AA$3:AA$74) | D10: =SUMPRODUCT(MAX('03_Colocation_Calc'!AA$3:AA$74*'03_Colocation_Calc'!$F$3:$F$74)) | E10: =SUMPRODUCT(MAX('03_Colocation_Calc'!AA$3:AA$74*'03_Colocation_Calc'!$G$3:$G$74)) | F10: =SUMPRODUCT('03_Colocation_Calc'!AA$3:AA$74,'03_Colocation_Calc'!$O$3:$O$74,'03_Colocation_Calc'!$F$3:$F$74) | G10: =SUMPRODUCT('03_Colocation_Calc'!AA$3:AA$74,'03_Colocation_Calc'!$O$3:$O$74,'03_Colocation_Calc'!$G$3:$G$74) | H10: =SUMPRODUCT('03_Colocation_Calc'!AA$3:AA$74,--('03_Colocation_Calc'!$D$3:$D$74="resident"),'03_Colocation_Calc'!$O$3:$O$74,'03_Colocation_Calc'!$F$3:$F$74)+SUMPRODUCT(MAX('03_Colocation_Calc'!AA$3:AA$74*--('03_Colocation_Calc'!$D$3:$D$74="ci_seq")*'03_Colocation_Calc'!$O$3:$O$74*'03_Colocation_Calc'!$F$3:$F$74))+SUMPRODUCT(MAX('03_Colocation_Calc'!AA$3:AA$74*--('03_Colocation_Calc'!$D$3:$D$74="async")*'03_Colocation_Calc'!$O$3:$O$74*'03_Colocation_Calc'!$F$3:$F$74))+SUMPRODUCT(MAX('03_Colocation_Calc'!AA$3:AA$74*--('03_Colocation_Calc'!$D$3:$D$74="load")*'03_Colocation_Calc'!$O$3:$O$74*'03_Colocation_Calc'!$F$3:$F$74)) | I10: =SUMPRODUCT('03_Colocation_Calc'!AA$3:AA$74,--('03_Colocation_Calc'!$D$3:$D$74="resident"),'03_Colocation_Calc'!$O$3:$O$74,'03_Colocation_Calc'!$G$3:$G$74)+SUMPRODUCT(MAX('03_Colocation_Calc'!AA$3:AA$74*--('03_Colocation_Calc'!$D$3:$D$74="ci_seq")*'03_Colocation_Calc'!$O$3:$O$74*'03_Colocation_Calc'!$G$3:$G$74))+SUMPRODUCT(MAX('03_Colocation_Calc'!AA$3:AA$74*--('03_Colocation_Calc'!$D$3:$D$74="async")*'03_Colocation_Calc'!$O$3:$O$74*'03_Colocation_Calc'!$G$3:$G$74))+SUMPRODUCT(MAX('03_Colocation_Calc'!AA$3:AA$74*--('03_Colocation_Calc'!$D$3:$D$74="load")*'03_Colocation_Calc'!$O$3:$O$74*'03_Colocation_Calc'!$G$3:$G$74)) | J10: =SUMPRODUCT('03_Colocation_Calc'!AA$3:AA$74,'03_Colocation_Calc'!$I$3:$I$74)*0.25 | K10: =SUMPRODUCT('03_Colocation_Calc'!AA$3:AA$74,'03_Colocation_Calc'!$I$3:$I$74,'03_Colocation_Calc'!$H$3:$H$74) | L10: =MAX(D10,IF('05_Params'!$B$3="strict",F10,H10),J10) | M10: =MAX(E10,IF('05_Params'!$B$3="strict",G10,I10),K10) | N10: =L10+'05_Params'!$B$5 | O10: =M10+'05_Params'!$B$6 | P10: =IFERROR(INDEX('05_Params'!$E$4:$E$23,COUNTIF('05_Params'!$E$4:$E$23,"<"&N10)+1),CEILING(N10,64)) | Q10: =IFERROR(INDEX('05_Params'!$F$4:$F$23,COUNTIF('05_Params'!$F$4:$F$23,"<"&O10)+1),CEILING(O10,64)) | R10: =SUMPRODUCT('03_Colocation_Calc'!AA$3:AA$74,'03_Colocation_Calc'!$J$3:$J$74) | S10: =SUMPRODUCT('03_Colocation_Calc'!AA$3:AA$74,'03_Colocation_Calc'!$R$3:$R$74) | T10: =('05_Params'!$B$7+R10)/(1-'05_Params'!$B$8) | U10: =S10/(1-'05_Params'!$B$8) | V10: =IFERROR(INDEX('05_Params'!$G$4:$G$23,COUNTIF('05_Params'!$G$4:$G$23,"<"&T10)+1),CEILING(T10,64)) | W10: =IF(U10<=0,0,IFERROR(INDEX('05_Params'!$G$4:$G$23,COUNTIF('05_Params'!$G$4:$G$23,"<"&U10)+1),CEILING(U10,64))) | AB10: =IF(X10="","",X10-P10) | AC10: =IF(Y10="","",Y10-Q10) | AD10: =IF(Z10="","",Z10-V10) | AE10: =IF(AA10="","",AA10-W10) | AF10: =IF(X10="","(ยังไม่กรอก spec)",IF(OR(AB10<0,AC10<0),"ไม่พอ: CPU/RAM",IF(OR(AD10<0,AE10<0),"เสี่ยง: Disk ไม่พอ","พอเพียง"))) | AG10: =IF(L10=D10,"A Peak-Max",IF(L10=J10,"C Resident","B Weighted")) | AH10: =IF(M10=E10,"A Peak-Max",IF(M10=K10,"C Resident","B Weighted"))
A11: VM09 | B11: (กรอกบทบาทหน้าที่) | C11: =SUM('03_Colocation_Calc'!AB$3:AB$74) | D11: =SUMPRODUCT(MAX('03_Colocation_Calc'!AB$3:AB$74*'03_Colocation_Calc'!$F$3:$F$74)) | E11: =SUMPRODUCT(MAX('03_Colocation_Calc'!AB$3:AB$74*'03_Colocation_Calc'!$G$3:$G$74)) | F11: =SUMPRODUCT('03_Colocation_Calc'!AB$3:AB$74,'03_Colocation_Calc'!$O$3:$O$74,'03_Colocation_Calc'!$F$3:$F$74) | G11: =SUMPRODUCT('03_Colocation_Calc'!AB$3:AB$74,'03_Colocation_Calc'!$O$3:$O$74,'03_Colocation_Calc'!$G$3:$G$74) | H11: =SUMPRODUCT('03_Colocation_Calc'!AB$3:AB$74,--('03_Colocation_Calc'!$D$3:$D$74="resident"),'03_Colocation_Calc'!$O$3:$O$74,'03_Colocation_Calc'!$F$3:$F$74)+SUMPRODUCT(MAX('03_Colocation_Calc'!AB$3:AB$74*--('03_Colocation_Calc'!$D$3:$D$74="ci_seq")*'03_Colocation_Calc'!$O$3:$O$74*'03_Colocation_Calc'!$F$3:$F$74))+SUMPRODUCT(MAX('03_Colocation_Calc'!AB$3:AB$74*--('03_Colocation_Calc'!$D$3:$D$74="async")*'03_Colocation_Calc'!$O$3:$O$74*'03_Colocation_Calc'!$F$3:$F$74))+SUMPRODUCT(MAX('03_Colocation_Calc'!AB$3:AB$74*--('03_Colocation_Calc'!$D$3:$D$74="load")*'03_Colocation_Calc'!$O$3:$O$74*'03_Colocation_Calc'!$F$3:$F$74)) | I11: =SUMPRODUCT('03_Colocation_Calc'!AB$3:AB$74,--('03_Colocation_Calc'!$D$3:$D$74="resident"),'03_Colocation_Calc'!$O$3:$O$74,'03_Colocation_Calc'!$G$3:$G$74)+SUMPRODUCT(MAX('03_Colocation_Calc'!AB$3:AB$74*--('03_Colocation_Calc'!$D$3:$D$74="ci_seq")*'03_Colocation_Calc'!$O$3:$O$74*'03_Colocation_Calc'!$G$3:$G$74))+SUMPRODUCT(MAX('03_Colocation_Calc'!AB$3:AB$74*--('03_Colocation_Calc'!$D$3:$D$74="async")*'03_Colocation_Calc'!$O$3:$O$74*'03_Colocation_Calc'!$G$3:$G$74))+SUMPRODUCT(MAX('03_Colocation_Calc'!AB$3:AB$74*--('03_Colocation_Calc'!$D$3:$D$74="load")*'03_Colocation_Calc'!$O$3:$O$74*'03_Colocation_Calc'!$G$3:$G$74)) | J11: =SUMPRODUCT('03_Colocation_Calc'!AB$3:AB$74,'03_Colocation_Calc'!$I$3:$I$74)*0.25 | K11: =SUMPRODUCT('03_Colocation_Calc'!AB$3:AB$74,'03_Colocation_Calc'!$I$3:$I$74,'03_Colocation_Calc'!$H$3:$H$74) | L11: =MAX(D11,IF('05_Params'!$B$3="strict",F11,H11),J11) | M11: =MAX(E11,IF('05_Params'!$B$3="strict",G11,I11),K11) | N11: =L11+'05_Params'!$B$5 | O11: =M11+'05_Params'!$B$6 | P11: =IFERROR(INDEX('05_Params'!$E$4:$E$23,COUNTIF('05_Params'!$E$4:$E$23,"<"&N11)+1),CEILING(N11,64)) | Q11: =IFERROR(INDEX('05_Params'!$F$4:$F$23,COUNTIF('05_Params'!$F$4:$F$23,"<"&O11)+1),CEILING(O11,64)) | R11: =SUMPRODUCT('03_Colocation_Calc'!AB$3:AB$74,'03_Colocation_Calc'!$J$3:$J$74) | S11: =SUMPRODUCT('03_Colocation_Calc'!AB$3:AB$74,'03_Colocation_Calc'!$R$3:$R$74) | T11: =('05_Params'!$B$7+R11)/(1-'05_Params'!$B$8) | U11: =S11/(1-'05_Params'!$B$8) | V11: =IFERROR(INDEX('05_Params'!$G$4:$G$23,COUNTIF('05_Params'!$G$4:$G$23,"<"&T11)+1),CEILING(T11,64)) | W11: =IF(U11<=0,0,IFERROR(INDEX('05_Params'!$G$4:$G$23,COUNTIF('05_Params'!$G$4:$G$23,"<"&U11)+1),CEILING(U11,64))) | AB11: =IF(X11="","",X11-P11) | AC11: =IF(Y11="","",Y11-Q11) | AD11: =IF(Z11="","",Z11-V11) | AE11: =IF(AA11="","",AA11-W11) | AF11: =IF(X11="","(ยังไม่กรอก spec)",IF(OR(AB11<0,AC11<0),"ไม่พอ: CPU/RAM",IF(OR(AD11<0,AE11<0),"เสี่ยง: Disk ไม่พอ","พอเพียง"))) | AG11: =IF(L11=D11,"A Peak-Max",IF(L11=J11,"C Resident","B Weighted")) | AH11: =IF(M11=E11,"A Peak-Max",IF(M11=K11,"C Resident","B Weighted"))
A12: VM10 | B12: (กรอกบทบาทหน้าที่) | C12: =SUM('03_Colocation_Calc'!AC$3:AC$74) | D12: =SUMPRODUCT(MAX('03_Colocation_Calc'!AC$3:AC$74*'03_Colocation_Calc'!$F$3:$F$74)) | E12: =SUMPRODUCT(MAX('03_Colocation_Calc'!AC$3:AC$74*'03_Colocation_Calc'!$G$3:$G$74)) | F12: =SUMPRODUCT('03_Colocation_Calc'!AC$3:AC$74,'03_Colocation_Calc'!$O$3:$O$74,'03_Colocation_Calc'!$F$3:$F$74) | G12: =SUMPRODUCT('03_Colocation_Calc'!AC$3:AC$74,'03_Colocation_Calc'!$O$3:$O$74,'03_Colocation_Calc'!$G$3:$G$74) | H12: =SUMPRODUCT('03_Colocation_Calc'!AC$3:AC$74,--('03_Colocation_Calc'!$D$3:$D$74="resident"),'03_Colocation_Calc'!$O$3:$O$74,'03_Colocation_Calc'!$F$3:$F$74)+SUMPRODUCT(MAX('03_Colocation_Calc'!AC$3:AC$74*--('03_Colocation_Calc'!$D$3:$D$74="ci_seq")*'03_Colocation_Calc'!$O$3:$O$74*'03_Colocation_Calc'!$F$3:$F$74))+SUMPRODUCT(MAX('03_Colocation_Calc'!AC$3:AC$74*--('03_Colocation_Calc'!$D$3:$D$74="async")*'03_Colocation_Calc'!$O$3:$O$74*'03_Colocation_Calc'!$F$3:$F$74))+SUMPRODUCT(MAX('03_Colocation_Calc'!AC$3:AC$74*--('03_Colocation_Calc'!$D$3:$D$74="load")*'03_Colocation_Calc'!$O$3:$O$74*'03_Colocation_Calc'!$F$3:$F$74)) | I12: =SUMPRODUCT('03_Colocation_Calc'!AC$3:AC$74,--('03_Colocation_Calc'!$D$3:$D$74="resident"),'03_Colocation_Calc'!$O$3:$O$74,'03_Colocation_Calc'!$G$3:$G$74)+SUMPRODUCT(MAX('03_Colocation_Calc'!AC$3:AC$74*--('03_Colocation_Calc'!$D$3:$D$74="ci_seq")*'03_Colocation_Calc'!$O$3:$O$74*'03_Colocation_Calc'!$G$3:$G$74))+SUMPRODUCT(MAX('03_Colocation_Calc'!AC$3:AC$74*--('03_Colocation_Calc'!$D$3:$D$74="async")*'03_Colocation_Calc'!$O$3:$O$74*'03_Colocation_Calc'!$G$3:$G$74))+SUMPRODUCT(MAX('03_Colocation_Calc'!AC$3:AC$74*--('03_Colocation_Calc'!$D$3:$D$74="load")*'03_Colocation_Calc'!$O$3:$O$74*'03_Colocation_Calc'!$G$3:$G$74)) | J12: =SUMPRODUCT('03_Colocation_Calc'!AC$3:AC$74,'03_Colocation_Calc'!$I$3:$I$74)*0.25 | K12: =SUMPRODUCT('03_Colocation_Calc'!AC$3:AC$74,'03_Colocation_Calc'!$I$3:$I$74,'03_Colocation_Calc'!$H$3:$H$74) | L12: =MAX(D12,IF('05_Params'!$B$3="strict",F12,H12),J12) | M12: =MAX(E12,IF('05_Params'!$B$3="strict",G12,I12),K12) | N12: =L12+'05_Params'!$B$5 | O12: =M12+'05_Params'!$B$6 | P12: =IFERROR(INDEX('05_Params'!$E$4:$E$23,COUNTIF('05_Params'!$E$4:$E$23,"<"&N12)+1),CEILING(N12,64)) | Q12: =IFERROR(INDEX('05_Params'!$F$4:$F$23,COUNTIF('05_Params'!$F$4:$F$23,"<"&O12)+1),CEILING(O12,64)) | R12: =SUMPRODUCT('03_Colocation_Calc'!AC$3:AC$74,'03_Colocation_Calc'!$J$3:$J$74) | S12: =SUMPRODUCT('03_Colocation_Calc'!AC$3:AC$74,'03_Colocation_Calc'!$R$3:$R$74) | T12: =('05_Params'!$B$7+R12)/(1-'05_Params'!$B$8) | U12: =S12/(1-'05_Params'!$B$8) | V12: =IFERROR(INDEX('05_Params'!$G$4:$G$23,COUNTIF('05_Params'!$G$4:$G$23,"<"&T12)+1),CEILING(T12,64)) | W12: =IF(U12<=0,0,IFERROR(INDEX('05_Params'!$G$4:$G$23,COUNTIF('05_Params'!$G$4:$G$23,"<"&U12)+1),CEILING(U12,64))) | AB12: =IF(X12="","",X12-P12) | AC12: =IF(Y12="","",Y12-Q12) | AD12: =IF(Z12="","",Z12-V12) | AE12: =IF(AA12="","",AA12-W12) | AF12: =IF(X12="","(ยังไม่กรอก spec)",IF(OR(AB12<0,AC12<0),"ไม่พอ: CPU/RAM",IF(OR(AD12<0,AE12<0),"เสี่ยง: Disk ไม่พอ","พอเพียง"))) | AG12: =IF(L12=D12,"A Peak-Max",IF(L12=J12,"C Resident","B Weighted")) | AH12: =IF(M12=E12,"A Peak-Max",IF(M12=K12,"C Resident","B Weighted"))
A15: วิธีคำนวณ (ตามเงื่อนไขที่กำหนด)
A16: เงื่อนไข 1 — A: Peak-Max | C16: คือ MAX( minimum ของทุกเครื่องมือบนเครื่องนั้น ) ตีความว่า ณ เวลาหนึ่งมีเครื่องมือเดียวที่ทำงานหนักสุด — เป็นพื้นขั้นต่ำที่ต้องมีเพื่อให้ตัวที่หนักสุดรันผ่าน
A17: เงื่อนไข 2 — B1: Weighted-Sum (strict) | C17: คือ ผลรวมของ ( minimum x w ) ทุกเครื่องมือ โดย w = 50% ถึง 95% ตามความถี่ที่เครื่องมือต้องรันหรือรันค้างหลังบ้าน (ดูชีท 02) — เป็นค่าที่โจทย์กำหนด และเป็นค่าปลอดภัยที่สุด
A18: เงื่อนไข 2 — B2: Weighted-Sum (realistic) | C18: คือ ผลรวมกลุ่ม resident (บวกทุกตัว) + ค่าสูงสุดของกลุ่ม ci_seq + ค่าสูงสุดของกลุ่ม async + ค่าสูงสุดของกลุ่ม load เพราะขั้นตอนภายใน Pipeline รอบเดียวกันทำงานเรียงต่อกัน ไม่ได้รันพร้อมกัน
A19: ตัวตรวจ — C: Resident Floor | C19: คือ ผลรวม Idle RAM ของเครื่องมือที่รันค้าง 24/7 ถ้า A และ B ต่ำกว่า C แปลว่าเครื่องบูตขึ้นมาก็เต็มแล้ว จึงต้องยกขึ้นเป็น C
A20: ผลลัพธ์ | C20: REQUIRED เท่ากับ MAX(A, B, C) + OS Reserve -> ปัดขึ้นตาม Allocation Ladder (ตามโจทย์ที่ระบุว่า 'ต้องเป็นค่าที่มากสุดสำหรับ minimum เท่านั้น')
A21: Disk OS | C21: คือ (OS Reserve + ผลรวม Install ของทุกเครื่องมือ) / (1 - Disk Free Ratio)
A22: Disk Data | C22: คือ ผลรวม Data GB ณ ช่วงเวลาที่ประเมิน / (1 - Disk Free Ratio) โดย Data GB เท่ากับ GB/วัน x Scale x (1+Growth)^(เดือน/12) x MIN(Retention, เดือน x 30.44) x (1 + Index OH)

Sheet 05_Params
A1: 05 — พารามิเตอร์ของโมเดล (แก้ไขได้) | C1: ช่องตัวอักษรสีน้ำเงิน = ผู้ใช้แก้ไขได้ / สีดำ = คำนวณอัตโนมัติ
E2: Allocation Ladder — ปัดขึ้นเสมอ
A3: โหมดการคำนวณ (mode) | B3: strict | C3: strict = ใช้เงื่อนไข B1 บวกทุกเครื่องมือถ่วงน้ำหนัก (ตามโจทย์ที่กำหนด, ปลอดภัยที่สุด) | realistic = ใช้ B2 บวกข้ามกลุ่มและใช้ค่าสูงสุดในกลุ่มที่รันเรียงกัน | E3: vCPU | F3: RAM (GB) | G3: Disk (GB)
A4: Scale Factor ปริมาณข้อมูล | B4: 1 | C4: 1.0 = ค่าฐาน UAT/Production ขนาดเล็ก (~10 builds/วัน, 1-3 แอป, ทีม 5-15 คน). ทีม 50 คน / 50 builds ต่อวัน ให้ใช้ 3-5 | E4: 2 | F4: 2 | G4: 20
A5: OS Reserve — vCPU | B5: 1 | C5: กันไว้ให้ OS + Container Runtime ของทุก VM | E5: 4 | F5: 4 | G5: 40
A6: OS Reserve — RAM (GB) | B6: 2 | C6: กันไว้ให้ OS + Docker/containerd + Agent ต่าง ๆ | E6: 6 | F6: 8 | G6: 60
A7: OS Reserve — Disk (GB) | B7: 20 | C7: ระบบปฏิบัติการ Ubuntu + swap + log ระบบ | E7: 8 | F7: 12 | G7: 80
A8: Disk Free Ratio | B8: 0.25 | C8: ต้องเหลือพื้นที่ว่างเป็นสัดส่วนนี้เสมอ (0.25 = เหลือว่าง 25%) เพราะ Docker/Elasticsearch จะหยุดทำงานเมื่อ disk ใกล้เต็ม | E8: 12 | F8: 16 | G8: 100
A9: w_base (น้ำหนักต่ำสุด) | B9: 0.2 | C9: คือ 20% — ใช้กับเครื่องมือที่รันตามคำสั่ง/รอบ Release | E9: 16 | F9: 24 | G9: 150
A10: w_span (ช่วงน้ำหนัก) | B10: 0.4 | C10: คือ 0.40 ทำให้น้ำหนักเดี่ยวสูงสุด = 0.20 + 0.40 = 0.60 (60%) เมื่ออยู่เครื่องเดียว | E10: 24 | F10: 32 | G10: 200
E11: 32 | F11: 48 | G11: 300
A12: ช่วงเวลาประเมินผลลัพธ์ระยะยาว (เดือน) | E12: 48 | F12: 64 | G12: 500
A13: H1 | B13: 12 | E13: 64 | F13: 96 | G13: 750
A14: H2 | B14: 24 | F14: 128 | G14: 1000
A15: H3 | B15: 36 | C15: ค่านี้ใช้ในคอลัมน์ 'Data @H3' ของชีท 04_VM_Sizing | F15: 192 | G15: 1500
A16: H4 | B16: 60 | F16: 256 | G16: 2000
G17: 3000
G18: 4000
G19: 6000
G20: 8000

Sheet 06_Storage_LongTerm
A1: 06 — ผลลัพธ์ระยะยาวของพื้นที่จัดเก็บ (Storage Long-term Projection) | C1: ต่อ 1 instance ของเครื่องมือ — คูณจำนวน instance และรวมตาม VM ที่ชีท 04
A2: tool_id | B2: เครื่องมือ | C2: Install (GB) | D2: GB/วัน | E2: Retention (วัน) | F2: Index OH | G2: Growth/ปี | H2: รวม @12 ด. | I2: รวม @24 ด. | J2: รวม @36 ด. | K2: รวม @60 ด. | L2: ต้องจัดสรร @60 ด. | M2: ข้อควรทำเพื่อคุมการโต
A3: gitlab-ce | B3: GitLab Community Edition (Self-hosted Git) | C3: 40 | D3: 0.05 | E3: 3650 | F3: 0.2 | G3: 0.25 | H3: =$C3+$D3*'05_Params'!$B$4*POWER(1+$G3,'05_Params'!$B$13/12)*MIN($E3,'05_Params'!$B$13*30.44)*(1+$F3) | I3: =$C3+$D3*'05_Params'!$B$4*POWER(1+$G3,'05_Params'!$B$14/12)*MIN($E3,'05_Params'!$B$14*30.44)*(1+$F3) | J3: =$C3+$D3*'05_Params'!$B$4*POWER(1+$G3,'05_Params'!$B$15/12)*MIN($E3,'05_Params'!$B$15*30.44)*(1+$F3) | K3: =$C3+$D3*'05_Params'!$B$4*POWER(1+$G3,'05_Params'!$B$16/12)*MIN($E3,'05_Params'!$B$16*30.44)*(1+$F3) | L3: =IFERROR(INDEX('05_Params'!$G$4:$G$23,COUNTIF('05_Params'!$G$4:$G$23,"<"&K3/(1-'05_Params'!$B$8))+1),CEILING(K3/(1-'05_Params'!$B$8),64)) | M3: ตั้ง housekeeping (git gc) อัตโนมัติ + จำกัดขนาด artifact และ LFS
A4: gitea | B4: Gitea / Forgejo (Lightweight Git) | C4: 10 | D4: 0.02 | E4: 3650 | F4: 0.1 | G4: 0.25 | H4: =$C4+$D4*'05_Params'!$B$4*POWER(1+$G4,'05_Params'!$B$13/12)*MIN($E4,'05_Params'!$B$13*30.44)*(1+$F4) | I4: =$C4+$D4*'05_Params'!$B$4*POWER(1+$G4,'05_Params'!$B$14/12)*MIN($E4,'05_Params'!$B$14*30.44)*(1+$F4) | J4: =$C4+$D4*'05_Params'!$B$4*POWER(1+$G4,'05_Params'!$B$15/12)*MIN($E4,'05_Params'!$B$15*30.44)*(1+$F4) | K4: =$C4+$D4*'05_Params'!$B$4*POWER(1+$G4,'05_Params'!$B$16/12)*MIN($E4,'05_Params'!$B$16*30.44)*(1+$F4) | L4: =IFERROR(INDEX('05_Params'!$G$4:$G$23,COUNTIF('05_Params'!$G$4:$G$23,"<"&K4/(1-'05_Params'!$B$8))+1),CEILING(K4/(1-'05_Params'!$B$8),64)) | M4: ปริมาณข้อมูลน้อย ไม่ต้องมีนโยบายเฉพาะ — รวมอยู่ใน Disk OS ได้
A5: github-actions-runner | B5: GitHub Actions Self-hosted Runner | C5: 60 | D5: 0.6 | E5: 30 | F5: 0.05 | G5: 0.2 | H5: =$C5+$D5*'05_Params'!$B$4*POWER(1+$G5,'05_Params'!$B$13/12)*MIN($E5,'05_Params'!$B$13*30.44)*(1+$F5) | I5: =$C5+$D5*'05_Params'!$B$4*POWER(1+$G5,'05_Params'!$B$14/12)*MIN($E5,'05_Params'!$B$14*30.44)*(1+$F5) | J5: =$C5+$D5*'05_Params'!$B$4*POWER(1+$G5,'05_Params'!$B$15/12)*MIN($E5,'05_Params'!$B$15*30.44)*(1+$F5) | K5: =$C5+$D5*'05_Params'!$B$4*POWER(1+$G5,'05_Params'!$B$16/12)*MIN($E5,'05_Params'!$B$16*30.44)*(1+$F5) | L5: =IFERROR(INDEX('05_Params'!$G$4:$G$23,COUNTIF('05_Params'!$G$4:$G$23,"<"&K5/(1-'05_Params'!$B$8))+1),CEILING(K5/(1-'05_Params'!$B$8),64)) | M5: ปริมาณข้อมูลน้อย ไม่ต้องมีนโยบายเฉพาะ — รวมอยู่ใน Disk OS ได้
A6: jenkins-master | B6: Jenkins Master / Controller | C6: 20 | D6: 0.15 | E6: 180 | F6: 0.1 | G6: 0.15 | H6: =$C6+$D6*'05_Params'!$B$4*POWER(1+$G6,'05_Params'!$B$13/12)*MIN($E6,'05_Params'!$B$13*30.44)*(1+$F6) | I6: =$C6+$D6*'05_Params'!$B$4*POWER(1+$G6,'05_Params'!$B$14/12)*MIN($E6,'05_Params'!$B$14*30.44)*(1+$F6) | J6: =$C6+$D6*'05_Params'!$B$4*POWER(1+$G6,'05_Params'!$B$15/12)*MIN($E6,'05_Params'!$B$15*30.44)*(1+$F6) | K6: =$C6+$D6*'05_Params'!$B$4*POWER(1+$G6,'05_Params'!$B$16/12)*MIN($E6,'05_Params'!$B$16*30.44)*(1+$F6) | L6: =IFERROR(INDEX('05_Params'!$G$4:$G$23,COUNTIF('05_Params'!$G$4:$G$23,"<"&K6/(1-'05_Params'!$B$8))+1),CEILING(K6/(1-'05_Params'!$B$8),64)) | M6: ตั้ง buildDiscarder(logRotator(numToKeepStr:'50', daysToKeepStr:'180'))
A7: jenkins-agent | B7: Jenkins Agent / Build Executor (ต่อ 1 Executor) | C7: 60 | D7: 0.8 | E7: 7 | F7: 0.05 | G7: 0.2 | H7: =$C7+$D7*'05_Params'!$B$4*POWER(1+$G7,'05_Params'!$B$13/12)*MIN($E7,'05_Params'!$B$13*30.44)*(1+$F7) | I7: =$C7+$D7*'05_Params'!$B$4*POWER(1+$G7,'05_Params'!$B$14/12)*MIN($E7,'05_Params'!$B$14*30.44)*(1+$F7) | J7: =$C7+$D7*'05_Params'!$B$4*POWER(1+$G7,'05_Params'!$B$15/12)*MIN($E7,'05_Params'!$B$15*30.44)*(1+$F7) | K7: =$C7+$D7*'05_Params'!$B$4*POWER(1+$G7,'05_Params'!$B$16/12)*MIN($E7,'05_Params'!$B$16*30.44)*(1+$F7) | L7: =IFERROR(INDEX('05_Params'!$G$4:$G$23,COUNTIF('05_Params'!$G$4:$G$23,"<"&K7/(1-'05_Params'!$B$8))+1),CEILING(K7/(1-'05_Params'!$B$8),64)) | M7: ใช้ cleanWs() ทุกท้าย Pipeline และตั้ง Workspace Cleanup Plugin
A8: argo-workflows | B8: Argo Workflows (CNCF Graduated) | C8: 10 | D8: 0.15 | E8: 90 | F8: 0.1 | G8: 0.2 | H8: =$C8+$D8*'05_Params'!$B$4*POWER(1+$G8,'05_Params'!$B$13/12)*MIN($E8,'05_Params'!$B$13*30.44)*(1+$F8) | I8: =$C8+$D8*'05_Params'!$B$4*POWER(1+$G8,'05_Params'!$B$14/12)*MIN($E8,'05_Params'!$B$14*30.44)*(1+$F8) | J8: =$C8+$D8*'05_Params'!$B$4*POWER(1+$G8,'05_Params'!$B$15/12)*MIN($E8,'05_Params'!$B$15*30.44)*(1+$F8) | K8: =$C8+$D8*'05_Params'!$B$4*POWER(1+$G8,'05_Params'!$B$16/12)*MIN($E8,'05_Params'!$B$16*30.44)*(1+$F8) | L8: =IFERROR(INDEX('05_Params'!$G$4:$G$23,COUNTIF('05_Params'!$G$4:$G$23,"<"&K8/(1-'05_Params'!$B$8))+1),CEILING(K8/(1-'05_Params'!$B$8),64)) | M8: ปริมาณข้อมูลน้อย ไม่ต้องมีนโยบายเฉพาะ — รวมอยู่ใน Disk OS ได้
A9: opa-conftest | B9: Open Policy Agent / Conftest (Policy-as-Code Gate) | C9: 5 | D9: 0.01 | E9: 90 | F9: 0.05 | G9: 0.1 | H9: =$C9+$D9*'05_Params'!$B$4*POWER(1+$G9,'05_Params'!$B$13/12)*MIN($E9,'05_Params'!$B$13*30.44)*(1+$F9) | I9: =$C9+$D9*'05_Params'!$B$4*POWER(1+$G9,'05_Params'!$B$14/12)*MIN($E9,'05_Params'!$B$14*30.44)*(1+$F9) | J9: =$C9+$D9*'05_Params'!$B$4*POWER(1+$G9,'05_Params'!$B$15/12)*MIN($E9,'05_Params'!$B$15*30.44)*(1+$F9) | K9: =$C9+$D9*'05_Params'!$B$4*POWER(1+$G9,'05_Params'!$B$16/12)*MIN($E9,'05_Params'!$B$16*30.44)*(1+$F9) | L9: =IFERROR(INDEX('05_Params'!$G$4:$G$23,COUNTIF('05_Params'!$G$4:$G$23,"<"&K9/(1-'05_Params'!$B$8))+1),CEILING(K9/(1-'05_Params'!$B$8),64)) | M9: ปริมาณข้อมูลน้อย ไม่ต้องมีนโยบายเฉพาะ — รวมอยู่ใน Disk OS ได้
A10: nginx-gateway | B10: Nginx (Reverse Proxy / Webhook Relay) | C10: 10 | D10: 0.1 | E10: 90 | F10: 0.1 | G10: 0.2 | H10: =$C10+$D10*'05_Params'!$B$4*POWER(1+$G10,'05_Params'!$B$13/12)*MIN($E10,'05_Params'!$B$13*30.44)*(1+$F10) | I10: =$C10+$D10*'05_Params'!$B$4*POWER(1+$G10,'05_Params'!$B$14/12)*MIN($E10,'05_Params'!$B$14*30.44)*(1+$F10) | J10: =$C10+$D10*'05_Params'!$B$4*POWER(1+$G10,'05_Params'!$B$15/12)*MIN($E10,'05_Params'!$B$15*30.44)*(1+$F10) | K10: =$C10+$D10*'05_Params'!$B$4*POWER(1+$G10,'05_Params'!$B$16/12)*MIN($E10,'05_Params'!$B$16*30.44)*(1+$F10) | L10: =IFERROR(INDEX('05_Params'!$G$4:$G$23,COUNTIF('05_Params'!$G$4:$G$23,"<"&K10/(1-'05_Params'!$B$8))+1),CEILING(K10/(1-'05_Params'!$B$8),64)) | M10: ปริมาณข้อมูลน้อย ไม่ต้องมีนโยบายเฉพาะ — รวมอยู่ใน Disk OS ได้
A11: sonarqube | B11: SonarQube Community Edition | C11: 30 | D11: 0.1 | E11: 365 | F11: 0.3 | G11: 0.2 | H11: =$C11+$D11*'05_Params'!$B$4*POWER(1+$G11,'05_Params'!$B$13/12)*MIN($E11,'05_Params'!$B$13*30.44)*(1+$F11) | I11: =$C11+$D11*'05_Params'!$B$4*POWER(1+$G11,'05_Params'!$B$14/12)*MIN($E11,'05_Params'!$B$14*30.44)*(1+$F11) | J11: =$C11+$D11*'05_Params'!$B$4*POWER(1+$G11,'05_Params'!$B$15/12)*MIN($E11,'05_Params'!$B$15*30.44)*(1+$F11) | K11: =$C11+$D11*'05_Params'!$B$4*POWER(1+$G11,'05_Params'!$B$16/12)*MIN($E11,'05_Params'!$B$16*30.44)*(1+$F11) | L11: =IFERROR(INDEX('05_Params'!$G$4:$G$23,COUNTIF('05_Params'!$G$4:$G$23,"<"&K11/(1-'05_Params'!$B$8))+1),CEILING(K11/(1-'05_Params'!$B$8),64)) | M11: ตั้ง Housekeeping: ลบ snapshot ที่เก่ากว่า 30 วัน, เก็บเฉพาะ analysis ของ branch หลัก
A12: postgresql-tools | B12: PostgreSQL (ฐานข้อมูลของเครื่องมือ CI/CD) | C12: 20 | D12: 0.05 | E12: 2555 | F12: 0.35 | G12: 0.2 | H12: =$C12+$D12*'05_Params'!$B$4*POWER(1+$G12,'05_Params'!$B$13/12)*MIN($E12,'05_Params'!$B$13*30.44)*(1+$F12) | I12: =$C12+$D12*'05_Params'!$B$4*POWER(1+$G12,'05_Params'!$B$14/12)*MIN($E12,'05_Params'!$B$14*30.44)*(1+$F12) | J12: =$C12+$D12*'05_Params'!$B$4*POWER(1+$G12,'05_Params'!$B$15/12)*MIN($E12,'05_Params'!$B$15*30.44)*(1+$F12) | K12: =$C12+$D12*'05_Params'!$B$4*POWER(1+$G12,'05_Params'!$B$16/12)*MIN($E12,'05_Params'!$B$16*30.44)*(1+$F12) | L12: =IFERROR(INDEX('05_Params'!$G$4:$G$23,COUNTIF('05_Params'!$G$4:$G$23,"<"&K12/(1-'05_Params'!$B$8))+1),CEILING(K12/(1-'05_Params'!$B$8),64)) | M12: ตั้ง partition ตารางที่โตเร็วเป็นรายเดือน + archive ไป MinIO เมื่อเกิน 1 ปี (Audit Trail ภาครัฐต้องเก็บ 7 ปีแต่ไม่จำเป็นต้องอยู่ใน DB หลัก)
A13: semgrep | B13: Semgrep (SAST แบบ Rule-based) | C13: 5 | D13: 0.02 | E13: 180 | F13: 0.05 | G13: 0.15 | H13: =$C13+$D13*'05_Params'!$B$4*POWER(1+$G13,'05_Params'!$B$13/12)*MIN($E13,'05_Params'!$B$13*30.44)*(1+$F13) | I13: =$C13+$D13*'05_Params'!$B$4*POWER(1+$G13,'05_Params'!$B$14/12)*MIN($E13,'05_Params'!$B$14*30.44)*(1+$F13) | J13: =$C13+$D13*'05_Params'!$B$4*POWER(1+$G13,'05_Params'!$B$15/12)*MIN($E13,'05_Params'!$B$15*30.44)*(1+$F13) | K13: =$C13+$D13*'05_Params'!$B$4*POWER(1+$G13,'05_Params'!$B$16/12)*MIN($E13,'05_Params'!$B$16*30.44)*(1+$F13) | L13: =IFERROR(INDEX('05_Params'!$G$4:$G$23,COUNTIF('05_Params'!$G$4:$G$23,"<"&K13/(1-'05_Params'!$B$8))+1),CEILING(K13/(1-'05_Params'!$B$8),64)) | M13: ปริมาณข้อมูลน้อย ไม่ต้องมีนโยบายเฉพาะ — รวมอยู่ใน Disk OS ได้
A14: gitleaks | B14: GitLeaks / TruffleHog (Secret Scanning) | C14: 3 | D14: 0.01 | E14: 365 | F14: 0.05 | G14: 0.1 | H14: =$C14+$D14*'05_Params'!$B$4*POWER(1+$G14,'05_Params'!$B$13/12)*MIN($E14,'05_Params'!$B$13*30.44)*(1+$F14) | I14: =$C14+$D14*'05_Params'!$B$4*POWER(1+$G14,'05_Params'!$B$14/12)*MIN($E14,'05_Params'!$B$14*30.44)*(1+$F14) | J14: =$C14+$D14*'05_Params'!$B$4*POWER(1+$G14,'05_Params'!$B$15/12)*MIN($E14,'05_Params'!$B$15*30.44)*(1+$F14) | K14: =$C14+$D14*'05_Params'!$B$4*POWER(1+$G14,'05_Params'!$B$16/12)*MIN($E14,'05_Params'!$B$16*30.44)*(1+$F14) | L14: =IFERROR(INDEX('05_Params'!$G$4:$G$23,COUNTIF('05_Params'!$G$4:$G$23,"<"&K14/(1-'05_Params'!$B$8))+1),CEILING(K14/(1-'05_Params'!$B$8),64)) | M14: ปริมาณข้อมูลน้อย ไม่ต้องมีนโยบายเฉพาะ — รวมอยู่ใน Disk OS ได้
... A74: gcp-cloud-operations | B74: Google Cloud Operations (Logging + Monitoring + Trace) | C74: 0 | D74: 1 | E74: 90 | F74: 0.1 | G74: 0.3 | H74: =$C74+$D74*'05_Params'!$B$4*POWER(1+$G74,'05_Params'!$B$13/12)*MIN($E74,'05_Params'!$B$13*30.44)*(1+$F74) | I74: =$C74+$D74*'05_Params'!$B$4*POWER(1+$G74,'05_Params'!$B$14/12)*MIN($E74,'05_Params'!$B$14*30.44)*(1+$F74) | J74: =$C74+$D74*'05_Params'!$B$4*POWER(1+$G74,'05_Params'!$B$15/12)*MIN($E74,'05_Params'!$B$15*30.44)*(1+$F74) | K74: =$C74+$D74*'05_Params'!$B$4*POWER(1+$G74,'05_Params'!$B$16/12)*MIN($E74,'05_Params'!$B$16*30.44)*(1+$F74) | L74: =IFERROR(INDEX('05_Params'!$G$4:$G$23,COUNTIF('05_Params'!$G$4:$G$23,"<"&K74/(1-'05_Params'!$B$8))+1),CEILING(K74/(1-'05_Params'!$B$8),64)) | M74: ปริมาณข้อมูลน้อย ไม่ต้องมีนโยบายเฉพาะ — รวมอยู่ใน Disk OS ได้
B75: รวมทุกเครื่องมือ (กรณีติดตั้งครบทุกตัว) | C75: =SUM(C3:C74) | H75: =SUM(H3:H74) | I75: =SUM(I3:I74) | J75: =SUM(J3:J74) | K75: =SUM(K3:K74)

Sheet 07_Compliance_Matrix
A1: 07 — มาตรการที่ต้องทำ (Controls) และสถานะตามเครื่องมือที่เลือก | C1: 1 แถว = 1 มาตรการ · มาตรฐานหลายฉบับอ้างมาตรการเดียวกันได้ ดูเลขข้อในคอลัมน์ท้าย
A2: control_id | B2: กลุ่มมาตรการ | C2: ระดับบังคับ | D2: มาตรการที่ต้องทำ | E2: คำอธิบายเพิ่มเติม | F2: Capability ที่ต้องมี | G2: สถานะ | H2: Capability ที่ยังขาด | I2: มาตรฐานที่อ้างมาตรการนี้ (เลขข้อ)
A3: C-SDLC-REVIEW | B3: กระบวนการพัฒนาและ Pipeline | C3: บังคับ | D3: โค้ดต้องผ่าน Code Review และ Status Check ก่อน Merge เข้า main | E3: ภาครัฐบังคับอย่างน้อย 2 ผู้อนุมัติ และห้าม merge โค้ดที่ตกเกณฑ์ | F3: git_scm, branch_protection, quality_gate | G3: =IF(('08_Tool_Capability'!C$76+'08_Tool_Capability'!E$76+'08_Tool_Capability'!AB$76)>=3,"ผ่าน","ไม่ผ่าน") | H3: =IF('08_Tool_Capability'!C$76=0,"git_scm ","")&IF('08_Tool_Capability'!E$76=0,"branch_protection ","")&IF('08_Tool_Capability'!AB$76=0,"quality_gate ","") | I3: ISO/IEC 27001:2022 — A.8.25, A.8.28 OWASP SAMM 2 — Implementation — Secure Build NIST SSDF (SP 800-218) — PW.7 Review Human-Readable Code SOC 2 (TSC) — CC8 Change Management
A4: C-SDLC-TRACE | B4: กระบวนการพัฒนาและ Pipeline | C4: บังคับ | D4: Pipeline ทำงานอัตโนมัติและตรวจสอบย้อนหลังได้ 100% (Traceability) | E4: ต้องรู้ได้ว่า artifact ที่ขึ้น production มาจาก commit ใด ผ่านขั้นตอนอะไร ใครอนุมัติ | F4: pipeline, webhook, audit_trail, version_tag | G4: =IF(('08_Tool_Capability'!F$76+'08_Tool_Capability'!D$76+'08_Tool_Capability'!Y$76+'08_Tool_Capability'!W$76)>=4,"ผ่าน","ไม่ผ่าน") | H4: =IF('08_Tool_Capability'!F$76=0,"pipeline ","")&IF('08_Tool_Capability'!D$76=0,"webhook ","")&IF('08_Tool_Capability'!Y$76=0,"audit_trail ","")&IF('08_Tool_Capability'!W$76=0,"version_tag ","") | I4: พ.ร.บ. ปฏิบัติราชการทางอิเล็กทรอนิกส์ 2565 — ความน่าเชื่อถือของระบบ มาตรฐานข้อมูลเปิดภาครัฐ — ที่มาของข้อมูล (Provenance) NIST SSDF (SP 800-218) — PO.3 Implement Supporting Toolchains SLSA v1.0 — Provenance Available
A5: C-SDLC-SAST | B5: กระบวนการพัฒนาและ Pipeline | C5: บังคับ | D5: สแกนหาช่องโหว่ในซอร์สโค้ดแบบ Static (SAST) ทุกรอบ | E5: ตั้งเป็น Blocking Gate สำหรับช่องโหว่ระดับ Critical/High | F5: sast | G5: =IF(('08_Tool_Capability'!G$76)>=1,"ผ่าน","ไม่ผ่าน") | H5: =IF('08_Tool_Capability'!G$76=0,"sast ","") | I5: มาตรฐานเว็บไซต์ 2568 — Secure Coding ขมธอ. ความมั่นคงปลอดภัยสารสนเทศ — การพัฒนาซอฟต์แวร์อย่างปลอดภัย ISO/IEC 27002:2022 — 8.28 ISO/IEC 27034 — ASC OWASP SAMM 2 — Verification — Security Testing NIST SSDF (SP 800-218) — PW.8 Test Executable Code NIST SP 800-53r5 — SA-11 CIS Controls v8.1 — Control 16 Application Software Security PCI DSS v4.0 — Req 6.2 Secure development
A6: C-SDLC-SECRET | B6: กระบวนการพัฒนาและ Pipeline | C6: บังคับ | D6: ห้าม Credential / Secret หลุดไปกับซอร์สโค้ดหรือ Log | E6: ต้องมี Secret Scanning ใน Pipeline และเก็บ Secret ใน Secret Manager | F6: secret_scan, secret_mgmt | G6: =IF(('08_Tool_Capability'!H$76+'08_Tool_Capability'!AG$76)>=2,"ผ่าน","ไม่ผ่าน") | H6: =IF('08_Tool_Capability'!H$76=0,"secret_scan ","")&IF('08_Tool_Capability'!AG$76=0,"secret_mgmt ","") | I6: ISO/IEC 27002:2022 — 8.24
A7: C-SDLC-QUALITY | B7: กระบวนการพัฒนาและ Pipeline | C7: บังคับ | D7: วัดคุณภาพโค้ดและ Test Coverage ตามเกณฑ์ที่กำหนด | E7: ภาครัฐมักกำหนด Coverage มากกว่า 80% และ Technical Debt ในระดับที่ยอมรับได้ | F7: code_quality, unit_test | G7: =IF(('08_Tool_Capability'!K$76+'08_Tool_Capability'!Q$76)>=2,"ผ่าน","ไม่ผ่าน") | H7: =IF('08_Tool_Capability'!K$76=0,"code_quality ","")&IF('08_Tool_Capability'!Q$76=0,"unit_test ","") | I7: ISO/IEC 25010:2023 — Maintainability
A8: C-SDLC-TEST | B8: กระบวนการพัฒนาและ Pipeline | C8: บังคับ | D8: ต้องมี Unit Test และ Integration Test ก่อนขึ้นระบบ | F8: unit_test, integration_test | G8: =IF(('08_Tool_Capability'!Q$76+'08_Tool_Capability'!R$76)>=2,"ผ่าน","ไม่ผ่าน") | H8: =IF('08_Tool_Capability'!Q$76=0,"unit_test ","")&IF('08_Tool_Capability'!R$76=0,"integration_test ","") | I8: ISO/IEC 27001:2022 — A.8.29 ISO/IEC 27034 — Verification ISO/IEC 25010:2023 — Functional Suitability NIST SSDF (SP 800-218) — PW.8 Test Executable Code
A9: C-SDLC-THREAT | B9: กระบวนการพัฒนาและ Pipeline | C9: แนะนำ | D9: ทำ Threat Modeling และ Security Architecture Review ตั้งแต่ออกแบบ | E9: ใช้ STRIDE / PASTA และทบทวนเมื่อสถาปัตยกรรมเปลี่ยน | F9: code_quality, quality_gate | G9: =IF(('08_Tool_Capability'!K$76+'08_Tool_Capability'!AB$76)>=2,"ผ่าน","ไม่ผ่าน") | H9: =IF('08_Tool_Capability'!K$76=0,"code_quality ","")&IF('08_Tool_Capability'!AB$76=0,"quality_gate ","") | I9: ISO/IEC 27001:2022 — A.8.27 ISO/IEC 27034 — Application Security Life Cycle OWASP Top 10:2025 — A06 Insecure Design OWASP SAMM 2 — Design — Threat Assessment
A10: C-APP-ACCESS | B10: ความปลอดภัยของแอปพลิเคชัน | C10: บังคับ | D10: ควบคุมสิทธิ์การเข้าถึงฝั่ง Server ทุก Request (รวมป้องกัน SSRF) | E10: deny-by-default, ตรวจ authorization ทุกครั้ง, ใช้ allowlist ปลายทางกัน SSRF | F10: sast, api_security, dast | G10: =IF(('08_Tool_Capability'!G$76+'08_Tool_Capability'!T$76+'08_Tool_Capability'!S$76)>=3,"ผ่าน","ไม่ผ่าน") | H10: =IF('08_Tool_Capability'!G$76=0,"sast ","")&IF('08_Tool_Capability'!T$76=0,"api_security ","")&IF('08_Tool_Capability'!S$76=0,"dast ","") | I10: OWASP Top 10:2025 — A01 Broken Access Control (รวม SSRF) OWASP ASVS 5.0 — V4 Access Control OWASP API Top 10:2023 — API1 BOLA / API3 BOPLA
A11: C-APP-INJECT | B11: ความปลอดภัยของแอปพลิเคชัน | C11: บังคับ | D11: ป้องกัน Injection ทุกรูปแบบ (SQL, Command, XSS) | E11: parameterized query, allowlist validation, output encoding, CSP header | F11: sast, dast | G11: =IF(('08_Tool_Capability'!G$76+'08_Tool_Capability'!S$76)>=2,"ผ่าน","ไม่ผ่าน") | H11: =IF('08_Tool_Capability'!G$76=0,"sast ","")&IF('08_Tool_Capability'!S$76=0,"dast ","") | I11: OWASP Top 10:2025 — A05 Injection OWASP ASVS 5.0 — V5 Validation & Encoding
A12: C-APP-AUTHN | B12: ความปลอดภัยของแอปพลิเคชัน | C12: บังคับ | D12: Authentication ปลอดภัย: hashing ที่แข็งแรง, session rotation, rate limiting | F12: iam_mfa, api_security | G12: =IF(('08_Tool_Capability'!AN$76+'08_Tool_Capability'!T$76)>=2,"ผ่าน","ไม่ผ่าน") | H12: =IF('08_Tool_Capability'!AN$76=0,"iam_mfa ","")&IF('08_Tool_Capability'!T$76=0,"api_security ","") | I12: OWASP Top 10:2025 — A07 Authentication Failures OWASP ASVS 5.0 — V2 Authentication OWASP API Top 10:2023 — API2 Broken Authentication OWASP MASVS — MASVS-AUTH NIST SP 800-63B — 5.1 Authenticator Requirements
A13: C-APP-ERROR | B13: ความปลอดภัยของแอปพลิเคชัน | C13: แนะนำ | D13: จัดการข้อผิดพลาดแบบ fail-safe ไม่เปิดเผย stack trace | F13: sast, code_quality | G13: =IF(('08_Tool_Capability'!G$76+'08_Tool_Capability'!K$76)>=2,"ผ่าน","ไม่ผ่าน") | H13: =IF('08_Tool_Capability'!G$76=0,"sast ","")&IF('08_Tool_Capability'!K$76=0,"code_quality ","") | I13: OWASP Top 10:2025 — A10 Mishandling of Exceptional Conditions OWASP ASVS 5.0 — V7 Error Handling & Logging OWASP MASVS — MASVS-CODE
A14: C-APP-DAST | B14: ความปลอดภัยของแอปพลิเคชัน | C14: บังคับ | D14: ทดสอบความปลอดภัยกับระบบที่รันอยู่จริง (DAST) | E14: ต้องรันบน Staging/UAT ที่มีข้อมูลเสมือนจริง ไม่ยิงจากเครื่องเดียวกับ target | F14: dast | G14: =IF(('08_Tool_Capability'!S$76)>=1,"ผ่าน","ไม่ผ่าน") | H14: =IF('08_Tool_Capability'!S$76=0,"dast ","") | I14: ISO/IEC 27034 — Verification OWASP SAMM 2 — Verification — Security Testing
A15: C-APP-API | B15: ความปลอดภัยของแอปพลิเคชัน | C15: บังคับ | D15: ทดสอบความปลอดภัยของ API (Authn, RBAC, Input Validation, Fuzzing) | F15: api_security | G15: =IF(('08_Tool_Capability'!T$76)>=1,"ผ่าน","ไม่ผ่าน") | H15: =IF('08_Tool_Capability'!T$76=0,"api_security ","") | I15: OWASP API Top 10:2023 — API1-API10
A16: C-APP-PENTEST | B16: ความปลอดภัยของแอปพลิเคชัน | C16: บังคับเมื่อผลกระทบสูง | D16: ประเมินช่องโหว่และทดสอบเจาะระบบ (VAPT) ก่อน Go-Live และเป็นระยะ | F16: vapt, dast | G16: =IF(('08_Tool_Capability'!AP$76+'08_Tool_Capability'!S$76)>=2,"ผ่าน","ไม่ผ่าน") | H16: =IF('08_Tool_Capability'!AP$76=0,"vapt ","")&IF('08_Tool_Capability'!S$76=0,"dast ","") | I16: พ.ร.บ. ไซเบอร์ 2562 — ม.54-57 มาตรฐานขั้นต่ำ 2566 — ระดับสูง — VAPT มาตรฐานเว็บไซต์ 2568 — Penetration Testing กรอบมาตรฐานไซเบอร์ 2564 — การประเมินความเสี่ยง ISO/IEC 27001:2022 — A.8.8 NIST SP 800-53r5 — CA-8 CIS Controls v8.1 — Control 18 Penetration Testing PCI DSS v4.0 — Req 11.4 Penetration testing
A17: C-APP-WAF | B17: ความปลอดภัยของแอปพลิเคชัน | C17: บังคับ | D17: ติดตั้ง Web Application Firewall หน้าระบบที่เปิดสู่ภายนอก | F17: waf | G17: =IF(('08_Tool_Capability'!AI$76)>=1,"ผ่าน","ไม่ผ่าน") | H17: =IF('08_Tool_Capability'!AI$76=0,"waf ","") | I17: มาตรฐานเว็บไซต์ 2568 — Website Security Operation มสพร. 11-2566 เว็บไซต์ภาครัฐ 3.0 — มาตรการทางเทคนิค (แนะนำ) PCI DSS v4.0 — Req 6.4.2 Automated technical solution
A18: C-SC-SBOM | B18: ความปลอดภัยของ Supply Chain | C18: บังคับ | D18: สร้าง SBOM ทุก artifact และเก็บคู่กับ artifact | E18: รูปแบบ SPDX หรือ CycloneDX เก็บนานเท่าอายุการใช้งานของระบบ | F18: sbom | G18: =IF(('08_Tool_Capability'!X$76)>=1,"ผ่าน","ไม่ผ่าน") | H18: =IF('08_Tool_Capability'!X$76=0,"sbom ","") | I18: มาตรฐานขั้นต่ำ 2566 — ระดับสูง — Third Party Management OWASP Top 10:2025 — A03 Software Supply Chain Failures NIST SSDF (SP 800-218) — PS.3 Archive and Protect Each Release NIST SP 800-161r1 — SR-4 Provenance SLSA v1.0 — Provenance content SPDX / ISO 5962 — SPDX document CycloneDX / ECMA-424 — BOM CSA CCM v4 / STAR — AIS-06
A19: C-SC-SCA | B19: ความปลอดภัยของ Supply Chain | C19: บังคับ | D19: ตรวจ Dependency เทียบฐานข้อมูลช่องโหว่ (CVE) ทุกรอบ | F19: sca | G19: =IF(('08_Tool_Capability'!I$76)>=1,"ผ่าน","ไม่ผ่าน") | H19: =IF('08_Tool_Capability'!I$76=0,"sca ","") | I19: มาตรฐานขั้นต่ำ 2566 — ระดับสูง — Third Party Management ISO/IEC 27002:2022 — 8.8 OWASP Top 10:2025 — A03 Software Supply Chain Failures NIST SP 800-161r1 — SR-3 CIS Controls v8.1 — Control 7 Continuous Vulnerability Management CycloneDX / ECMA-424 — VEX PCI DSS v4.0 — Req 6.3 Vulnerability management
A20: C-SC-LICENSE | B20: ความปลอดภัยของ Supply Chain | C20: บังคับเมื่อผลกระทบสูง | D20: ตรวจลิขสิทธิ์ของ Open Source ให้สอดคล้องนโยบายองค์กร | E20: โครงการภาครัฐหลายแห่งห้ามใช้ GPL/AGPL ในงานเชิงพาณิชย์ | F20: license | G20: =IF(('08_Tool_Capability'!J$76)>=1,"ผ่าน","ไม่ผ่าน") | H20: =IF('08_Tool_Capability'!J$76=0,"license ","") | I20: ISO/IEC 27001:2022 — A.5.32 NIST SP 800-161r1 — SR-5 SPDX / ISO 5962 — License expression
A21: C-SC-SIGN | B21: ความปลอดภัยของ Supply Chain | C21: บังคับ | D21: ลงนามดิจิทัลบน artifact และ Verify ลายเซ็นก่อน Deploy ทุกครั้ง | E21: การ Sign อย่างเดียวไม่พอ ต้องบังคับ Verify ที่ขั้น Deploy ด้วย | F21: artifact_sign | G21: =IF(('08_Tool_Capability'!P$76)>=1,"ผ่าน","ไม่ผ่าน") | H21: =IF('08_Tool_Capability'!P$76=0,"artifact_sign ","") | I21: ขมธอ. ลายมือชื่อ/เอกสารอิเล็กทรอนิกส์ — ความครบถ้วนและการลงลายมือชื่อ OWASP Top 10:2025 — A08 Software/Data Integrity Failures NIST SSDF (SP 800-218) — PS.2 Provide a Mechanism for Verifying Integrity NIST SP 800-161r1 — SR-4(3) SLSA v1.0 — Build L2-L3 Signed provenance
A22: C-SC-REGISTRY | B22: ความปลอดภัยของ Supply Chain | C22: บังคับ | D22: ใช้ Private Registry ควบคุมที่มาของ Image และ Package | F22: registry | G22: =IF(('08_Tool_Capability'!V$76)>=1,"ผ่าน","ไม่ผ่าน") | H22: =IF('08_Tool_Capability'!V$76=0,"registry ","") | I22: OWASP Top 10:2025 — A03 Software Supply Chain Failures NIST SP 800-161r1 — SR-11
A23: C-SC-PIN | B23: ความปลอดภัยของ Supply Chain | C23: บังคับ | D23: ตรึงเวอร์ชัน Dependency และทำให้ Build ซ้ำได้ (Reproducible) | F23: version_tag, build | G23: =IF(('08_Tool_Capability'!W$76+'08_Tool_Capability'!L$76)>=2,"ผ่าน","ไม่ผ่าน") | H23: =IF('08_Tool_Capability'!W$76=0,"version_tag ","")&IF('08_Tool_Capability'!L$76=0,"build ","") | I23: OWASP Top 10:2025 — A08 Software/Data Integrity Failures NIST SSDF (SP 800-218) — PW.4 Reuse Existing Software Securely SLSA v1.0 — Dependencies Complete
A24: C-SC-IMG | B24: ความปลอดภัยของ Supply Chain | C24: บังคับเมื่อผลกระทบสูง | D24: สร้าง Container Image แบบควบคุมได้ (Rootless / Hermetic Build) | F24: image_build, build | G24: =IF(('08_Tool_Capability'!M$76+'08_Tool_Capability'!L$76)>=2,"ผ่าน","ไม่ผ่าน") | H24: =IF('08_Tool_Capability'!M$76=0,"image_build ","")&IF('08_Tool_Capability'!L$76=0,"build ","") | I24: CIS Benchmarks — Image build hardening SLSA v1.0 — Build L3 Hermetic / Isolated build
A25: C-SC-CONTAINER | B25: ความปลอดภัยของ Supply Chain | C25: บังคับ | D25: สแกนช่องโหว่ของ Container Image ทุก Layer ก่อน Deploy | F25: container_scan | G25: =IF(('08_Tool_Capability'!N$76)>=1,"ผ่าน","ไม่ผ่าน") | H25: =IF('08_Tool_Capability'!N$76=0,"container_scan ","") | I25: OWASP Top 10:2025 — A02/A03 Container image vulnerabilities CIS Benchmarks — Image scanning before deploy PCI DSS v4.0 — Req 6.3 Vulnerability management
A26: C-CRY-TLS | B26: การเข้ารหัสและการจัดการกุญแจ | C26: บังคับ | D26: ใช้ TLS 1.2 หรือ 1.3 เท่านั้น ห้าม Self-signed Certificate | F26: tls_check | G26: =IF(('08_Tool_Capability'!AJ$76)>=1,"ผ่าน","ไม่ผ่าน") | H26: =IF('08_Tool_Capability'!AJ$76=0,"tls_check ","") | I26: พ.ร.บ. ปฏิบัติราชการทางอิเล็กทรอนิกส์ 2565 — ความปลอดภัยของช่องทาง พ.ร.ฎ. วิธีการแบบปลอดภัย 2553 — การรักษาความลับของข้อมูล มาตรฐานเว็บไซต์ 2568 — Website Security Operation ประกาศ PDPC มาตรการความปลอดภัย 2565 — การเข้ารหัสข้อมูล มสพร. 11-2566 เว็บไซต์ภาครัฐ 3.0 — ความมั่นคงปลอดภัยทางเทคนิค ขมธอ. ความมั่นคงปลอดภัยสารสนเทศ — การเข้ารหัสข้อมูล OWASP Top 10:2025 — A04 Cryptographic Failures NIST PQC Migration — Protocol Migration PCI DSS v4.0 — Req 4 Protect data in transit
A27: C-CRY-KEY | B27: การเข้ารหัสและการจัดการกุญแจ | C27: บังคับ | D27: จัดการกุญแจและ Secret อย่างปลอดภัย พร้อม Key Rotation | F27: secret_mgmt | G27: =IF(('08_Tool_Capability'!AG$76)>=1,"ผ่าน","ไม่ผ่าน") | H27: =IF('08_Tool_Capability'!AG$76=0,"secret_mgmt ","") | I27: PDPA 2562 — ม.37 มาตรฐานคลาวด์ 2567 — Data Encryption ประกาศ PDPC มาตรการความปลอดภัย 2565 — การบริหารกุญแจ ขมธอ. การใช้บริการคลาวด์ — การจัดการกุญแจของผู้ใช้บริการ ขมธอ. ลายมือชื่อ/เอกสารอิเล็กทรอนิกส์ — การจัดการกุญแจ ISO/IEC 27001:2022 — A.8.24 ISO/IEC 27017 — CLD.10 OWASP Top 10:2025 — A04 Cryptographic Failures OWASP ASVS 5.0 — V6 Cryptography OWASP MASVS — MASVS-CRYPTO CSA CCM v4 / STAR — CEK
A28: C-CRY-PQC | B28: การเข้ารหัสและการจัดการกุญแจ | C28: แนะนำ | D28: ทำ Crypto Inventory (CBOM) และออกแบบให้เปลี่ยนอัลกอริทึมได้ (Crypto-Agility) | E28: เตรียมรองรับ Post-Quantum Cryptography ในอนาคต | F28: crypto_agility, tls_check | G28: =IF(('08_Tool_Capability'!AO$76+'08_Tool_Capability'!AJ$76)>=2,"ผ่าน","ไม่ผ่าน") | H28: =IF('08_Tool_Capability'!AO$76=0,"crypto_agility ","")&IF('08_Tool_Capability'!AJ$76=0,"tls_check ","") | I28: OWASP Top 10:2025 — Post-Quantum Threat & Crypto-Agility NIST PQC Migration — Crypto Discovery & Inventory CycloneDX / ECMA-424 — CBOM
A29: C-IAM-MFA | B29: การยืนยันตัวตนและสิทธิ์การเข้าถึง | C29: บังคับ | D29: บังคับ Multi-Factor Authentication สำหรับบัญชีสำคัญ | F29: iam_mfa | G29: =IF(('08_Tool_Capability'!AN$76)>=1,"ผ่าน","ไม่ผ่าน") | H29: =IF('08_Tool_Capability'!AN$76=0,"iam_mfa ","") | I29: พ.ร.ฎ. วิธีการแบบปลอดภัย 2553 — การยืนยันตัวตน มาตรฐานเว็บไซต์ 2568 — Website Security Operation ประกาศ PDPC มาตรการความปลอดภัย 2565 — การควบคุมการเข้าถึง NIST SP 800-207 — Policy Enforcement Point NIST SP 800-63B — AAL2-AAL3 CIS Controls v8.1 — Control 6 Access Control Management
A30: C-IAM-LEAST | B30: การยืนยันตัวตนและสิทธิ์การเข้าถึง | C30: บังคับ | D30: ให้สิทธิ์เท่าที่จำเป็น (Least Privilege) และตรวจสิทธิ์ทุกการเรียกใช้ | E30: แนวทาง Zero Trust: ไม่เชื่อถือเครือข่ายภายในโดยปริยาย | F30: iam_mfa, orchestration, runtime_security | G30: =IF(('08_Tool_Capability'!AN$76+'08_Tool_Capability'!AD$76+'08_Tool_Capability'!AE$76)>=3,"ผ่าน","ไม่ผ่าน") | H30: =IF('08_Tool_Capability'!AN$76=0,"iam_mfa ","")&IF('08_Tool_Capability'!AD$76=0,"orchestration ","")&IF('08_Tool_Capability'!AE$76=0,"runtime_security ","") | I30: PDPA 2562 — ม.37 มาตรฐานคลาวด์ 2567 — Access Control ขมธอ. ความมั่นคงปลอดภัยสารสนเทศ — การควบคุมการเข้าถึง ขมธอ. การใช้บริการคลาวด์ — การควบคุมการเข้าถึง ISO/IEC 27001:2022 — A.5.15, A.8.2 ISO/IEC 27017 — CLD.9.5 NIST SP 800-207 — Tenet 1-7 NIST SP 800-53r5 — AC-6 CIS Benchmarks — RBAC SOC 2 (TSC) — CC6 Logical Access CSA CCM v4 / STAR — IAM
A31: C-IAM-REMOTE | B31: การยืนยันตัวตนและสิทธิ์การเข้าถึง | C31: บังคับเมื่อผลกระทบสูง | D31: ควบคุมการเชื่อมต่อระยะไกลและสื่อบันทึกข้อมูลแบบถอดได้ | F31: iam_mfa, config_mgmt | G31: =IF(('08_Tool_Capability'!AN$76+'08_Tool_Capability'!AH$76)>=2,"ผ่าน","ไม่ผ่าน") | H31: =IF('08_Tool_Capability'!AN$76=0,"iam_mfa ","")&IF('08_Tool_Capability'!AH$76=0,"config_mgmt ","") | I31: มาตรฐานขั้นต่ำ 2566 — ระดับกลาง — Remote Connection
A32: C-LOG-90 | B32: การบันทึกและเฝ้าระวังเหตุการณ์ | C32: บังคับ | D32: เก็บ Log จราจรคอมพิวเตอร์ไม่น้อยกว่า 90 วัน และตรวจสอบย้อนหลังได้ | E32: เป็นตัวกำหนดขนาด Data Disk ของระบบ Log โดยตรง | F32: log_mgmt, audit_trail | G32: =IF(('08_Tool_Capability'!Z$76+'08_Tool_Capability'!Y$76)>=2,"ผ่าน","ไม่ผ่าน") | H32: =IF('08_Tool_Capability'!Z$76=0,"log_mgmt ","")&IF('08_Tool_Capability'!Y$76=0,"audit_trail ","") | I32: พ.ร.บ. คอมพิวเตอร์ 2550/2560 — ม.26 มาตรฐานขั้นต่ำ 2566 — Log Management
A33: C-LOG-CENTRAL | B33: การบันทึกและเฝ้าระวังเหตุการณ์ | C33: บังคับ | D33: รวบรวม Log ไว้ที่ศูนย์กลางที่แก้ไขย้อนหลังไม่ได้ | F33: log_mgmt | G33: =IF(('08_Tool_Capability'!Z$76)>=1,"ผ่าน","ไม่ผ่าน") | H33: =IF('08_Tool_Capability'!Z$76=0,"log_mgmt ","") | I33: พ.ร.บ. คอมพิวเตอร์ 2550/2560 — ม.26 พ.ร.ฎ. วิธีการแบบปลอดภัย 2553 — การบันทึกเหตุการณ์ มาตรฐานคลาวด์ 2567 — Operation Security มาตรฐานเว็บไซต์ 2568 — Logging & Monitoring ประกาศ PDPC มาตรการความปลอดภัย 2565 — การบันทึกการเข้าถึง ขมธอ. ความมั่นคงปลอดภัยสารสนเทศ — การบันทึกเหตุการณ์ ISO/IEC 27001:2022 — A.8.15 ISO/IEC 27002:2022 — 8.15 ISO/IEC 27017 — CLD.12.4 OWASP Top 10:2025 — A09 Logging & Alerting Failures OWASP ASVS 5.0 — V7 Error Handling & Logging CIS Controls v8.1 — Control 8 Audit Log Management PCI DSS v4.0 — Req 10 Log and monitor CSA CCM v4 / STAR — LOG
A34: C-LOG-SIEM | B34: การบันทึกและเฝ้าระวังเหตุการณ์ | C34: บังคับ | D34: มีระบบเฝ้าระวังและแจ้งเตือนเหตุการณ์ด้านความปลอดภัย (SIEM / Alerting) | F34: siem_alert, monitoring | G34: =IF(('08_Tool_Capability'!AA$76+'08_Tool_Capability'!AF$76)>=2,"ผ่าน","ไม่ผ่าน") | H34: =IF('08_Tool_Capability'!AA$76=0,"siem_alert ","")&IF('08_Tool_Capability'!AF$76=0,"monitoring ","") | I34: พ.ร.บ. ไซเบอร์ 2562 — ม.56 มาตรฐานเว็บไซต์ 2568 — Logging & Monitoring กรอบมาตรฐานไซเบอร์ 2564 — การเฝ้าระวัง ประกาศ PDPC แจ้งเหตุละเมิด 2565 — การตรวจพบเหตุ OWASP Top 10:2025 — A09 Logging & Alerting Failures NIST SP 800-207 — Continuous Monitoring NIST CSF 2.0 — DE.AE SOC 2 (TSC) — CC7.2 Monitoring
A35: C-LOG-AUDIT | B35: การบันทึกและเฝ้าระวังเหตุการณ์ | C35: บังคับ | D35: บันทึก Audit Trail ว่าใครทำอะไรเมื่อไหร่ และเก็บตามอายุที่กฎหมายกำหนด | E35: ภาครัฐมักต้องเก็บหลักฐานการอนุมัติและการเปลี่ยนแปลงระบบ 5-7 ปี | F35: audit_trail | G35: =IF(('08_Tool_Capability'!Y$76)>=1,"ผ่าน","ไม่ผ่าน") | H35: =IF('08_Tool_Capability'!Y$76=0,"audit_trail ","") | I35: พ.ร.บ. คอมพิวเตอร์ 2550/2560 — ม.26 พ.ร.บ. ไซเบอร์ 2562 — ม.54 PDPA 2562 — ม.39 (RoPA) พ.ร.บ. ปฏิบัติราชการทางอิเล็กทรอนิกส์ 2565 — การเก็บหลักฐานทางอิเล็กทรอนิกส์ มาตรฐานขั้นต่ำ 2566 — Log Management มาตรฐานข้อมูลเปิดภาครัฐ — ธรรมาภิบาลข้อมูล ขมธอ. ลายมือชื่อ/เอกสารอิเล็กทรอนิกส์ — การเก็บหลักฐาน ITA (ป.ป.ช.) — การเปิดเผยข้อมูลและตรวจสอบได้ ISO/IEC 27001:2022 — A.8.15 ISO/IEC 27018 — A.12 ISO/IEC 27701 — A.7.2 ISO/IEC 42001:2023 — A.5 Records NIST SP 800-53r5 — AU-2, AU-12 SOC 2 (TSC) — CC7 System Operations
A36: C-LOG-NOTIFY | B36: การบันทึกและเฝ้าระวังเหตุการณ์ | C36: บังคับ | D36: แจ้งเหตุและยกระดับเหตุการณ์ได้ทันกรอบเวลาที่กฎหมายกำหนด | E36: PDPA กำหนด 72 ชั่วโมงต่อ PDPC และกฎหมายไซเบอร์กำหนดให้แจ้ง สกมช. โดยเร็ว | F36: notify, siem_alert | G36: =IF(('08_Tool_Capability'!AQ$76+'08_Tool_Capability'!AA$76)>=2,"ผ่าน","ไม่ผ่าน") | H36: =IF('08_Tool_Capability'!AQ$76=0,"notify ","")&IF('08_Tool_Capability'!AA$76=0,"siem_alert ","") | I36: พ.ร.บ. ไซเบอร์ 2562 — ม.57 ประกาศ PDPC แจ้งเหตุละเมิด 2565 — ช่องทางการแจ้งเหตุ NIST CSF 2.0 — RS.CO
A37: C-OPS-HARDEN | B37: การปฏิบัติการและโครงสร้างพื้นฐาน | C37: บังคับ | D37: มี Hardening Baseline และตรวจการตั้งค่าที่ผิดพลาดอย่างสม่ำเสมอ | F37: config_mgmt | G37: =IF(('08_Tool_Capability'!AH$76)>=1,"ผ่าน","ไม่ผ่าน") | H37: =IF('08_Tool_Capability'!AH$76=0,"config_mgmt ","") | I37: มาตรฐานขั้นต่ำ 2566 — การควบคุมเชิงเทคนิค กรอบมาตรฐานไซเบอร์ 2564 — การควบคุมเชิงเทคนิค ขมธอ. ความมั่นคงปลอดภัยสารสนเทศ — การตั้งค่าอย่างปลอดภัย ISO/IEC 27001:2022 — A.8.9 ISO/IEC 27002:2022 — 8.9 OWASP Top 10:2025 — A02 Security Misconfiguration NIST CSF 2.0 — PR.PS NIST SP 800-53r5 — CM-6 CIS Controls v8.1 — Control 4 Secure Configuration CIS Benchmarks — Benchmark items
A38: C-OPS-IAC | B38: การปฏิบัติการและโครงสร้างพื้นฐาน | C38: บังคับ | D38: ตรวจไฟล์ Infrastructure as Code และบังคับ Policy-as-Code ก่อนใช้งาน | F38: iac_scan | G38: =IF(('08_Tool_Capability'!O$76)>=1,"ผ่าน","ไม่ผ่าน") | H38: =IF('08_Tool_Capability'!O$76=0,"iac_scan ","") | I38: มาตรฐานคลาวด์ 2567 — Cloud Infrastructure Security OWASP Top 10:2025 — A02 Security Misconfiguration CIS Benchmarks — Policy enforcement
A39: C-OPS-CSPM | B39: การปฏิบัติการและโครงสร้างพื้นฐาน | C39: บังคับเมื่อผลกระทบสูง | D39: ตรวจสถานะความปลอดภัยของโครงสร้างพื้นฐาน / คลาวด์เป็นระยะ | F39: cspm | G39: =IF(('08_Tool_Capability'!AL$76)>=1,"ผ่าน","ไม่ผ่าน") | H39: =IF('08_Tool_Capability'!AL$76=0,"cspm ","") | I39: มาตรฐานคลาวด์ 2567 — Cloud Infrastructure Security ขมธอ. การใช้บริการคลาวด์ — การควบคุมผู้ให้บริการ ISO/IEC 27017 — CLD.9 CSA CCM v4 / STAR — IVS / DCS
A40: C-OPS-RUNTIME | B40: การปฏิบัติการและโครงสร้างพื้นฐาน | C40: บังคับเมื่อผลกระทบสูง | D40: เฝ้าระวังพฤติกรรมผิดปกติของ Container ตอนรันจริง (Runtime Security) | F40: runtime_security | G40: =IF(('08_Tool_Capability'!AE$76)>=1,"ผ่าน","ไม่ผ่าน") | H40: =IF('08_Tool_Capability'!AE$76=0,"runtime_security ","") | I40: NIST SP 800-207 — Continuous Diagnostics CIS Benchmarks — Runtime policies
A41: C-OPS-MONITOR | B41: การปฏิบัติการและโครงสร้างพื้นฐาน | C41: บังคับ | D41: มีระบบ Observability เก็บ Metrics / Logs / Traces และตั้ง Alert | F41: monitoring | G41: =IF(('08_Tool_Capability'!AF$76)>=1,"ผ่าน","ไม่ผ่าน") | H41: =IF('08_Tool_Capability'!AF$76=0,"monitoring ","") | I41: มาตรฐานคลาวด์ 2567 — Continuous Monitoring NIST CSF 2.0 — DE.CM
A42: C-OPS-PERF | B42: การปฏิบัติการและโครงสร้างพื้นฐาน | C42: บังคับเมื่อผลกระทบสูง | D42: ทดสอบประสิทธิภาพเทียบ SLA ก่อน Go-Live | F42: perf_test | G42: =IF(('08_Tool_Capability'!U$76)>=1,"ผ่าน","ไม่ผ่าน") | H42: =IF('08_Tool_Capability'!U$76=0,"perf_test ","") | I42: ISO/IEC 27001:2022 — A.8.6 ISO/IEC 25010:2023 — Performance Efficiency
A43: C-OPS-DEPLOY | B43: การปฏิบัติการและโครงสร้างพื้นฐาน | C43: บังคับ | D43: มีกลยุทธ์การ Deploy ที่ย้อนกลับได้ (Rolling / Blue-Green / Canary) | F43: deploy_strategy, orchestration | G43: =IF(('08_Tool_Capability'!AC$76+'08_Tool_Capability'!AD$76)>=2,"ผ่าน","ไม่ผ่าน") | H43: =IF('08_Tool_Capability'!AC$76=0,"deploy_strategy ","")&IF('08_Tool_Capability'!AD$76=0,"orchestration ","") | I43: พ.ร.บ. ไซเบอร์ 2562 — ม.62 การรักษาความต่อเนื่องของบริการ CIS Controls v8.1 — Control 4.7 Change control SOC 2 (TSC) — CC8.1 Change deployment & rollback
A44: C-OPS-BACKUP | B44: การปฏิบัติการและโครงสร้างพื้นฐาน | C44: บังคับ | D44: สำรองข้อมูลและ ทดสอบการกู้คืนจริง ไม่ใช่แค่สำรองผ่าน | F44: backup_dr | G44: =IF(('08_Tool_Capability'!AM$76)>=1,"ผ่าน","ไม่ผ่าน") | H44: =IF('08_Tool_Capability'!AM$76=0,"backup_dr ","") | I44: พ.ร.ฎ. วิธีการแบบปลอดภัย 2553 — ความพร้อมใช้ของระบบ มาตรฐานขั้นต่ำ 2566 — ระดับสูง — Resilience & Recovery มาตรฐานเว็บไซต์ 2568 — Website Security Governance มสพร. 11-2566 เว็บไซต์ภาครัฐ 3.0 — แผนสำรองข้อมูล ขมธอ. การใช้บริการคลาวด์ — การสำรองและย้ายข้อมูล ISO/IEC 27001:2022 — A.8.13 ISO 22301:2019 — 8.4.4 NIST SP 800-53r5 — CP-9 CIS Controls v8.1 — Control 11 Data Recovery
A45: C-OPS-BCP | B45: การปฏิบัติการและโครงสร้างพื้นฐาน | C45: บังคับเมื่อผลกระทบสูง | D45: มีแผนความต่อเนื่องทางธุรกิจและการกู้คืนระบบ พร้อมซ้อมแผนเป็นประจำ | F45: backup_dr, audit_trail | G45: =IF(('08_Tool_Capability'!AM$76+'08_Tool_Capability'!Y$76)>=2,"ผ่าน","ไม่ผ่าน") | H45: =IF('08_Tool_Capability'!AM$76=0,"backup_dr ","")&IF('08_Tool_Capability'!Y$76=0,"audit_trail ","") | I45: พ.ร.บ. ไซเบอร์ 2562 — ม.3, ม.62 มาตรฐานขั้นต่ำ 2566 — ระดับสูง — Resilience & Recovery กรอบมาตรฐานไซเบอร์ 2564 — การรับมือและกู้คืน ISO 22301:2019 — 8.4 Business continuity plans NIST CSF 2.0 — RC.RP SOC 2 (TSC) — A1.2 Availability
A46: C-PRV-MEASURE | B46: การคุ้มครองข้อมูลส่วนบุคคล | C46: บังคับ | D46: มีมาตรการรักษาความมั่นคงปลอดภัยที่เหมาะสมกับข้อมูลส่วนบุคคล | E46: ครอบคลุมการเข้ารหัส การควบคุมสิทธิ์ และการบันทึกเหตุการณ์ | F46: secret_mgmt, iam_mfa, log_mgmt, tls_check | G46: =IF(('08_Tool_Capability'!AG$76+'08_Tool_Capability'!AN$76+'08_Tool_Capability'!Z$76+'08_Tool_Capability'!AJ$76)>=4,"ผ่าน","ไม่ผ่าน") | H46: =IF('08_Tool_Capability'!AG$76=0,"secret_mgmt ","")&IF('08_Tool_Capability'!AN$76=0,"iam_mfa ","")&IF('08_Tool_Capability'!Z$76=0,"log_mgmt ","")&IF('08_Tool_Capability'!AJ$76=0,"tls_check ","") | I46: PDPA 2562 — ม.37 ประกาศ PDPC มาตรการความปลอดภัย 2565 — มาตรการเชิงเทคนิค มสพร. 11-2566 เว็บไซต์ภาครัฐ 3.0 — การคุ้มครองข้อมูลส่วนบุคคล ISO/IEC 27018 — A.11 ISO/IEC 27701 — 6.x ISO/IEC 29100 — Information security
A47: C-PRV-BREACH | B47: การคุ้มครองข้อมูลส่วนบุคคล | C47: บังคับ | D47: ตรวจจับเหตุละเมิดข้อมูลส่วนบุคคลได้เร็วพอที่จะแจ้งภายในกรอบเวลา | F47: siem_alert, log_mgmt, notify | G47: =IF(('08_Tool_Capability'!AA$76+'08_Tool_Capability'!Z$76+'08_Tool_Capability'!AQ$76)>=3,"ผ่าน","ไม่ผ่าน") | H47: =IF('08_Tool_Capability'!AA$76=0,"siem_alert ","")&IF('08_Tool_Capability'!Z$76=0,"log_mgmt ","")&IF('08_Tool_Capability'!AQ$76=0,"notify ","") | I47: PDPA 2562 — ม.37(4) ประกาศ PDPC แจ้งเหตุละเมิด 2565 — การแจ้งภายใน 72 ชั่วโมง ISO/IEC 27701 — A.7.3
A48: C-PRV-MINIMIZE | B48: การคุ้มครองข้อมูลส่วนบุคคล | C48: บังคับ | D48: ไม่ให้ข้อมูลส่วนบุคคลรั่วไหลไปกับ Log, Artifact หรือชุดข้อมูลทดสอบ | F48: secret_scan, log_mgmt | G48: =IF(('08_Tool_Capability'!H$76+'08_Tool_Capability'!Z$76)>=2,"ผ่าน","ไม่ผ่าน") | H48: =IF('08_Tool_Capability'!H$76=0,"secret_scan ","")&IF('08_Tool_Capability'!Z$76=0,"log_mgmt ","") | I48: PDPA 2562 — ม.37 ISO/IEC 27018 — A.10 ISO/IEC 27701 — A.7.4 ISO/IEC 29100 — Data minimization
A49: C-WEB-A11Y | B49: เว็บไซต์และการเข้าถึงที่เท่าเทียม | C49: บังคับ | D49: เว็บไซต์ต้องผ่าน WCAG 2.1 หรือ 2.2 ระดับ AA | E49: เป็นข้อที่โครงการเว็บภาครัฐตกบ่อยที่สุด เพราะไม่มีการทดสอบใน Pipeline | F49: accessibility | G49: =IF(('08_Tool_Capability'!AK$76)>=1,"ผ่าน","ไม่ผ่าน") | H49: =IF('08_Tool_Capability'!AK$76=0,"accessibility ","") | I49: มสพร. 11-2566 เว็บไซต์ภาครัฐ 3.0 — Web Accessibility (WCAG AA) WCAG 2.2 AA — Level AA success criteria
A50: C-WEB-SELF | B50: เว็บไซต์และการเข้าถึงที่เท่าเทียม | C50: บังคับ | D50: ประเมินตนเองอย่างน้อยปีละ 1 ครั้ง และรายงานผลต่อผู้บริหาร | F50: audit_trail, vapt | G50: =IF(('08_Tool_Capability'!Y$76+'08_Tool_Capability'!AP$76)>=2,"ผ่าน","ไม่ผ่าน") | H50: =IF('08_Tool_Capability'!Y$76=0,"audit_trail ","")&IF('08_Tool_Capability'!AP$76=0,"vapt ","") | I50: มาตรฐานเว็บไซต์ 2568 — Self-Assessment รายปี ITA (ป.ป.ช.) — การประเมินตนเองรายปี
A51: C-AI-GOV | B51: การกำกับดูแลโมเดล AI | C51: บังคับเมื่อผลกระทบสูง | D51: กำกับดูแลเวอร์ชันโมเดล ที่มาของข้อมูล และเกณฑ์ผ่านก่อนนำโมเดลขึ้นใช้ | F51: version_tag, registry, quality_gate, artifact_sign | G51: =IF(('08_Tool_Capability'!W$76+'08_Tool_Capability'!V$76+'08_Tool_Capability'!AB$76+'08_Tool_Capability'!P$76)>=4,"ผ่าน","ไม่ผ่าน") | H51: =IF('08_Tool_Capability'!W$76=0,"version_tag ","")&IF('08_Tool_Capability'!V$76=0,"registry ","")&IF('08_Tool_Capability'!AB$76=0,"quality_gate ","")&IF('08_Tool_Capability'!P$76=0,"artifact_sign ","") | I51: ISO/IEC 42001:2023 — A.6 AI system life cycle
A52: C-AI-DRIFT | B52: การกำกับดูแลโมเดล AI | C52: บังคับเมื่อผลกระทบสูง | D52: เฝ้าระวัง Model Drift และ Bias หลังนำขึ้นใช้งาน | F52: monitoring, runtime_security | G52: =IF(('08_Tool_Capability'!AF$76+'08_Tool_Capability'!AE$76)>=2,"ผ่าน","ไม่ผ่าน") | H52: =IF('08_Tool_Capability'!AF$76=0,"monitoring ","")&IF('08_Tool_Capability'!AE$76=0,"runtime_security ","") | I52: ISO/IEC 42001:2023 — A.9 Performance monitoring
D54: คะแนน Compliance (นับทุกมาตรการในระบบ) | G54: =COUNTIF(G3:G52,"ผ่าน")/COUNTA(G3:G52)
D55: จำนวนมาตรการที่ไม่ผ่าน | G55: =COUNTIF(G3:G52,"ไม่ผ่าน")
A57: หมายเหตุ: คะแนนในชีทนี้นับทุกมาตรการที่มีในระบบ ไม่ได้กรองตามมาตรฐานที่โครงการเลือก — ถ้าต้องการคะแนนตามชุดมาตรฐานที่เลือกจริง ให้ใช้โปรแกรมเว็บ (แท็บ 3)

Sheet 08_Tool_Capability
A1: 08 — เมทริกซ์เครื่องมือ x Capability | C1: 1 = เครื่องมือนี้ตอบ capability นั้นได้ | ใช้เป็นฐานของการตรวจ compliance ในชีท 07
A2: tool_id | B2: เครื่องมือ | C2: git_scm | D2: webhook | E2: branch_protection | F2: pipeline | G2: sast | H2: secret_scan | I2: sca | J2: license | K2: code_quality | L2: build | M2: image_build | N2: container_scan | O2: iac_scan | P2: artifact_sign | Q2: unit_test | R2: integration_test | S2: dast | T2: api_security | U2: perf_test | V2: registry | W2: version_tag | X2: sbom | Y2: audit_trail | Z2: log_mgmt | AA2: siem_alert | AB2: quality_gate | AC2: deploy_strategy | AD2: orchestration | AE2: runtime_security | AF2: monitoring | AG2: secret_mgmt | AH2: config_mgmt | AI2: waf | AJ2: tls_check | AK2: accessibility | AL2: cspm | AM2: backup_dr | AN2: iam_mfa | AO2: crypto_agility | AP2: vapt | AQ2: notify | AS2: เลือกใน VM ใดก็ได้
A3: gitlab-ce | B3: GitLab Community Edition (Self-hosted Git) | C3: 1 | D3: 1 | E3: 1 | F3: 1 | G3: 0 | H3: 0 | I3: 0 | J3: 0 | K3: 0 | L3: 0 | M3: 0 | N3: 0 | O3: 0 | P3: 0 | Q3: 0 | R3: 0 | S3: 0 | T3: 0 | U3: 0 | V3: 0 | W3: 0 | X3: 0 | Y3: 1 | Z3: 0 | AA3: 0 | AB3: 0 | AC3: 0 | AD3: 0 | AE3: 0 | AF3: 0 | AG3: 0 | AH3: 0 | AI3: 0 | AJ3: 0 | AK3: 0 | AL3: 0 | AM3: 0 | AN3: 0 | AO3: 0 | AP3: 0 | AQ3: 0 | AS3: =IF(SUM('03_Colocation_Calc'!$T$3:$AC$3)>0,1,0)
A4: gitea | B4: Gitea / Forgejo (Lightweight Git) | C4: 1 | D4: 1 | E4: 1 | F4: 0 | G4: 0 | H4: 0 | I4: 0 | J4: 0 | K4: 0 | L4: 0 | M4: 0 | N4: 0 | O4: 0 | P4: 0 | Q4: 0 | R4: 0 | S4: 0 | T4: 0 | U4: 0 | V4: 0 | W4: 0 | X4: 0 | Y4: 1 | Z4: 0 | AA4: 0 | AB4: 0 | AC4: 0 | AD4: 0 | AE4: 0 | AF4: 0 | AG4: 0 | AH4: 0 | AI4: 0 | AJ4: 0 | AK4: 0 | AL4: 0 | AM4: 0 | AN4: 0 | AO4: 0 | AP4: 0 | AQ4: 0 | AS4: =IF(SUM('03_Colocation_Calc'!$T$4:$AC$4)>0,1,0)
A5: github-actions-runner | B5: GitHub Actions Self-hosted Runner | C5: 0 | D5: 1 | E5: 0 | F5: 1 | G5: 0 | H5: 0 | I5: 0 | J5: 0 | K5: 0 | L5: 1 | M5: 0 | N5: 0 | O5: 0 | P5: 0 | Q5: 0 | R5: 0 | S5: 0 | T5: 0 | U5: 0 | V5: 0 | W5: 0 | X5: 0 | Y5: 0 | Z5: 0 | AA5: 0 | AB5: 0 | AC5: 0 | AD5: 0 | AE5: 0 | AF5: 0 | AG5: 0 | AH5: 0 | AI5: 0 | AJ5: 0 | AK5: 0 | AL5: 0 | AM5: 0 | AN5: 0 | AO5: 0 | AP5: 0 | AQ5: 0 | AS5: =IF(SUM('03_Colocation_Calc'!$T$5:$AC$5)>0,1,0)
A6: jenkins-master | B6: Jenkins Master / Controller | C6: 0 | D6: 1 | E6: 0 | F6: 1 | G6: 0 | H6: 0 | I6: 0 | J6: 0 | K6: 0 | L6: 0 | M6: 0 | N6: 0 | O6: 0 | P6: 0 | Q6: 0 | R6: 0 | S6: 0 | T6: 0 | U6: 0 | V6: 0 | W6: 0 | X6: 0 | Y6: 1 | Z6: 0 | AA6: 0 | AB6: 1 | AC6: 0 | AD6: 0 | AE6: 0 | AF6: 0 | AG6: 0 | AH6: 0 | AI6: 0 | AJ6: 0 | AK6: 0 | AL6: 0 | AM6: 0 | AN6: 0 | AO6: 0 | AP6: 0 | AQ6: 1 | AS6: =IF(SUM('03_Colocation_Calc'!$T$6:$AC$6)>0,1,0)
A7: jenkins-agent | B7: Jenkins Agent / Build Executor (ต่อ 1 Executor) | C7: 0 | D7: 0 | E7: 0 | F7: 1 | G7: 0 | H7: 0 | I7: 0 | J7: 0 | K7: 0 | L7: 1 | M7: 0 | N7: 0 | O7: 0 | P7: 0 | Q7: 1 | R7: 0 | S7: 0 | T7: 0 | U7: 0 | V7: 0 | W7: 0 | X7: 0 | Y7: 0 | Z7: 0 | AA7: 0 | AB7: 0 | AC7: 0 | AD7: 0 | AE7: 0 | AF7: 0 | AG7: 0 | AH7: 0 | AI7: 0 | AJ7: 0 | AK7: 0 | AL7: 0 | AM7: 0 | AN7: 0 | AO7: 0 | AP7: 0 | AQ7: 0 | AS7: =IF(SUM('03_Colocation_Calc'!$T$7:$AC$7)>0,1,0)
A8: argo-workflows | B8: Argo Workflows (CNCF Graduated) | C8: 0 | D8: 1 | E8: 0 | F8: 1 | G8: 0 | H8: 0 | I8: 0 | J8: 0 | K8: 0 | L8: 0 | M8: 0 | N8: 0 | O8: 0 | P8: 0 | Q8: 0 | R8: 0 | S8: 0 | T8: 0 | U8: 0 | V8: 0 | W8: 0 | X8: 0 | Y8: 1 | Z8: 0 | AA8: 0 | AB8: 0 | AC8: 0 | AD8: 0 | AE8: 0 | AF8: 0 | AG8: 0 | AH8: 0 | AI8: 0 | AJ8: 0 | AK8: 0 | AL8: 0 | AM8: 0 | AN8: 0 | AO8: 0 | AP8: 0 | AQ8: 0 | AS8: =IF(SUM('03_Colocation_Calc'!$T$8:$AC$8)>0,1,0)
A9: opa-conftest | B9: Open Policy Agent / Conftest (Policy-as-Code Gate) | C9: 0 | D9: 0 | E9: 1 | F9: 0 | G9: 0 | H9: 0 | I9: 0 | J9: 0 | K9: 0 | L9: 0 | M9: 0 | N9: 0 | O9: 1 | P9: 0 | Q9: 0 | R9: 0 | S9: 0 | T9: 0 | U9: 0 | V9: 0 | W9: 0 | X9: 0 | Y9: 0 | Z9: 0 | AA9: 0 | AB9: 1 | AC9: 0 | AD9: 0 | AE9: 0 | AF9: 0 | AG9: 0 | AH9: 0 | AI9: 0 | AJ9: 0 | AK9: 0 | AL9: 0 | AM9: 0 | AN9: 0 | AO9: 0 | AP9: 0 | AQ9: 0 | AS9: =IF(SUM('03_Colocation_Calc'!$T$9:$AC$9)>0,1,0)
A10: nginx-gateway | B10: Nginx (Reverse Proxy / Webhook Relay) | C10: 0 | D10: 1 | E10: 0 | F10: 0 | G10: 0 | H10: 0 | I10: 0 | J10: 0 | K10: 0 | L10: 0 | M10: 0 | N10: 0 | O10: 0 | P10: 0 | Q10: 0 | R10: 0 | S10: 0 | T10: 0 | U10: 0 | V10: 0 | W10: 0 | X10: 0 | Y10: 0 | Z10: 0 | AA10: 0 | AB10: 0 | AC10: 0 | AD10: 0 | AE10: 0 | AF10: 0 | AG10: 0 | AH10: 0 | AI10: 0 | AJ10: 1 | AK10: 0 | AL10: 0 | AM10: 0 | AN10: 0 | AO10: 0 | AP10: 0 | AQ10: 0 | AS10: =IF(SUM('03_Colocation_Calc'!$T$10:$AC$10)>0,1,0)
A11: sonarqube | B11: SonarQube Community Edition | C11: 0 | D11: 0 | E11: 0 | F11: 0 | G11: 1 | H11: 0 | I11: 0 | J11: 0 | K11: 1 | L11: 0 | M11: 0 | N11: 0 | O11: 0 | P11: 0 | Q11: 0 | R11: 0 | S11: 0 | T11: 0 | U11: 0 | V11: 0 | W11: 0 | X11: 0 | Y11: 0 | Z11: 0 | AA11: 0 | AB11: 1 | AC11: 0 | AD11: 0 | AE11: 0 | AF11: 0 | AG11: 0 | AH11: 0 | AI11: 0 | AJ11: 0 | AK11: 0 | AL11: 0 | AM11: 0 | AN11: 0 | AO11: 0 | AP11: 0 | AQ11: 0 | AS11: =IF(SUM('03_Colocation_Calc'!$T$11:$AC$11)>0,1,0)
A12: postgresql-tools | B12: PostgreSQL (ฐานข้อมูลของเครื่องมือ CI/CD) | C12: 0 | D12: 0 | E12: 0 | F12: 0 | G12: 0 | H12: 0 | I12: 0 | J12: 0 | K12: 0 | L12: 0 | M12: 0 | N12: 0 | O12: 0 | P12: 0 | Q12: 0 | R12: 0 | S12: 0 | T12: 0 | U12: 0 | V12: 0 | W12: 0 | X12: 0 | Y12: 1 | Z12: 0 | AA12: 0 | AB12: 0 | AC12: 0 | AD12: 0 | AE12: 0 | AF12: 0 | AG12: 0 | AH12: 0 | AI12: 0 | AJ12: 0 | AK12: 0 | AL12: 0 | AM12: 0 | AN12: 0 | AO12: 0 | AP12: 0 | AQ12: 0 | AS12: =IF(SUM('03_Colocation_Calc'!$T$12:$AC$12)>0,1,0)
A13: semgrep | B13: Semgrep (SAST แบบ Rule-based) | C13: 0 | D13: 0 | E13: 0 | F13: 0 | G13: 1 | H13: 0 | I13: 0 | J13: 0 | K13: 0 | L13: 0 | M13: 0 | N13: 0 | O13: 0 | P13: 0 | Q13: 0 | R13: 0 | S13: 0 | T13: 0 | U13: 0 | V13: 0 | W13: 0 | X13: 0 | Y13: 0 | Z13: 0 | AA13: 0 | AB13: 0 | AC13: 0 | AD13: 0 | AE13: 0 | AF13: 0 | AG13: 0 | AH13: 0 | AI13: 0 | AJ13: 0 | AK13: 0 | AL13: 0 | AM13: 0 | AN13: 0 | AO13: 0 | AP13: 0 | AQ13: 0 | AS13: =IF(SUM('03_Colocation_Calc'!$T$13:$AC$13)>0,1,0)
A14: gitleaks | B14: GitLeaks / TruffleHog (Secret Scanning) | C14: 0 | D14: 0 | E14: 0 | F14: 0 | G14: 0 | H14: 1 | I14: 0 | J14: 0 | K14: 0 | L14: 0 | M14: 0 | N14: 0 | O14: 0 | P14: 0 | Q14: 0 | R14: 0 | S14: 0 | T14: 0 | U14: 0 | V14: 0 | W14: 0 | X14: 0 | Y14: 0 | Z14: 0 | AA14: 0 | AB14: 0 | AC14: 0 | AD14: 0 | AE14: 0 | AF14: 0 | AG14: 0 | AH14: 0 | AI14: 0 | AJ14: 0 | AK14: 0 | AL14: 0 | AM14: 0 | AN14: 0 | AO14: 0 | AP14: 0 | AQ14: 0 | AS14: =IF(SUM('03_Colocation_Calc'!$T$14:$AC$14)>0,1,0)
A15: dependency-check | B15: OWASP Dependency-Check (SCA) | C15: 0 | D15: 0 | E15: 0 | F15: 0 | G15: 0 | H15: 0 | I15: 1 | J15: 0 | K15: 0 | L15: 0 | M15: 0 | N15: 0 | O15: 0 | P15: 0 | Q15: 0 | R15: 0 | S15: 0 | T15: 0 | U15: 0 | V15: 0 | W15: 0 | X15: 1 | Y15: 0 | Z15: 0 | AA15: 0 | AB15: 0 | AC15: 0 | AD15: 0 | AE15: 0 | AF15: 0 | AG15: 0 | AH15: 0 | AI15: 0 | AJ15: 0 | AK15: 0 | AL15: 0 | AM15: 0 | AN15: 0 | AO15: 0 | AP15: 0 | AQ15: 0 | AS15: =IF(SUM('03_Colocation_Calc'!$T$15:$AC$15)>0,1,0)
A16: trivy | B16: Trivy (SCA + Container + IaC + Secret ในตัวเดียว) | C16: 0 | D16: 0 | E16: 0 | F16: 0 | G16: 0 | H16: 1 | I16: 1 | J16: 0 | K16: 0 | L16: 0 | M16: 0 | N16: 1 | O16: 1 | P16: 0 | Q16: 0 | R16: 0 | S16: 0 | T16: 0 | U16: 0 | V16: 0 | W16: 0 | X16: 1 | Y16: 0 | Z16: 0 | AA16: 0 | AB16: 0 | AC16: 0 | AD16: 0 | AE16: 0 | AF16: 0 | AG16: 0 | AH16: 0 | AI16: 0 | AJ16: 0 | AK16: 0 | AL16: 0 | AM16: 0 | AN16: 0 | AO16: 0 | AP16: 0 | AQ16: 0 | AS16: =IF(SUM('03_Colocation_Calc'!$T$16:$AC$16)>0,1,0)
A17: fossology | B17: FOSSology / ScanCode (License Compliance) | C17: 0 | D17: 0 | E17: 0 | F17: 0 | G17: 0 | H17: 0 | I17: 0 | J17: 1 | K17: 0 | L17: 0 | M17: 0 | N17: 0 | O17: 0 | P17: 0 | Q17: 0 | R17: 0 | S17: 0 | T17: 0 | U17: 0 | V17: 0 | W17: 0 | X17: 0 | Y17: 0 | Z17: 0 | AA17: 0 | AB17: 0 | AC17: 0 | AD17: 0 | AE17: 0 | AF17: 0 | AG17: 0 | AH17: 0 | AI17: 0 | AJ17: 0 | AK17: 0 | AL17: 0 | AM17: 0 | AN17: 0 | AO17: 0 | AP17: 0 | AQ17: 0 | AS17: =IF(SUM('03_Colocation_Calc'!$T$17:$AC$17)>0,1,0)
A18: linters | B18: Linters (ESLint / Pylint / golangci-lint / RuboCop) | C18: 0 | D18: 0 | E18: 0 | F18: 0 | G18: 0 | H18: 0 | I18: 0 | J18: 0 | K18: 1 | L18: 0 | M18: 0 | N18: 0 | O18: 0 | P18: 0 | Q18: 0 | R18: 0 | S18: 0 | T18: 0 | U18: 0 | V18: 0 | W18: 0 | X18: 0 | Y18: 0 | Z18: 0 | AA18: 0 | AB18: 0 | AC18: 0 | AD18: 0 | AE18: 0 | AF18: 0 | AG18: 0 | AH18: 0 | AI18: 0 | AJ18: 0 | AK18: 0 | AL18: 0 | AM18: 0 | AN18: 0 | AO18: 0 | AP18: 0 | AQ18: 0 | AS18: =IF(SUM('03_Colocation_Calc'!$T$18:$AC$18)>0,1,0)
A19: maven-gradle | B19: Maven / Gradle / npm / pip (Build & Compilation) | C19: 0 | D19: 0 | E19: 0 | F19: 0 | G19: 0 | H19: 0 | I19: 0 | J19: 0 | K19: 0 | L19: 1 | M19: 0 | N19: 0 | O19: 0 | P19: 0 | Q19: 0 | R19: 0 | S19: 0 | T19: 0 | U19: 0 | V19: 0 | W19: 0 | X19: 0 | Y19: 0 | Z19: 0 | AA19: 0 | AB19: 0 | AC19: 0 | AD19: 0 | AE19: 0 | AF19: 0 | AG19: 0 | AH19: 0 | AI19: 0 | AJ19: 0 | AK19: 0 | AL19: 0 | AM19: 0 | AN19: 0 | AO19: 0 | AP19: 0 | AQ19: 0 | AS19: =IF(SUM('03_Colocation_Calc'!$T$19:$AC$19)>0,1,0)
A20: docker-buildkit | B20: Docker Engine / BuildKit (Container Image Builder) | C20: 0 | D20: 0 | E20: 0 | F20: 0 | G20: 0 | H20: 0 | I20: 0 | J20: 0 | K20: 0 | L20: 1 | M20: 1 | N20: 0 | O20: 0 | P20: 0 | Q20: 0 | R20: 0 | S20: 0 | T20: 0 | U20: 0 | V20: 0 | W20: 0 | X20: 0 | Y20: 0 | Z20: 0 | AA20: 0 | AB20: 0 | AC20: 0 | AD20: 0 | AE20: 0 | AF20: 0 | AG20: 0 | AH20: 0 | AI20: 0 | AJ20: 0 | AK20: 0 | AL20: 0 | AM20: 0 | AN20: 0 | AO20: 0 | AP20: 0 | AQ20: 0 | AS20: =IF(SUM('03_Colocation_Calc'!$T$20:$AC$20)>0,1,0)
A21: checkov | B21: Checkov / tfsec / KubeLinter (IaC Validation) | C21: 0 | D21: 0 | E21: 0 | F21: 0 | G21: 0 | H21: 0 | I21: 0 | J21: 0 | K21: 0 | L21: 0 | M21: 0 | N21: 0 | O21: 1 | P21: 0 | Q21: 0 | R21: 0 | S21: 0 | T21: 0 | U21: 0 | V21: 0 | W21: 0 | X21: 0 | Y21: 0 | Z21: 0 | AA21: 0 | AB21: 0 | AC21: 0 | AD21: 0 | AE21: 0 | AF21: 0 | AG21: 0 | AH21: 0 | AI21: 0 | AJ21: 0 | AK21: 0 | AL21: 0 | AM21: 0 | AN21: 0 | AO21: 0 | AP21: 0 | AQ21: 0 | AS21: =IF(SUM('03_Colocation_Calc'!$T$21:$AC$21)>0,1,0)
A22: cosign | B22: Sigstore Cosign / Notary v2 (Artifact Signing) | C22: 0 | D22: 0 | E22: 0 | F22: 0 | G22: 0 | H22: 0 | I22: 0 | J22: 0 | K22: 0 | L22: 0 | M22: 0 | N22: 0 | O22: 0 | P22: 1 | Q22: 0 | R22: 0 | S22: 0 | T22: 0 | U22: 0 | V22: 0 | W22: 0 | X22: 0 | Y22: 0 | Z22: 0 | AA22: 0 | AB22: 0 | AC22: 0 | AD22: 0 | AE22: 0 | AF22: 0 | AG22: 0 | AH22: 0 | AI22: 0 | AJ22: 0 | AK22: 0 | AL22: 0 | AM22: 0 | AN22: 0 | AO22: 0 | AP22: 0 | AQ22: 0 | AS22: =IF(SUM('03_Colocation_Calc'!$T$22:$AC$22)>0,1,0)
A23: syft | B23: Syft / CycloneDX CLI (SBOM Generation) | C23: 0 | D23: 0 | E23: 0 | F23: 0 | G23: 0 | H23: 0 | I23: 0 | J23: 0 | K23: 0 | L23: 0 | M23: 0 | N23: 0 | O23: 0 | P23: 0 | Q23: 0 | R23: 0 | S23: 0 | T23: 0 | U23: 0 | V23: 0 | W23: 0 | X23: 1 | Y23: 0 | Z23: 0 | AA23: 0 | AB23: 0 | AC23: 0 | AD23: 0 | AE23: 0 | AF23: 0 | AG23: 0 | AH23: 0 | AI23: 0 | AJ23: 0 | AK23: 0 | AL23: 0 | AM23: 0 | AN23: 0 | AO23: 0 | AP23: 0 | AQ23: 0 | AS23: =IF(SUM('03_Colocation_Calc'!$T$23:$AC$23)>0,1,0)
A24: unit-test-runner | B24: pytest / Jest / JUnit / Go test (Unit Test) | C24: 0 | D24: 0 | E24: 0 | F24: 0 | G24: 0 | H24: 0 | I24: 0 | J24: 0 | K24: 1 | L24: 0 | M24: 0 | N24: 0 | O24: 0 | P24: 0 | Q24: 1 | R24: 0 | S24: 0 | T24: 0 | U24: 0 | V24: 0 | W24: 0 | X24: 0 | Y24: 0 | Z24: 0 | AA24: 0 | AB24: 0 | AC24: 0 | AD24: 0 | AE24: 0 | AF24: 0 | AG24: 0 | AH24: 0 | AI24: 0 | AJ24: 0 | AK24: 0 | AL24: 0 | AM24: 0 | AN24: 0 | AO24: 0 | AP24: 0 | AQ24: 0 | AS24: =IF(SUM('03_Colocation_Calc'!$T$24:$AC$24)>0,1,0)
A25: testcontainers | B25: Testcontainers / WireMock / Pact (Integration Test) | C25: 0 | D25: 0 | E25: 0 | F25: 0 | G25: 0 | H25: 0 | I25: 0 | J25: 0 | K25: 0 | L25: 0 | M25: 0 | N25: 0 | O25: 0 | P25: 0 | Q25: 0 | R25: 1 | S25: 0 | T25: 0 | U25: 0 | V25: 0 | W25: 0 | X25: 0 | Y25: 0 | Z25: 0 | AA25: 0 | AB25: 0 | AC25: 0 | AD25: 0 | AE25: 0 | AF25: 0 | AG25: 0 | AH25: 0 | AI25: 0 | AJ25: 0 | AK25: 0 | AL25: 0 | AM25: 0 | AN25: 0 | AO25: 0 | AP25: 0 | AQ25: 0 | AS25: =IF(SUM('03_Colocation_Calc'!$T$25:$AC$25)>0,1,0)
A26: owasp-zap | B26: OWASP ZAP (DAST + API Security) | C26: 0 | D26: 0 | E26: 0 | F26: 0 | G26: 0 | H26: 0 | I26: 0 | J26: 0 | K26: 0 | L26: 0 | M26: 0 | N26: 0 | O26: 0 | P26: 0 | Q26: 0 | R26: 0 | S26: 1 | T26: 1 | U26: 0 | V26: 0 | W26: 0 | X26: 0 | Y26: 0 | Z26: 0 | AA26: 0 | AB26: 0 | AC26: 0 | AD26: 0 | AE26: 0 | AF26: 0 | AG26: 0 | AH26: 0 | AI26: 0 | AJ26: 0 | AK26: 0 | AL26: 0 | AM26: 0 | AN26: 0 | AO26: 0 | AP26: 1 | AQ26: 0 | AS26: =IF(SUM('03_Colocation_Calc'!$T$26:$AC$26)>0,1,0)
A27: nuclei | B27: Nuclei (Template-based Vulnerability Scan) | C27: 0 | D27: 0 | E27: 0 | F27: 0 | G27: 0 | H27: 0 | I27: 0 | J27: 0 | K27: 0 | L27: 0 | M27: 0 | N27: 0 | O27: 0 | P27: 0 | Q27: 0 | R27: 0 | S27: 1 | T27: 1 | U27: 0 | V27: 0 | W27: 0 | X27: 0 | Y27: 0 | Z27: 0 | AA27: 0 | AB27: 0 | AC27: 0 | AD27: 0 | AE27: 0 | AF27: 0 | AG27: 0 | AH27: 0 | AI27: 0 | AJ27: 1 | AK27: 0 | AL27: 0 | AM27: 0 | AN27: 0 | AO27: 0 | AP27: 1 | AQ27: 0 | AS27: =IF(SUM('03_Colocation_Calc'!$T$27:$AC$27)>0,1,0)
A28: locust | B28: Locust (Performance / Load Test) | C28: 0 | D28: 0 | E28: 0 | F28: 0 | G28: 0 | H28: 0 | I28: 0 | J28: 0 | K28: 0 | L28: 0 | M28: 0 | N28: 0 | O28: 0 | P28: 0 | Q28: 0 | R28: 0 | S28: 0 | T28: 0 | U28: 1 | V28: 0 | W28: 0 | X28: 0 | Y28: 0 | Z28: 0 | AA28: 0 | AB28: 0 | AC28: 0 | AD28: 0 | AE28: 0 | AF28: 0 | AG28: 0 | AH28: 0 | AI28: 0 | AJ28: 0 | AK28: 0 | AL28: 0 | AM28: 0 | AN28: 0 | AO28: 0 | AP28: 0 | AQ28: 0 | AS28: =IF(SUM('03_Colocation_Calc'!$T$28:$AC$28)>0,1,0)
A29: playwright-a11y | B29: Playwright + axe-core / pa11y-ci / Lighthouse CI (Accessibility) | C29: 0 | D29: 0 | E29: 0 | F29: 0 | G29: 0 | H29: 0 | I29: 0 | J29: 0 | K29: 0 | L29: 0 | M29: 0 | N29: 0 | O29: 0 | P29: 0 | Q29: 0 | R29: 1 | S29: 0 | T29: 0 | U29: 0 | V29: 0 | W29: 0 | X29: 0 | Y29: 0 | Z29: 0 | AA29: 0 | AB29: 0 | AC29: 0 | AD29: 0 | AE29: 0 | AF29: 0 | AG29: 0 | AH29: 0 | AI29: 0 | AJ29: 0 | AK29: 1 | AL29: 0 | AM29: 0 | AN29: 0 | AO29: 0 | AP29: 0 | AQ29: 0 | AS29: =IF(SUM('03_Colocation_Calc'!$T$29:$AC$29)>0,1,0)
A30: testssl | B30: testssl.sh / sslyze / CBOMkit (TLS + Crypto Inventory) | C30: 0 | D30: 0 | E30: 0 | F30: 0 | G30: 0 | H30: 0 | I30: 0 | J30: 0 | K30: 0 | L30: 0 | M30: 0 | N30: 0 | O30: 0 | P30: 0 | Q30: 0 | R30: 0 | S30: 0 | T30: 0 | U30: 0 | V30: 0 | W30: 0 | X30: 0 | Y30: 0 | Z30: 0 | AA30: 0 | AB30: 0 | AC30: 0 | AD30: 0 | AE30: 0 | AF30: 0 | AG30: 0 | AH30: 0 | AI30: 0 | AJ30: 1 | AK30: 0 | AL30: 0 | AM30: 0 | AN30: 0 | AO30: 1 | AP30: 0 | AQ30: 0 | AS30: =IF(SUM('03_Colocation_Calc'!$T$30:$AC$30)>0,1,0)
A31: harbor | B31: Harbor (Private Container Registry, CNCF Graduated) | C31: 0 | D31: 0 | E31: 0 | F31: 0 | G31: 0 | H31: 0 | I31: 0 | J31: 0 | K31: 0 | L31: 0 | M31: 0 | N31: 1 | O31: 0 | P31: 1 | Q31: 0 | R31: 0 | S31: 0 | T31: 0 | U31: 0 | V31: 1 | W31: 1 | X31: 0 | Y31: 1 | Z31: 0 | AA31: 0 | AB31: 0 | AC31: 0 | AD31: 0 | AE31: 0 | AF31: 0 | AG31: 0 | AH31: 0 | AI31: 0 | AJ31: 0 | AK31: 0 | AL31: 0 | AM31: 0 | AN31: 0 | AO31: 0 | AP31: 0 | AQ31: 0 | AS31: =IF(SUM('03_Colocation_Calc'!$T$31:$AC$31)>0,1,0)
A32: minio | B32: MinIO (S3-compatible Object Storage) | C32: 0 | D32: 0 | E32: 0 | F32: 0 | G32: 0 | H32: 0 | I32: 0 | J32: 0 | K32: 0 | L32: 0 | M32: 0 | N32: 0 | O32: 0 | P32: 0 | Q32: 0 | R32: 0 | S32: 0 | T32: 0 | U32: 0 | V32: 1 | W32: 0 | X32: 0 | Y32: 1 | Z32: 0 | AA32: 0 | AB32: 0 | AC32: 0 | AD32: 0 | AE32: 0 | AF32: 0 | AG32: 0 | AH32: 0 | AI32: 0 | AJ32: 0 | AK32: 0 | AL32: 0 | AM32: 1 | AN32: 0 | AO32: 0 | AP32: 0 | AQ32: 0 | AS32: =IF(SUM('03_Colocation_Calc'!$T$32:$AC$32)>0,1,0)
A33: elasticsearch | B33: Elasticsearch (Log / Audit Trail Index) | C33: 0 | D33: 0 | E33: 0 | F33: 0 | G33: 0 | H33: 0 | I33: 0 | J33: 0 | K33: 0 | L33: 0 | M33: 0 | N33: 0 | O33: 0 | P33: 0 | Q33: 0 | R33: 0 | S33: 0 | T33: 0 | U33: 0 | V33: 0 | W33: 0 | X33: 0 | Y33: 1 | Z33: 1 | AA33: 1 | AB33: 0 | AC33: 0 | AD33: 0 | AE33: 0 | AF33: 0 | AG33: 0 | AH33: 0 | AI33: 0 | AJ33: 0 | AK33: 0 | AL33: 0 | AM33: 0 | AN33: 0 | AO33: 0 | AP33: 0 | AQ33: 0 | AS33: =IF(SUM('03_Colocation_Calc'!$T$33:$AC$33)>0,1,0)
A34: logstash | B34: Logstash (Log Pipeline / Parser) | C34: 0 | D34: 0 | E34: 0 | F34: 0 | G34: 0 | H34: 0 | I34: 0 | J34: 0 | K34: 0 | L34: 0 | M34: 0 | N34: 0 | O34: 0 | P34: 0 | Q34: 0 | R34: 0 | S34: 0 | T34: 0 | U34: 0 | V34: 0 | W34: 0 | X34: 0 | Y34: 0 | Z34: 1 | AA34: 0 | AB34: 0 | AC34: 0 | AD34: 0 | AE34: 0 | AF34: 0 | AG34: 0 | AH34: 0 | AI34: 0 | AJ34: 0 | AK34: 0 | AL34: 0 | AM34: 0 | AN34: 0 | AO34: 0 | AP34: 0 | AQ34: 0 | AS34: =IF(SUM('03_Colocation_Calc'!$T$34:$AC$34)>0,1,0)
A35: kibana | B35: Kibana (Log Visualization / Audit Review) | C35: 0 | D35: 0 | E35: 0 | F35: 0 | G35: 0 | H35: 0 | I35: 0 | J35: 0 | K35: 0 | L35: 0 | M35: 0 | N35: 0 | O35: 0 | P35: 0 | Q35: 0 | R35: 0 | S35: 0 | T35: 0 | U35: 0 | V35: 0 | W35: 0 | X35: 0 | Y35: 1 | Z35: 1 | AA35: 1 | AB35: 0 | AC35: 0 | AD35: 0 | AE35: 0 | AF35: 0 | AG35: 0 | AH35: 0 | AI35: 0 | AJ35: 0 | AK35: 0 | AL35: 0 | AM35: 0 | AN35: 0 | AO35: 0 | AP35: 0 | AQ35: 0 | AS35: =IF(SUM('03_Colocation_Calc'!$T$35:$AC$35)>0,1,0)
A36: filebeat | B36: Filebeat (Log Shipper ต่อเครื่อง) | C36: 0 | D36: 0 | E36: 0 | F36: 0 | G36: 0 | H36: 0 | I36: 0 | J36: 0 | K36: 0 | L36: 0 | M36: 0 | N36: 0 | O36: 0 | P36: 0 | Q36: 0 | R36: 0 | S36: 0 | T36: 0 | U36: 0 | V36: 0 | W36: 0 | X36: 0 | Y36: 0 | Z36: 1 | AA36: 0 | AB36: 0 | AC36: 0 | AD36: 0 | AE36: 0 | AF36: 0 | AG36: 0 | AH36: 0 | AI36: 0 | AJ36: 0 | AK36: 0 | AL36: 0 | AM36: 0 | AN36: 0 | AO36: 0 | AP36: 0 | AQ36: 0 | AS36: =IF(SUM('03_Colocation_Calc'!$T$36:$AC$36)>0,1,0)
A37: wazuh | B37: Wazuh (SIEM / HIDS + Alerting) | C37: 0 | D37: 0 | E37: 0 | F37: 0 | G37: 0 | H37: 0 | I37: 0 | J37: 0 | K37: 0 | L37: 0 | M37: 0 | N37: 0 | O37: 0 | P37: 0 | Q37: 0 | R37: 0 | S37: 0 | T37: 0 | U37: 0 | V37: 0 | W37: 0 | X37: 0 | Y37: 1 | Z37: 1 | AA37: 1 | AB37: 0 | AC37: 0 | AD37: 0 | AE37: 1 | AF37: 0 | AG37: 0 | AH37: 1 | AI37: 0 | AJ37: 0 | AK37: 0 | AL37: 0 | AM37: 0 | AN37: 0 | AO37: 0 | AP37: 0 | AQ37: 0 | AS37: =IF(SUM('03_Colocation_Calc'!$T$37:$AC$37)>0,1,0)
A38: vault | B38: HashiCorp Vault / OpenBao (Secret Management) | C38: 0 | D38: 0 | E38: 0 | F38: 0 | G38: 0 | H38: 0 | I38: 0 | J38: 0 | K38: 0 | L38: 0 | M38: 0 | N38: 0 | O38: 0 | P38: 0 | Q38: 0 | R38: 0 | S38: 0 | T38: 0 | U38: 0 | V38: 0 | W38: 0 | X38: 0 | Y38: 1 | Z38: 0 | AA38: 0 | AB38: 0 | AC38: 0 | AD38: 0 | AE38: 0 | AF38: 0 | AG38: 1 | AH38: 0 | AI38: 0 | AJ38: 0 | AK38: 0 | AL38: 0 | AM38: 0 | AN38: 1 | AO38: 0 | AP38: 0 | AQ38: 0 | AS38: =IF(SUM('03_Colocation_Calc'!$T$38:$AC$38)>0,1,0)
A39: k3s-control | B39: Kubernetes / K3s Control Plane (ต่อ 1 Node) | C39: 0 | D39: 0 | E39: 0 | F39: 0 | G39: 0 | H39: 0 | I39: 0 | J39: 0 | K39: 0 | L39: 0 | M39: 0 | N39: 0 | O39: 0 | P39: 0 | Q39: 0 | R39: 0 | S39: 0 | T39: 0 | U39: 0 | V39: 0 | W39: 0 | X39: 0 | Y39: 0 | Z39: 0 | AA39: 0 | AB39: 0 | AC39: 1 | AD39: 1 | AE39: 0 | AF39: 0 | AG39: 0 | AH39: 0 | AI39: 0 | AJ39: 0 | AK39: 0 | AL39: 0 | AM39: 0 | AN39: 1 | AO39: 0 | AP39: 0 | AQ39: 0 | AS39: =IF(SUM('03_Colocation_Calc'!$T$39:$AC$39)>0,1,0)
A40: argocd | B40: Argo CD / Flux (GitOps Continuous Delivery) | C40: 0 | D40: 0 | E40: 0 | F40: 0 | G40: 0 | H40: 0 | I40: 0 | J40: 0 | K40: 0 | L40: 0 | M40: 0 | N40: 0 | O40: 0 | P40: 0 | Q40: 0 | R40: 0 | S40: 0 | T40: 0 | U40: 0 | V40: 0 | W40: 1 | X40: 0 | Y40: 1 | Z40: 0 | AA40: 0 | AB40: 1 | AC40: 1 | AD40: 0 | AE40: 0 | AF40: 0 | AG40: 0 | AH40: 0 | AI40: 0 | AJ40: 0 | AK40: 0 | AL40: 0 | AM40: 0 | AN40: 0 | AO40: 0 | AP40: 0 | AQ40: 0 | AS40: =IF(SUM('03_Colocation_Calc'!$T$40:$AC$40)>0,1,0)
A41: falco | B41: Falco (Runtime Security Monitoring, ต่อ Node) | C41: 0 | D41: 0 | E41: 0 | F41: 0 | G41: 0 | H41: 0 | I41: 0 | J41: 0 | K41: 0 | L41: 0 | M41: 0 | N41: 0 | O41: 0 | P41: 0 | Q41: 0 | R41: 0 | S41: 0 | T41: 0 | U41: 0 | V41: 0 | W41: 0 | X41: 0 | Y41: 0 | Z41: 0 | AA41: 1 | AB41: 0 | AC41: 0 | AD41: 0 | AE41: 1 | AF41: 0 | AG41: 0 | AH41: 0 | AI41: 0 | AJ41: 0 | AK41: 0 | AL41: 0 | AM41: 0 | AN41: 0 | AO41: 0 | AP41: 0 | AQ41: 0 | AS41: =IF(SUM('03_Colocation_Calc'!$T$41:$AC$41)>0,1,0)
A42: prometheus | B42: Prometheus (Metrics & Alerting) | C42: 0 | D42: 0 | E42: 0 | F42: 0 | G42: 0 | H42: 0 | I42: 0 | J42: 0 | K42: 0 | L42: 0 | M42: 0 | N42: 0 | O42: 0 | P42: 0 | Q42: 0 | R42: 0 | S42: 0 | T42: 0 | U42: 0 | V42: 0 | W42: 0 | X42: 0 | Y42: 0 | Z42: 0 | AA42: 1 | AB42: 0 | AC42: 0 | AD42: 0 | AE42: 0 | AF42: 1 | AG42: 0 | AH42: 0 | AI42: 0 | AJ42: 0 | AK42: 0 | AL42: 0 | AM42: 0 | AN42: 0 | AO42: 0 | AP42: 0 | AQ42: 1 | AS42: =IF(SUM('03_Colocation_Calc'!$T$42:$AC$42)>0,1,0)
A43: grafana | B43: Grafana (Dashboard) | C43: 0 | D43: 0 | E43: 0 | F43: 0 | G43: 0 | H43: 0 | I43: 0 | J43: 0 | K43: 0 | L43: 0 | M43: 0 | N43: 0 | O43: 0 | P43: 0 | Q43: 0 | R43: 0 | S43: 0 | T43: 0 | U43: 0 | V43: 0 | W43: 0 | X43: 0 | Y43: 0 | Z43: 0 | AA43: 0 | AB43: 0 | AC43: 0 | AD43: 0 | AE43: 0 | AF43: 1 | AG43: 0 | AH43: 0 | AI43: 0 | AJ43: 0 | AK43: 0 | AL43: 0 | AM43: 0 | AN43: 0 | AO43: 0 | AP43: 0 | AQ43: 0 | AS43: =IF(SUM('03_Colocation_Calc'!$T$43:$AC$43)>0,1,0)
A44: zabbix | B44: Zabbix Server (Infrastructure Monitoring) | C44: 0 | D44: 0 | E44: 0 | F44: 0 | G44: 0 | H44: 0 | I44: 0 | J44: 0 | K44: 0 | L44: 0 | M44: 0 | N44: 0 | O44: 0 | P44: 0 | Q44: 0 | R44: 0 | S44: 0 | T44: 0 | U44: 0 | V44: 0 | W44: 0 | X44: 0 | Y44: 0 | Z44: 0 | AA44: 1 | AB44: 0 | AC44: 0 | AD44: 0 | AE44: 0 | AF44: 1 | AG44: 0 | AH44: 0 | AI44: 0 | AJ44: 0 | AK44: 0 | AL44: 0 | AM44: 0 | AN44: 0 | AO44: 0 | AP44: 0 | AQ44: 1 | AS44: =IF(SUM('03_Colocation_Calc'!$T$44:$AC$44)>0,1,0)
A45: ansible-chef | B45: Ansible / Chef Client (Config Management & Hardening) | C45: 0 | D45: 0 | E45: 0 | F45: 0 | G45: 0 | H45: 0 | I45: 0 | J45: 0 | K45: 0 | L45: 0 | M45: 0 | N45: 0 | O45: 1 | P45: 0 | Q45: 0 | R45: 0 | S45: 0 | T45: 0 | U45: 0 | V45: 0 | W45: 0 | X45: 0 | Y45: 0 | Z45: 0 | AA45: 0 | AB45: 0 | AC45: 0 | AD45: 0 | AE45: 0 | AF45: 0 | AG45: 0 | AH45: 1 | AI45: 0 | AJ45: 0 | AK45: 0 | AL45: 0 | AM45: 1 | AN45: 0 | AO45: 0 | AP45: 0 | AQ45: 0 | AS45: =IF(SUM('03_Colocation_Calc'!$T$45:$AC$45)>0,1,0)
A46: modsecurity | B46: ModSecurity / Coraza (Web Application Firewall) | C46: 0 | D46: 0 | E46: 0 | F46: 0 | G46: 0 | H46: 0 | I46: 0 | J46: 0 | K46: 0 | L46: 0 | M46: 0 | N46: 0 | O46: 0 | P46: 0 | Q46: 0 | R46: 0 | S46: 0 | T46: 0 | U46: 0 | V46: 0 | W46: 0 | X46: 0 | Y46: 0 | Z46: 0 | AA46: 0 | AB46: 0 | AC46: 0 | AD46: 0 | AE46: 0 | AF46: 0 | AG46: 0 | AH46: 0 | AI46: 1 | AJ46: 1 | AK46: 0 | AL46: 0 | AM46: 0 | AN46: 0 | AO46: 0 | AP46: 0 | AQ46: 0 | AS46: =IF(SUM('03_Colocation_Calc'!$T$46:$AC$46)>0,1,0)
A47: keycloak | B47: Keycloak (SSO / MFA / Identity) | C47: 0 | D47: 0 | E47: 0 | F47: 0 | G47: 0 | H47: 0 | I47: 0 | J47: 0 | K47: 0 | L47: 0 | M47: 0 | N47: 0 | O47: 0 | P47: 0 | Q47: 0 | R47: 0 | S47: 0 | T47: 0 | U47: 0 | V47: 0 | W47: 0 | X47: 0 | Y47: 1 | Z47: 0 | AA47: 0 | AB47: 0 | AC47: 0 | AD47: 0 | AE47: 0 | AF47: 0 | AG47: 0 | AH47: 0 | AI47: 0 | AJ47: 0 | AK47: 0 | AL47: 0 | AM47: 0 | AN47: 1 | AO47: 0 | AP47: 0 | AQ47: 0 | AS47: =IF(SUM('03_Colocation_Calc'!$T$47:$AC$47)>0,1,0)
A48: velero-restic | B48: Velero / restic / pgBackRest (Backup & DR) | C48: 0 | D48: 0 | E48: 0 | F48: 0 | G48: 0 | H48: 0 | I48: 0 | J48: 0 | K48: 0 | L48: 0 | M48: 0 | N48: 0 | O48: 0 | P48: 0 | Q48: 0 | R48: 0 | S48: 0 | T48: 0 | U48: 0 | V48: 0 | W48: 0 | X48: 0 | Y48: 0 | Z48: 0 | AA48: 0 | AB48: 0 | AC48: 0 | AD48: 0 | AE48: 0 | AF48: 0 | AG48: 0 | AH48: 0 | AI48: 0 | AJ48: 0 | AK48: 0 | AL48: 0 | AM48: 1 | AN48: 0 | AO48: 0 | AP48: 0 | AQ48: 0 | AS48: =IF(SUM('03_Colocation_Calc'!$T$48:$AC$48)>0,1,0)
A49: prowler | B49: Prowler / ScoutSuite (Cloud & Infra Posture Scan) | C49: 0 | D49: 0 | E49: 0 | F49: 0 | G49: 0 | H49: 0 | I49: 0 | J49: 0 | K49: 0 | L49: 0 | M49: 0 | N49: 0 | O49: 1 | P49: 0 | Q49: 0 | R49: 0 | S49: 0 | T49: 0 | U49: 0 | V49: 0 | W49: 0 | X49: 0 | Y49: 0 | Z49: 0 | AA49: 0 | AB49: 0 | AC49: 0 | AD49: 0 | AE49: 0 | AF49: 0 | AG49: 0 | AH49: 1 | AI49: 0 | AJ49: 0 | AK49: 0 | AL49: 1 | AM49: 0 | AN49: 0 | AO49: 0 | AP49: 0 | AQ49: 0 | AS49: =IF(SUM('03_Colocation_Calc'!$T$49:$AC$49)>0,1,0)
